Workbook

Sheet Executive Report
A1: JANVI AIKA - EXECUTIVE ORDER ANALYSIS REPORT: COD vs. PARTIAL COD vs. PREPAID ORDERS
A3: Comprehensive Performance Evaluation, Delivery Realization, RTO Risk Assessment & Strategic Action Plan
A5: 1. EXECUTIVE KPI SUMMARY
A6: TOTAL ORDERS | C6: TOTAL GROSS REVENUE | E6: NET DELIVERED REVENUE | G6: DELIVERY SUCCESS RATE | I6: COD RTO REVENUE LOSS | K6: COD FAILURE RATE
A7: =COUNT(Master_Orders!A2:A174) | C7: =SUM(Master_Orders!E2:E174) | E7: =SUMIF(Master_Orders!K2:K174, "Delivered", Master_Orders!E2:E174) | G7: =COUNTIF(Master_Orders!K2:K174, "Delivered")/COUNT(Master_Orders!A2:A174) | I7: =SUMIFS(Master_Orders!E2:E174, Master_Orders!J2:J174, "COD", Master_Orders!K2:K174, "RTO / Returned") | K7: =(COUNTIFS(Master_Orders!J2:J174, "COD", Master_Orders!K2:K174, "RTO / Returned") + COUNTIFS(Master_Orders!J2:J174, "COD", Master_Orders!K2:K174, "Canceled")) / COUNTIF(Master_Orders!J2:J174, "COD")
A9: 2. PAYMENT CATEGORY COMPARATIVE REALIZATION MATRIX
A10: Payment Category | B10: Total Orders | C10: Order Share % | D10: Gross Revenue (Rs.) | E10: Revenue Share % | F10: AOV (Rs.) | G10: Delivered Count | H10: Delivered Net Rev (Rs.) | I10: RTO Count | J10: RTO Rate % | K10: RTO Rev at Risk (Rs.) | L10: Canceled Count | M10: Overall Failure Rate %
A11: Cash on Delivery (COD) | B11: =COUNTIF(Master_Orders!J2:J174, "COD") | C11: =B11/B14 | D11: =SUMIF(Master_Orders!J2:J174, "COD", Master_Orders!E2:E174) | E11: =D11/D14 | F11: =D11/B11 | G11: =COUNTIFS(Master_Orders!J2:J174, "COD", Master_Orders!K2:K174, "Delivered") | H11: =SUMIFS(Master_Orders!E2:E174, Master_Orders!J2:J174, "COD", Master_Orders!K2:K174, "Delivered") | I11: =COUNTIFS(Master_Orders!J2:J174, "COD", Master_Orders!K2:K174, "RTO / Returned") | J11: =I11/B11 | K11: =SUMIFS(Master_Orders!E2:E174, Master_Orders!J2:J174, "COD", Master_Orders!K2:K174, "RTO / Returned") | L11: =COUNTIFS(Master_Orders!J2:J174, "COD", Master_Orders!K2:K174, "Canceled") | M11: =(I11+L11)/B11
A12: Partial COD | B12: =COUNTIF(Master_Orders!J2:J174, "Partial COD") | C12: =B12/B14 | D12: =SUMIF(Master_Orders!J2:J174, "Partial COD", Master_Orders!E2:E174) | E12: =D12/D14 | F12: =D12/B12 | G12: =COUNTIFS(Master_Orders!J2:J174, "Partial COD", Master_Orders!K2:K174, "Delivered") | H12: =SUMIFS(Master_Orders!E2:E174, Master_Orders!J2:J174, "Partial COD", Master_Orders!K2:K174, "Delivered") | I12: =COUNTIFS(Master_Orders!J2:J174, "Partial COD", Master_Orders!K2:K174, "RTO / Returned") | J12: =I12/B12 | K12: =SUMIFS(Master_Orders!E2:E174, Master_Orders!J2:J174, "Partial COD", Master_Orders!K2:K174, "RTO / Returned") | L12: =COUNTIFS(Master_Orders!J2:J174, "Partial COD", Master_Orders!K2:K174, "Canceled") | M12: =(I12+L12)/B12
A13: Prepaid (Razorpay / UPI / Cards) | B13: =COUNTIF(Master_Orders!J2:J174, "Prepaid") | C13: =B13/B14 | D13: =SUMIF(Master_Orders!J2:J174, "Prepaid", Master_Orders!E2:E174) | E13: =D13/D14 | F13: =D13/B13 | G13: =COUNTIFS(Master_Orders!J2:J174, "Prepaid", Master_Orders!K2:K174, "Delivered") | H13: =SUMIFS(Master_Orders!E2:E174, Master_Orders!J2:J174, "Prepaid", Master_Orders!K2:K174, "Delivered") | I13: =COUNTIFS(Master_Orders!J2:J174, "Prepaid", Master_Orders!K2:K174, "RTO / Returned") | J13: =I13/B13 | K13: =SUMIFS(Master_Orders!E2:E174, Master_Orders!J2:J174, "Prepaid", Master_Orders!K2:K174, "RTO / Returned") | L13: =COUNTIFS(Master_Orders!J2:J174, "Prepaid", Master_Orders!K2:K174, "Canceled") | M13: =(I13+L13)/B13
A14: Total Portfolio / Combined | B14: =SUM(B11:B13) | C14: =SUM(C11:C13) | D14: =SUM(D11:D13) | E14: =SUM(E11:E13) | F14: =D14/B14 | G14: =SUM(G11:G13) | H14: =SUM(H11:H13) | I14: =SUM(I11:I13) | J14: =I14/B14 | K14: =SUM(K11:K13) | L14: =SUM(L11:L13) | M14: =(I14+L14)/B14
A16: 3. GEOGRAPHIC DISTRIBUTION & TOP DEMAND REGIONS
A17: Payment Category | B17: Top State #1 | C17: Top State #2 | D17: Top State #3 | E17: Top State #4 | F17: Demand Concentration
A18: Prepaid | B18: Tamil Nadu (58 orders) | C18: Andhra Pradesh (15 orders) | D18: Telangana (13 orders) | E18: Karnataka (11 orders) | F18: High concentration in South Metro & Tier-1 cities
A19: Cash on Delivery (COD) | B19: Tamil Nadu (30 orders) | C19: Telangana (8 orders) | D19: Karnataka (6 orders) | E19: Andhra Pradesh (4 orders) | F19: Tier-2/3 pincodes in TN and TS show high RTO rates
A20: Partial COD | B20: Telangana (4 orders) | C20: Tamil Nadu (3 orders) | D20: Maharashtra (3 orders) | E20: Kerala (1 order) | F20: Strong acceptance in urban hubs looking for intent verification
A22: 4. STRATEGIC RECOMMENDATIONS & ACTION PLAN
A23: Pillar / Focus Area | B23: Current Issue / Risk | C23: Proposed Action / Strategic Policy | D23: Expected Impact & Result
A24: Mandatory Partial COD | B24: Pure COD incurs 25% RTO rate and Rs. 18.5k in locked inventory | C24: Enforce Rs. 150-Rs. 200 non-refundable advance deposit for all COD checkouts | D24: Eliminates non-serious orders; reduces RTO to < 2% (matching Partial COD 0% RTO)
A25: Prepaid Discount Incentives | B25: 30% of buyers select COD due to lack of immediate checkout incentive | C25: Offer 5% instant discount or free gift for UPI / Razorpay checkout | D25: Shifts ~40% of prospective COD orders to Prepaid, locking in instant cashflow
A26: Automated NDR Verification | B26: Doorstep refusal due to buyer absence or impulse cancellation | C26: Implement automated WhatsApp order verification prior to Shiprocket manifest | D26: Prevents dispatch of unconfirmed orders; saves forward and return freight costs
A27: Regional Fulfillment Hubs | B27: 80%+ demand is concentrated in South India (TN, TS, AP, KA) | C27: Optimize courier routing via South India express hubs for <48h delivery | D27: Faster transit times directly improve delivery acceptance rate and reduce buyer remorse

Sheet Side_By_Side_Comparison
A1: JANVI AIKA - SIDE-BY-SIDE DAY-WISE COMPARATIVE ANALYSIS: COD vs. PARTIAL COD vs. PREPAID
A3: Order Date | B3: ORDER VOLUME MIX | E3: GROSS REVENUE (Rs.) | H3: DELIVERED ORDERS | K3: RTO / RETURNED ORDERS | N3: Total Daily Rev
B4: COD | C4: Partial COD | D4: Prepaid | E4: COD | F4: Partial COD | G4: Prepaid | H4: COD | I4: Partial COD | J4: Prepaid | K4: COD | L4: Partial COD | M4: Prepaid
A5: 2026-06-22 | B5: =COUNTIFS(Master_Orders!D2:D174, "2026-06-22", Master_Orders!J2:J174, "COD") | C5: =COUNTIFS(Master_Orders!D2:D174, "2026-06-22", Master_Orders!J2:J174, "Partial COD") | D5: =COUNTIFS(Master_Orders!D2:D174, "2026-06-22", Master_Orders!J2:J174, "Prepaid") | E5: =SUMIFS(Master_Orders!E2:E174, Master_Orders!D2:D174, "2026-06-22", Master_Orders!J2:J174, "COD") | F5: =SUMIFS(Master_Orders!E2:E174, Master_Orders!D2:D174, "2026-06-22", Master_Orders!J2:J174, "Partial COD") | G5: =SUMIFS(Master_Orders!E2:E174, Master_Orders!D2:D174, "2026-06-22", Master_Orders!J2:J174, "Prepaid") | H5: =COUNTIFS(Master_Orders!D2:D174, "2026-06-22", Master_Orders!J2:J174, "COD", Master_Orders!K2:K174, "Delivered") | I5: =COUNTIFS(Master_Orders!D2:D174, "2026-06-22", Master_Orders!J2:J174, "Partial COD", Master_Orders!K2:K174, "Delivered") | J5: =COUNTIFS(Master_Orders!D2:D174, "2026-06-22", Master_Orders!J2:J174, "Prepaid", Master_Orders!K2:K174, "Delivered") | K5: =COUNTIFS(Master_Orders!D2:D174, "2026-06-22", Master_Orders!J2:J174, "COD", Master_Orders!K2:K174, "RTO / Returned") | L5: =COUNTIFS(Master_Orders!D2:D174, "2026-06-22", Master_Orders!J2:J174, "Partial COD", Master_Orders!K2:K174, "RTO / Returned") | M5: =COUNTIFS(Master_Orders!D2:D174, "2026-06-22", Master_Orders!J2:J174, "Prepaid", Master_Orders!K2:K174, "RTO / Returned") | N5: =E5+F5+G5
A6: 2026-06-24 | B6: =COUNTIFS(Master_Orders!D2:D174, "2026-06-24", Master_Orders!J2:J174, "COD") | C6: =COUNTIFS(Master_Orders!D2:D174, "2026-06-24", Master_Orders!J2:J174, "Partial COD") | D6: =COUNTIFS(Master_Orders!D2:D174, "2026-06-24", Master_Orders!J2:J174, "Prepaid") | E6: =SUMIFS(Master_Orders!E2:E174, Master_Orders!D2:D174, "2026-06-24", Master_Orders!J2:J174, "COD") | F6: =SUMIFS(Master_Orders!E2:E174, Master_Orders!D2:D174, "2026-06-24", Master_Orders!J2:J174, "Partial COD") | G6: =SUMIFS(Master_Orders!E2:E174, Master_Orders!D2:D174, "2026-06-24", Master_Orders!J2:J174, "Prepaid") | H6: =COUNTIFS(Master_Orders!D2:D174, "2026-06-24", Master_Orders!J2:J174, "COD", Master_Orders!K2:K174, "Delivered") | I6: =COUNTIFS(Master_Orders!D2:D174, "2026-06-24", Master_Orders!J2:J174, "Partial COD", Master_Orders!K2:K174, "Delivered") | J6: =COUNTIFS(Master_Orders!D2:D174, "2026-06-24", Master_Orders!J2:J174, "Prepaid", Master_Orders!K2:K174, "Delivered") | K6: =COUNTIFS(Master_Orders!D2:D174, "2026-06-24", Master_Orders!J2:J174, "COD", Master_Orders!K2:K174, "RTO / Returned") | L6: =COUNTIFS(Master_Orders!D2:D174, "2026-06-24", Master_Orders!J2:J174, "Partial COD", Master_Orders!K2:K174, "RTO / Returned") | M6: =COUNTIFS(Master_Orders!D2:D174, "2026-06-24", Master_Orders!J2:J174, "Prepaid", Master_Orders!K2:K174, "RTO / Returned") | N6: =E6+F6+G6
A7: 2026-06-25 | B7: =COUNTIFS(Master_Orders!D2:D174, "2026-06-25", Master_Orders!J2:J174, "COD") | C7: =COUNTIFS(Master_Orders!D2:D174, "2026-06-25", Master_Orders!J2:J174, "Partial COD") | D7: =COUNTIFS(Master_Orders!D2:D174, "2026-06-25", Master_Orders!J2:J174, "Prepaid") | E7: =SUMIFS(Master_Orders!E2:E174, Master_Orders!D2:D174, "2026-06-25", Master_Orders!J2:J174, "COD") | F7: =SUMIFS(Master_Orders!E2:E174, Master_Orders!D2:D174, "2026-06-25", Master_Orders!J2:J174, "Partial COD") | G7: =SUMIFS(Master_Orders!E2:E174, Master_Orders!D2:D174, "2026-06-25", Master_Orders!J2:J174, "Prepaid") | H7: =COUNTIFS(Master_Orders!D2:D174, "2026-06-25", Master_Orders!J2:J174, "COD", Master_Orders!K2:K174, "Delivered") | I7: =COUNTIFS(Master_Orders!D2:D174, "2026-06-25", Master_Orders!J2:J174, "Partial COD", Master_Orders!K2:K174, "Delivered") | J7: =COUNTIFS(Master_Orders!D2:D174, "2026-06-25", Master_Orders!J2:J174, "Prepaid", Master_Orders!K2:K174, "Delivered") | K7: =COUNTIFS(Master_Orders!D2:D174, "2026-06-25", Master_Orders!J2:J174, "COD", Master_Orders!K2:K174, "RTO / Returned") | L7: =COUNTIFS(Master_Orders!D2:D174, "2026-06-25", Master_Orders!J2:J174, "Partial COD", Master_Orders!K2:K174, "RTO / Returned") | M7: =COUNTIFS(Master_Orders!D2:D174, "2026-06-25", Master_Orders!J2:J174, "Prepaid", Master_Orders!K2:K174, "RTO / Returned") | N7: =E7+F7+G7
A8: 2026-06-27 | B8: =COUNTIFS(Master_Orders!D2:D174, "2026-06-27", Master_Orders!J2:J174, "COD") | C8: =COUNTIFS(Master_Orders!D2:D174, "2026-06-27", Master_Orders!J2:J174, "Partial COD") | D8: =COUNTIFS(Master_Orders!D2:D174, "2026-06-27", Master_Orders!J2:J174, "Prepaid") | E8: =SUMIFS(Master_Orders!E2:E174, Master_Orders!D2:D174, "2026-06-27", Master_Orders!J2:J174, "COD") | F8: =SUMIFS(Master_Orders!E2:E174, Master_Orders!D2:D174, "2026-06-27", Master_Orders!J2:J174, "Partial COD") | G8: =SUMIFS(Master_Orders!E2:E174, Master_Orders!D2:D174, "2026-06-27", Master_Orders!J2:J174, "Prepaid") | H8: =COUNTIFS(Master_Orders!D2:D174, "2026-06-27", Master_Orders!J2:J174, "COD", Master_Orders!K2:K174, "Delivered") | I8: =COUNTIFS(Master_Orders!D2:D174, "2026-06-27", Master_Orders!J2:J174, "Partial COD", Master_Orders!K2:K174, "Delivered") | J8: =COUNTIFS(Master_Orders!D2:D174, "2026-06-27", Master_Orders!J2:J174, "Prepaid", Master_Orders!K2:K174, "Delivered") | K8: =COUNTIFS(Master_Orders!D2:D174, "2026-06-27", Master_Orders!J2:J174, "COD", Master_Orders!K2:K174, "RTO / Returned") | L8: =COUNTIFS(Master_Orders!D2:D174, "2026-06-27", Master_Orders!J2:J174, "Partial COD", Master_Orders!K2:K174, "RTO / Returned") | M8: =COUNTIFS(Master_Orders!D2:D174, "2026-06-27", Master_Orders!J2:J174, "Prepaid", Master_Orders!K2:K174, "RTO / Returned") | N8: =E8+F8+G8
A9: 2026-06-28 | B9: =COUNTIFS(Master_Orders!D2:D174, "2026-06-28", Master_Orders!J2:J174, "COD") | C9: =COUNTIFS(Master_Orders!D2:D174, "2026-06-28", Master_Orders!J2:J174, "Partial COD") | D9: =COUNTIFS(Master_Orders!D2:D174, "2026-06-28", Master_Orders!J2:J174, "Prepaid") | E9: =SUMIFS(Master_Orders!E2:E174, Master_Orders!D2:D174, "2026-06-28", Master_Orders!J2:J174, "COD") | F9: =SUMIFS(Master_Orders!E2:E174, Master_Orders!D2:D174, "2026-06-28", Master_Orders!J2:J174, "Partial COD") | G9: =SUMIFS(Master_Orders!E2:E174, Master_Orders!D2:D174, "2026-06-28", Master_Orders!J2:J174, "Prepaid") | H9: =COUNTIFS(Master_Orders!D2:D174, "2026-06-28", Master_Orders!J2:J174, "COD", Master_Orders!K2:K174, "Delivered") | I9: =COUNTIFS(Master_Orders!D2:D174, "2026-06-28", Master_Orders!J2:J174, "Partial COD", Master_Orders!K2:K174, "Delivered") | J9: =COUNTIFS(Master_Orders!D2:D174, "2026-06-28", Master_Orders!J2:J174, "Prepaid", Master_Orders!K2:K174, "Delivered") | K9: =COUNTIFS(Master_Orders!D2:D174, "2026-06-28", Master_Orders!J2:J174, "COD", Master_Orders!K2:K174, "RTO / Returned") | L9: =COUNTIFS(Master_Orders!D2:D174, "2026-06-28", Master_Orders!J2:J174, "Partial COD", Master_Orders!K2:K174, "RTO / Returned") | M9: =COUNTIFS(Master_Orders!D2:D174, "2026-06-28", Master_Orders!J2:J174, "Prepaid", Master_Orders!K2:K174, "RTO / Returned") | N9: =E9+F9+G9
A10: 2026-06-29 | B10: =COUNTIFS(Master_Orders!D2:D174, "2026-06-29", Master_Orders!J2:J174, "COD") | C10: =COUNTIFS(Master_Orders!D2:D174, "2026-06-29", Master_Orders!J2:J174, "Partial COD") | D10: =COUNTIFS(Master_Orders!D2:D174, "2026-06-29", Master_Orders!J2:J174, "Prepaid") | E10: =SUMIFS(Master_Orders!E2:E174, Master_Orders!D2:D174, "2026-06-29", Master_Orders!J2:J174, "COD") | F10: =SUMIFS(Master_Orders!E2:E174, Master_Orders!D2:D174, "2026-06-29", Master_Orders!J2:J174, "Partial COD") | G10: =SUMIFS(Master_Orders!E2:E174, Master_Orders!D2:D174, "2026-06-29", Master_Orders!J2:J174, "Prepaid") | H10: =COUNTIFS(Master_Orders!D2:D174, "2026-06-29", Master_Orders!J2:J174, "COD", Master_Orders!K2:K174, "Delivered") | I10: =COUNTIFS(Master_Orders!D2:D174, "2026-06-29", Master_Orders!J2:J174, "Partial COD", Master_Orders!K2:K174, "Delivered") | J10: =COUNTIFS(Master_Orders!D2:D174, "2026-06-29", Master_Orders!J2:J174, "Prepaid", Master_Orders!K2:K174, "Delivered") | K10: =COUNTIFS(Master_Orders!D2:D174, "2026-06-29", Master_Orders!J2:J174, "COD", Master_Orders!K2:K174, "RTO / Returned") | L10: =COUNTIFS(Master_Orders!D2:D174, "2026-06-29", Master_Orders!J2:J174, "Partial COD", Master_Orders!K2:K174, "RTO / Returned") | M10: =COUNTIFS(Master_Orders!D2:D174, "2026-06-29", Master_Orders!J2:J174, "Prepaid", Master_Orders!K2:K174, "RTO / Returned") | N10: =E10+F10+G10
A11: 2026-06-30 | B11: =COUNTIFS(Master_Orders!D2:D174, "2026-06-30", Master_Orders!J2:J174, "COD") | C11: =COUNTIFS(Master_Orders!D2:D174, "2026-06-30", Master_Orders!J2:J174, "Partial COD") | D11: =COUNTIFS(Master_Orders!D2:D174, "2026-06-30", Master_Orders!J2:J174, "Prepaid") | E11: =SUMIFS(Master_Orders!E2:E174, Master_Orders!D2:D174, "2026-06-30", Master_Orders!J2:J174, "COD") | F11: =SUMIFS(Master_Orders!E2:E174, Master_Orders!D2:D174, "2026-06-30", Master_Orders!J2:J174, "Partial COD") | G11: =SUMIFS(Master_Orders!E2:E174, Master_Orders!D2:D174, "2026-06-30", Master_Orders!J2:J174, "Prepaid") | H11: =COUNTIFS(Master_Orders!D2:D174, "2026-06-30", Master_Orders!J2:J174, "COD", Master_Orders!K2:K174, "Delivered") | I11: =COUNTIFS(Master_Orders!D2:D174, "2026-06-30", Master_Orders!J2:J174, "Partial COD", Master_Orders!K2:K174, "Delivered") | J11: =COUNTIFS(Master_Orders!D2:D174, "2026-06-30", Master_Orders!J2:J174, "Prepaid", Master_Orders!K2:K174, "Delivered") | K11: =COUNTIFS(Master_Orders!D2:D174, "2026-06-30", Master_Orders!J2:J174, "COD", Master_Orders!K2:K174, "RTO / Returned") | L11: =COUNTIFS(Master_Orders!D2:D174, "2026-06-30", Master_Orders!J2:J174, "Partial COD", Master_Orders!K2:K174, "RTO / Returned") | M11: =COUNTIFS(Master_Orders!D2:D174, "2026-06-30", Master_Orders!J2:J174, "Prepaid", Master_Orders!K2:K174, "RTO / Returned") | N11: =E11+F11+G11
A12: 2026-07-01 | B12: =COUNTIFS(Master_Orders!D2:D174, "2026-07-01", Master_Orders!J2:J174, "COD") | C12: =COUNTIFS(Master_Orders!D2:D174, "2026-07-01", Master_Orders!J2:J174, "Partial COD") | D12: =COUNTIFS(Master_Orders!D2:D174, "2026-07-01", Master_Orders!J2:J174, "Prepaid") | E12: =SUMIFS(Master_Orders!E2:E174, Master_Orders!D2:D174, "2026-07-01", Master_Orders!J2:J174, "COD") | F12: =SUMIFS(Master_Orders!E2:E174, Master_Orders!D2:D174, "2026-07-01", Master_Orders!J2:J174, "Partial COD") | G12: =SUMIFS(Master_Orders!E2:E174, Master_Orders!D2:D174, "2026-07-01", Master_Orders!J2:J174, "Prepaid") | H12: =COUNTIFS(Master_Orders!D2:D174, "2026-07-01", Master_Orders!J2:J174, "COD", Master_Orders!K2:K174, "Delivered") | I12: =COUNTIFS(Master_Orders!D2:D174, "2026-07-01", Master_Orders!J2:J174, "Partial COD", Master_Orders!K2:K174, "Delivered") | J12: =COUNTIFS(Master_Orders!D2:D174, "2026-07-01", Master_Orders!J2:J174, "Prepaid", Master_Orders!K2:K174, "Delivered") | K12: =COUNTIFS(Master_Orders!D2:D174, "2026-07-01", Master_Orders!J2:J174, "COD", Master_Orders!K2:K174, "RTO / Returned") | L12: =COUNTIFS(Master_Orders!D2:D174, "2026-07-01", Master_Orders!J2:J174, "Partial COD", Master_Orders!K2:K174, "RTO / Returned") | M12: =COUNTIFS(Master_Orders!D2:D174, "2026-07-01", Master_Orders!J2:J174, "Prepaid", Master_Orders!K2:K174, "RTO / Returned") | N12: =E12+F12+G12
A13: 2026-07-02 | B13: =COUNTIFS(Master_Orders!D2:D174, "2026-07-02", Master_Orders!J2:J174, "COD") | C13: =COUNTIFS(Master_Orders!D2:D174, "2026-07-02", Master_Orders!J2:J174, "Partial COD") | D13: =COUNTIFS(Master_Orders!D2:D174, "2026-07-02", Master_Orders!J2:J174, "Prepaid") | E13: =SUMIFS(Master_Orders!E2:E174, Master_Orders!D2:D174, "2026-07-02", Master_Orders!J2:J174, "COD") | F13: =SUMIFS(Master_Orders!E2:E174, Master_Orders!D2:D174, "2026-07-02", Master_Orders!J2:J174, "Partial COD") | G13: =SUMIFS(Master_Orders!E2:E174, Master_Orders!D2:D174, "2026-07-02", Master_Orders!J2:J174, "Prepaid") | H13: =COUNTIFS(Master_Orders!D2:D174, "2026-07-02", Master_Orders!J2:J174, "COD", Master_Orders!K2:K174, "Delivered") | I13: =COUNTIFS(Master_Orders!D2:D174, "2026-07-02", Master_Orders!J2:J174, "Partial COD", Master_Orders!K2:K174, "Delivered") | J13: =COUNTIFS(Master_Orders!D2:D174, "2026-07-02", Master_Orders!J2:J174, "Prepaid", Master_Orders!K2:K174, "Delivered") | K13: =COUNTIFS(Master_Orders!D2:D174, "2026-07-02", Master_Orders!J2:J174, "COD", Master_Orders!K2:K174, "RTO / Returned") | L13: =COUNTIFS(Master_Orders!D2:D174, "2026-07-02", Master_Orders!J2:J174, "Partial COD", Master_Orders!K2:K174, "RTO / Returned") | M13: =COUNTIFS(Master_Orders!D2:D174, "2026-07-02", Master_Orders!J2:J174, "Prepaid", Master_Orders!K2:K174, "RTO / Returned") | N13: =E13+F13+G13
A14: 2026-07-03 | B14: =COUNTIFS(Master_Orders!D2:D174, "2026-07-03", Master_Orders!J2:J174, "COD") | C14: =COUNTIFS(Master_Orders!D2:D174, "2026-07-03", Master_Orders!J2:J174, "Partial COD") | D14: =COUNTIFS(Master_Orders!D2:D174, "2026-07-03", Master_Orders!J2:J174, "Prepaid") | E14: =SUMIFS(Master_Orders!E2:E174, Master_Orders!D2:D174, "2026-07-03", Master_Orders!J2:J174, "COD") | F14: =SUMIFS(Master_Orders!E2:E174, Master_Orders!D2:D174, "2026-07-03", Master_Orders!J2:J174, "Partial COD") | G14: =SUMIFS(Master_Orders!E2:E174, Master_Orders!D2:D174, "2026-07-03", Master_Orders!J2:J174, "Prepaid") | H14: =COUNTIFS(Master_Orders!D2:D174, "2026-07-03", Master_Orders!J2:J174, "COD", Master_Orders!K2:K174, "Delivered") | I14: =COUNTIFS(Master_Orders!D2:D174, "2026-07-03", Master_Orders!J2:J174, "Partial COD", Master_Orders!K2:K174, "Delivered") | J14: =COUNTIFS(Master_Orders!D2:D174, "2026-07-03", Master_Orders!J2:J174, "Prepaid", Master_Orders!K2:K174, "Delivered") | K14: =COUNTIFS(Master_Orders!D2:D174, "2026-07-03", Master_Orders!J2:J174, "COD", Master_Orders!K2:K174, "RTO / Returned") | L14: =COUNTIFS(Master_Orders!D2:D174, "2026-07-03", Master_Orders!J2:J174, "Partial COD", Master_Orders!K2:K174, "RTO / Returned") | M14: =COUNTIFS(Master_Orders!D2:D174, "2026-07-03", Master_Orders!J2:J174, "Prepaid", Master_Orders!K2:K174, "RTO / Returned") | N14: =E14+F14+G14
A15: 2026-07-04 | B15: =COUNTIFS(Master_Orders!D2:D174, "2026-07-04", Master_Orders!J2:J174, "COD") | C15: =COUNTIFS(Master_Orders!D2:D174, "2026-07-04", Master_Orders!J2:J174, "Partial COD") | D15: =COUNTIFS(Master_Orders!D2:D174, "2026-07-04", Master_Orders!J2:J174, "Prepaid") | E15: =SUMIFS(Master_Orders!E2:E174, Master_Orders!D2:D174, "2026-07-04", Master_Orders!J2:J174, "COD") | F15: =SUMIFS(Master_Orders!E2:E174, Master_Orders!D2:D174, "2026-07-04", Master_Orders!J2:J174, "Partial COD") | G15: =SUMIFS(Master_Orders!E2:E174, Master_Orders!D2:D174, "2026-07-04", Master_Orders!J2:J174, "Prepaid") | H15: =COUNTIFS(Master_Orders!D2:D174, "2026-07-04", Master_Orders!J2:J174, "COD", Master_Orders!K2:K174, "Delivered") | I15: =COUNTIFS(Master_Orders!D2:D174, "2026-07-04", Master_Orders!J2:J174, "Partial COD", Master_Orders!K2:K174, "Delivered") | J15: =COUNTIFS(Master_Orders!D2:D174, "2026-07-04", Master_Orders!J2:J174, "Prepaid", Master_Orders!K2:K174, "Delivered") | K15: =COUNTIFS(Master_Orders!D2:D174, "2026-07-04", Master_Orders!J2:J174, "COD", Master_Orders!K2:K174, "RTO / Returned") | L15: =COUNTIFS(Master_Orders!D2:D174, "2026-07-04", Master_Orders!J2:J174, "Partial COD", Master_Orders!K2:K174, "RTO / Returned") | M15: =COUNTIFS(Master_Orders!D2:D174, "2026-07-04", Master_Orders!J2:J174, "Prepaid", Master_Orders!K2:K174, "RTO / Returned") | N15: =E15+F15+G15
A16: 2026-07-05 | B16: =COUNTIFS(Master_Orders!D2:D174, "2026-07-05", Master_Orders!J2:J174, "COD") | C16: =COUNTIFS(Master_Orders!D2:D174, "2026-07-05", Master_Orders!J2:J174, "Partial COD") | D16: =COUNTIFS(Master_Orders!D2:D174, "2026-07-05", Master_Orders!J2:J174, "Prepaid") | E16: =SUMIFS(Master_Orders!E2:E174, Master_Orders!D2:D174, "2026-07-05", Master_Orders!J2:J174, "COD") | F16: =SUMIFS(Master_Orders!E2:E174, Master_Orders!D2:D174, "2026-07-05", Master_Orders!J2:J174, "Partial COD") | G16: =SUMIFS(Master_Orders!E2:E174, Master_Orders!D2:D174, "2026-07-05", Master_Orders!J2:J174, "Prepaid") | H16: =COUNTIFS(Master_Orders!D2:D174, "2026-07-05", Master_Orders!J2:J174, "COD", Master_Orders!K2:K174, "Delivered") | I16: =COUNTIFS(Master_Orders!D2:D174, "2026-07-05", Master_Orders!J2:J174, "Partial COD", Master_Orders!K2:K174, "Delivered") | J16: =COUNTIFS(Master_Orders!D2:D174, "2026-07-05", Master_Orders!J2:J174, "Prepaid", Master_Orders!K2:K174, "Delivered") | K16: =COUNTIFS(Master_Orders!D2:D174, "2026-07-05", Master_Orders!J2:J174, "COD", Master_Orders!K2:K174, "RTO / Returned") | L16: =COUNTIFS(Master_Orders!D2:D174, "2026-07-05", Master_Orders!J2:J174, "Partial COD", Master_Orders!K2:K174, "RTO / Returned") | M16: =COUNTIFS(Master_Orders!D2:D174, "2026-07-05", Master_Orders!J2:J174, "Prepaid", Master_Orders!K2:K174, "RTO / Returned") | N16: =E16+F16+G16
A17: 2026-07-06 | B17: =COUNTIFS(Master_Orders!D2:D174, "2026-07-06", Master_Orders!J2:J174, "COD") | C17: =COUNTIFS(Master_Orders!D2:D174, "2026-07-06", Master_Orders!J2:J174, "Partial COD") | D17: =COUNTIFS(Master_Orders!D2:D174, "2026-07-06", Master_Orders!J2:J174, "Prepaid") | E17: =SUMIFS(Master_Orders!E2:E174, Master_Orders!D2:D174, "2026-07-06", Master_Orders!J2:J174, "COD") | F17: =SUMIFS(Master_Orders!E2:E174, Master_Orders!D2:D174, "2026-07-06", Master_Orders!J2:J174, "Partial COD") | G17: =SUMIFS(Master_Orders!E2:E174, Master_Orders!D2:D174, "2026-07-06", Master_Orders!J2:J174, "Prepaid") | H17: =COUNTIFS(Master_Orders!D2:D174, "2026-07-06", Master_Orders!J2:J174, "COD", Master_Orders!K2:K174, "Delivered") | I17: =COUNTIFS(Master_Orders!D2:D174, "2026-07-06", Master_Orders!J2:J174, "Partial COD", Master_Orders!K2:K174, "Delivered") | J17: =COUNTIFS(Master_Orders!D2:D174, "2026-07-06", Master_Orders!J2:J174, "Prepaid", Master_Orders!K2:K174, "Delivered") | K17: =COUNTIFS(Master_Orders!D2:D174, "2026-07-06", Master_Orders!J2:J174, "COD", Master_Orders!K2:K174, "RTO / Returned") | L17: =COUNTIFS(Master_Orders!D2:D174, "2026-07-06", Master_Orders!J2:J174, "Partial COD", Master_Orders!K2:K174, "RTO / Returned") | M17: =COUNTIFS(Master_Orders!D2:D174, "2026-07-06", Master_Orders!J2:J174, "Prepaid", Master_Orders!K2:K174, "RTO / Returned") | N17: =E17+F17+G17
A18: 2026-07-07 | B18: =COUNTIFS(Master_Orders!D2:D174, "2026-07-07", Master_Orders!J2:J174, "COD") | C18: =COUNTIFS(Master_Orders!D2:D174, "2026-07-07", Master_Orders!J2:J174, "Partial COD") | D18: =COUNTIFS(Master_Orders!D2:D174, "2026-07-07", Master_Orders!J2:J174, "Prepaid") | E18: =SUMIFS(Master_Orders!E2:E174, Master_Orders!D2:D174, "2026-07-07", Master_Orders!J2:J174, "COD") | F18: =SUMIFS(Master_Orders!E2:E174, Master_Orders!D2:D174, "2026-07-07", Master_Orders!J2:J174, "Partial COD") | G18: =SUMIFS(Master_Orders!E2:E174, Master_Orders!D2:D174, "2026-07-07", Master_Orders!J2:J174, "Prepaid") | H18: =COUNTIFS(Master_Orders!D2:D174, "2026-07-07", Master_Orders!J2:J174, "COD", Master_Orders!K2:K174, "Delivered") | I18: =COUNTIFS(Master_Orders!D2:D174, "2026-07-07", Master_Orders!J2:J174, "Partial COD", Master_Orders!K2:K174, "Delivered") | J18: =COUNTIFS(Master_Orders!D2:D174, "2026-07-07", Master_Orders!J2:J174, "Prepaid", Master_Orders!K2:K174, "Delivered") | K18: =COUNTIFS(Master_Orders!D2:D174, "2026-07-07", Master_Orders!J2:J174, "COD", Master_Orders!K2:K174, "RTO / Returned") | L18: =COUNTIFS(Master_Orders!D2:D174, "2026-07-07", Master_Orders!J2:J174, "Partial COD", Master_Orders!K2:K174, "RTO / Returned") | M18: =COUNTIFS(Master_Orders!D2:D174, "2026-07-07", Master_Orders!J2:J174, "Prepaid", Master_Orders!K2:K174, "RTO / Returned") | N18: =E18+F18+G18
A19: 2026-07-08 | B19: =COUNTIFS(Master_Orders!D2:D174, "2026-07-08", Master_Orders!J2:J174, "COD") | C19: =COUNTIFS(Master_Orders!D2:D174, "2026-07-08", Master_Orders!J2:J174, "Partial COD") | D19: =COUNTIFS(Master_Orders!D2:D174, "2026-07-08", Master_Orders!J2:J174, "Prepaid") | E19: =SUMIFS(Master_Orders!E2:E174, Master_Orders!D2:D174, "2026-07-08", Master_Orders!J2:J174, "COD") | F19: =SUMIFS(Master_Orders!E2:E174, Master_Orders!D2:D174, "2026-07-08", Master_Orders!J2:J174, "Partial COD") | G19: =SUMIFS(Master_Orders!E2:E174, Master_Orders!D2:D174, "2026-07-08", Master_Orders!J2:J174, "Prepaid") | H19: =COUNTIFS(Master_Orders!D2:D174, "2026-07-08", Master_Orders!J2:J174, "COD", Master_Orders!K2:K174, "Delivered") | I19: =COUNTIFS(Master_Orders!D2:D174, "2026-07-08", Master_Orders!J2:J174, "Partial COD", Master_Orders!K2:K174, "Delivered") | J19: =COUNTIFS(Master_Orders!D2:D174, "2026-07-08", Master_Orders!J2:J174, "Prepaid", Master_Orders!K2:K174, "Delivered") | K19: =COUNTIFS(Master_Orders!D2:D174, "2026-07-08", Master_Orders!J2:J174, "COD", Master_Orders!K2:K174, "RTO / Returned") | L19: =COUNTIFS(Master_Orders!D2:D174, "2026-07-08", Master_Orders!J2:J174, "Partial COD", Master_Orders!K2:K174, "RTO / Returned") | M19: =COUNTIFS(Master_Orders!D2:D174, "2026-07-08", Master_Orders!J2:J174, "Prepaid", Master_Orders!K2:K174, "RTO / Returned") | N19: =E19+F19+G19
A20: 2026-07-09 | B20: =COUNTIFS(Master_Orders!D2:D174, "2026-07-09", Master_Orders!J2:J174, "COD") | C20: =COUNTIFS(Master_Orders!D2:D174, "2026-07-09", Master_Orders!J2:J174, "Partial COD") | D20: =COUNTIFS(Master_Orders!D2:D174, "2026-07-09", Master_Orders!J2:J174, "Prepaid") | E20: =SUMIFS(Master_Orders!E2:E174, Master_Orders!D2:D174, "2026-07-09", Master_Orders!J2:J174, "COD") | F20: =SUMIFS(Master_Orders!E2:E174, Master_Orders!D2:D174, "2026-07-09", Master_Orders!J2:J174, "Partial COD") | G20: =SUMIFS(Master_Orders!E2:E174, Master_Orders!D2:D174, "2026-07-09", Master_Orders!J2:J174, "Prepaid") | H20: =COUNTIFS(Master_Orders!D2:D174, "2026-07-09", Master_Orders!J2:J174, "COD", Master_Orders!K2:K174, "Delivered") | I20: =COUNTIFS(Master_Orders!D2:D174, "2026-07-09", Master_Orders!J2:J174, "Partial COD", Master_Orders!K2:K174, "Delivered") | J20: =COUNTIFS(Master_Orders!D2:D174, "2026-07-09", Master_Orders!J2:J174, "Prepaid", Master_Orders!K2:K174, "Delivered") | K20: =COUNTIFS(Master_Orders!D2:D174, "2026-07-09", Master_Orders!J2:J174, "COD", Master_Orders!K2:K174, "RTO / Returned") | L20: =COUNTIFS(Master_Orders!D2:D174, "2026-07-09", Master_Orders!J2:J174, "Partial COD", Master_Orders!K2:K174, "RTO / Returned") | M20: =COUNTIFS(Master_Orders!D2:D174, "2026-07-09", Master_Orders!J2:J174, "Prepaid", Master_Orders!K2:K174, "RTO / Returned") | N20: =E20+F20+G20
A21: 2026-07-10 | B21: =COUNTIFS(Master_Orders!D2:D174, "2026-07-10", Master_Orders!J2:J174, "COD") | C21: =COUNTIFS(Master_Orders!D2:D174, "2026-07-10", Master_Orders!J2:J174, "Partial COD") | D21: =COUNTIFS(Master_Orders!D2:D174, "2026-07-10", Master_Orders!J2:J174, "Prepaid") | E21: =SUMIFS(Master_Orders!E2:E174, Master_Orders!D2:D174, "2026-07-10", Master_Orders!J2:J174, "COD") | F21: =SUMIFS(Master_Orders!E2:E174, Master_Orders!D2:D174, "2026-07-10", Master_Orders!J2:J174, "Partial COD") | G21: =SUMIFS(Master_Orders!E2:E174, Master_Orders!D2:D174, "2026-07-10", Master_Orders!J2:J174, "Prepaid") | H21: =COUNTIFS(Master_Orders!D2:D174, "2026-07-10", Master_Orders!J2:J174, "COD", Master_Orders!K2:K174, "Delivered") | I21: =COUNTIFS(Master_Orders!D2:D174, "2026-07-10", Master_Orders!J2:J174, "Partial COD", Master_Orders!K2:K174, "Delivered") | J21: =COUNTIFS(Master_Orders!D2:D174, "2026-07-10", Master_Orders!J2:J174, "Prepaid", Master_Orders!K2:K174, "Delivered") | K21: =COUNTIFS(Master_Orders!D2:D174, "2026-07-10", Master_Orders!J2:J174, "COD", Master_Orders!K2:K174, "RTO / Returned") | L21: =COUNTIFS(Master_Orders!D2:D174, "2026-07-10", Master_Orders!J2:J174, "Partial COD", Master_Orders!K2:K174, "RTO / Returned") | M21: =COUNTIFS(Master_Orders!D2:D174, "2026-07-10", Master_Orders!J2:J174, "Prepaid", Master_Orders!K2:K174, "RTO / Returned") | N21: =E21+F21+G21
A22: 2026-07-11 | B22: =COUNTIFS(Master_Orders!D2:D174, "2026-07-11", Master_Orders!J2:J174, "COD") | C22: =COUNTIFS(Master_Orders!D2:D174, "2026-07-11", Master_Orders!J2:J174, "Partial COD") | D22: =COUNTIFS(Master_Orders!D2:D174, "2026-07-11", Master_Orders!J2:J174, "Prepaid") | E22: =SUMIFS(Master_Orders!E2:E174, Master_Orders!D2:D174, "2026-07-11", Master_Orders!J2:J174, "COD") | F22: =SUMIFS(Master_Orders!E2:E174, Master_Orders!D2:D174, "2026-07-11", Master_Orders!J2:J174, "Partial COD") | G22: =SUMIFS(Master_Orders!E2:E174, Master_Orders!D2:D174, "2026-07-11", Master_Orders!J2:J174, "Prepaid") | H22: =COUNTIFS(Master_Orders!D2:D174, "2026-07-11", Master_Orders!J2:J174, "COD", Master_Orders!K2:K174, "Delivered") | I22: =COUNTIFS(Master_Orders!D2:D174, "2026-07-11", Master_Orders!J2:J174, "Partial COD", Master_Orders!K2:K174, "Delivered") | J22: =COUNTIFS(Master_Orders!D2:D174, "2026-07-11", Master_Orders!J2:J174, "Prepaid", Master_Orders!K2:K174, "Delivered") | K22: =COUNTIFS(Master_Orders!D2:D174, "2026-07-11", Master_Orders!J2:J174, "COD", Master_Orders!K2:K174, "RTO / Returned") | L22: =COUNTIFS(Master_Orders!D2:D174, "2026-07-11", Master_Orders!J2:J174, "Partial COD", Master_Orders!K2:K174, "RTO / Returned") | M22: =COUNTIFS(Master_Orders!D2:D174, "2026-07-11", Master_Orders!J2:J174, "Prepaid", Master_Orders!K2:K174, "RTO / Returned") | N22: =E22+F22+G22
A23: 2026-07-12 | B23: =COUNTIFS(Master_Orders!D2:D174, "2026-07-12", Master_Orders!J2:J174, "COD") | C23: =COUNTIFS(Master_Orders!D2:D174, "2026-07-12", Master_Orders!J2:J174, "Partial COD") | D23: =COUNTIFS(Master_Orders!D2:D174, "2026-07-12", Master_Orders!J2:J174, "Prepaid") | E23: =SUMIFS(Master_Orders!E2:E174, Master_Orders!D2:D174, "2026-07-12", Master_Orders!J2:J174, "COD") | F23: =SUMIFS(Master_Orders!E2:E174, Master_Orders!D2:D174, "2026-07-12", Master_Orders!J2:J174, "Partial COD") | G23: =SUMIFS(Master_Orders!E2:E174, Master_Orders!D2:D174, "2026-07-12", Master_Orders!J2:J174, "Prepaid") | H23: =COUNTIFS(Master_Orders!D2:D174, "2026-07-12", Master_Orders!J2:J174, "COD", Master_Orders!K2:K174, "Delivered") | I23: =COUNTIFS(Master_Orders!D2:D174, "2026-07-12", Master_Orders!J2:J174, "Partial COD", Master_Orders!K2:K174, "Delivered") | J23: =COUNTIFS(Master_Orders!D2:D174, "2026-07-12", Master_Orders!J2:J174, "Prepaid", Master_Orders!K2:K174, "Delivered") | K23: =COUNTIFS(Master_Orders!D2:D174, "2026-07-12", Master_Orders!J2:J174, "COD", Master_Orders!K2:K174, "RTO / Returned") | L23: =COUNTIFS(Master_Orders!D2:D174, "2026-07-12", Master_Orders!J2:J174, "Partial COD", Master_Orders!K2:K174, "RTO / Returned") | M23: =COUNTIFS(Master_Orders!D2:D174, "2026-07-12", Master_Orders!J2:J174, "Prepaid", Master_Orders!K2:K174, "RTO / Returned") | N23: =E23+F23+G23
A24: 2026-07-13 | B24: =COUNTIFS(Master_Orders!D2:D174, "2026-07-13", Master_Orders!J2:J174, "COD") | C24: =COUNTIFS(Master_Orders!D2:D174, "2026-07-13", Master_Orders!J2:J174, "Partial COD") | D24: =COUNTIFS(Master_Orders!D2:D174, "2026-07-13", Master_Orders!J2:J174, "Prepaid") | E24: =SUMIFS(Master_Orders!E2:E174, Master_Orders!D2:D174, "2026-07-13", Master_Orders!J2:J174, "COD") | F24: =SUMIFS(Master_Orders!E2:E174, Master_Orders!D2:D174, "2026-07-13", Master_Orders!J2:J174, "Partial COD") | G24: =SUMIFS(Master_Orders!E2:E174, Master_Orders!D2:D174, "2026-07-13", Master_Orders!J2:J174, "Prepaid") | H24: =COUNTIFS(Master_Orders!D2:D174, "2026-07-13", Master_Orders!J2:J174, "COD", Master_Orders!K2:K174, "Delivered") | I24: =COUNTIFS(Master_Orders!D2:D174, "2026-07-13", Master_Orders!J2:J174, "Partial COD", Master_Orders!K2:K174, "Delivered") | J24: =COUNTIFS(Master_Orders!D2:D174, "2026-07-13", Master_Orders!J2:J174, "Prepaid", Master_Orders!K2:K174, "Delivered") | K24: =COUNTIFS(Master_Orders!D2:D174, "2026-07-13", Master_Orders!J2:J174, "COD", Master_Orders!K2:K174, "RTO / Returned") | L24: =COUNTIFS(Master_Orders!D2:D174, "2026-07-13", Master_Orders!J2:J174, "Partial COD", Master_Orders!K2:K174, "RTO / Returned") | M24: =COUNTIFS(Master_Orders!D2:D174, "2026-07-13", Master_Orders!J2:J174, "Prepaid", Master_Orders!K2:K174, "RTO / Returned") | N24: =E24+F24+G24
A25: 2026-07-14 | B25: =COUNTIFS(Master_Orders!D2:D174, "2026-07-14", Master_Orders!J2:J174, "COD") | C25: =COUNTIFS(Master_Orders!D2:D174, "2026-07-14", Master_Orders!J2:J174, "Partial COD") | D25: =COUNTIFS(Master_Orders!D2:D174, "2026-07-14", Master_Orders!J2:J174, "Prepaid") | E25: =SUMIFS(Master_Orders!E2:E174, Master_Orders!D2:D174, "2026-07-14", Master_Orders!J2:J174, "COD") | F25: =SUMIFS(Master_Orders!E2:E174, Master_Orders!D2:D174, "2026-07-14", Master_Orders!J2:J174, "Partial COD") | G25: =SUMIFS(Master_Orders!E2:E174, Master_Orders!D2:D174, "2026-07-14", Master_Orders!J2:J174, "Prepaid") | H25: =COUNTIFS(Master_Orders!D2:D174, "2026-07-14", Master_Orders!J2:J174, "COD", Master_Orders!K2:K174, "Delivered") | I25: =COUNTIFS(Master_Orders!D2:D174, "2026-07-14", Master_Orders!J2:J174, "Partial COD", Master_Orders!K2:K174, "Delivered") | J25: =COUNTIFS(Master_Orders!D2:D174, "2026-07-14", Master_Orders!J2:J174, "Prepaid", Master_Orders!K2:K174, "Delivered") | K25: =COUNTIFS(Master_Orders!D2:D174, "2026-07-14", Master_Orders!J2:J174, "COD", Master_Orders!K2:K174, "RTO / Returned") | L25: =COUNTIFS(Master_Orders!D2:D174, "2026-07-14", Master_Orders!J2:J174, "Partial COD", Master_Orders!K2:K174, "RTO / Returned") | M25: =COUNTIFS(Master_Orders!D2:D174, "2026-07-14", Master_Orders!J2:J174, "Prepaid", Master_Orders!K2:K174, "RTO / Returned") | N25: =E25+F25+G25
A26: 2026-07-15 | B26: =COUNTIFS(Master_Orders!D2:D174, "2026-07-15", Master_Orders!J2:J174, "COD") | C26: =COUNTIFS(Master_Orders!D2:D174, "2026-07-15", Master_Orders!J2:J174, "Partial COD") | D26: =COUNTIFS(Master_Orders!D2:D174, "2026-07-15", Master_Orders!J2:J174, "Prepaid") | E26: =SUMIFS(Master_Orders!E2:E174, Master_Orders!D2:D174, "2026-07-15", Master_Orders!J2:J174, "COD") | F26: =SUMIFS(Master_Orders!E2:E174, Master_Orders!D2:D174, "2026-07-15", Master_Orders!J2:J174, "Partial COD") | G26: =SUMIFS(Master_Orders!E2:E174, Master_Orders!D2:D174, "2026-07-15", Master_Orders!J2:J174, "Prepaid") | H26: =COUNTIFS(Master_Orders!D2:D174, "2026-07-15", Master_Orders!J2:J174, "COD", Master_Orders!K2:K174, "Delivered") | I26: =COUNTIFS(Master_Orders!D2:D174, "2026-07-15", Master_Orders!J2:J174, "Partial COD", Master_Orders!K2:K174, "Delivered") | J26: =COUNTIFS(Master_Orders!D2:D174, "2026-07-15", Master_Orders!J2:J174, "Prepaid", Master_Orders!K2:K174, "Delivered") | K26: =COUNTIFS(Master_Orders!D2:D174, "2026-07-15", Master_Orders!J2:J174, "COD", Master_Orders!K2:K174, "RTO / Returned") | L26: =COUNTIFS(Master_Orders!D2:D174, "2026-07-15", Master_Orders!J2:J174, "Partial COD", Master_Orders!K2:K174, "RTO / Returned") | M26: =COUNTIFS(Master_Orders!D2:D174, "2026-07-15", Master_Orders!J2:J174, "Prepaid", Master_Orders!K2:K174, "RTO / Returned") | N26: =E26+F26+G26
A27: 2026-07-16 | B27: =COUNTIFS(Master_Orders!D2:D174, "2026-07-16", Master_Orders!J2:J174, "COD") | C27: =COUNTIFS(Master_Orders!D2:D174, "2026-07-16", Master_Orders!J2:J174, "Partial COD") | D27: =COUNTIFS(Master_Orders!D2:D174, "2026-07-16", Master_Orders!J2:J174, "Prepaid") | E27: =SUMIFS(Master_Orders!E2:E174, Master_Orders!D2:D174, "2026-07-16", Master_Orders!J2:J174, "COD") | F27: =SUMIFS(Master_Orders!E2:E174, Master_Orders!D2:D174, "2026-07-16", Master_Orders!J2:J174, "Partial COD") | G27: =SUMIFS(Master_Orders!E2:E174, Master_Orders!D2:D174, "2026-07-16", Master_Orders!J2:J174, "Prepaid") | H27: =COUNTIFS(Master_Orders!D2:D174, "2026-07-16", Master_Orders!J2:J174, "COD", Master_Orders!K2:K174, "Delivered") | I27: =COUNTIFS(Master_Orders!D2:D174, "2026-07-16", Master_Orders!J2:J174, "Partial COD", Master_Orders!K2:K174, "Delivered") | J27: =COUNTIFS(Master_Orders!D2:D174, "2026-07-16", Master_Orders!J2:J174, "Prepaid", Master_Orders!K2:K174, "Delivered") | K27: =COUNTIFS(Master_Orders!D2:D174, "2026-07-16", Master_Orders!J2:J174, "COD", Master_Orders!K2:K174, "RTO / Returned") | L27: =COUNTIFS(Master_Orders!D2:D174, "2026-07-16", Master_Orders!J2:J174, "Partial COD", Master_Orders!K2:K174, "RTO / Returned") | M27: =COUNTIFS(Master_Orders!D2:D174, "2026-07-16", Master_Orders!J2:J174, "Prepaid", Master_Orders!K2:K174, "RTO / Returned") | N27: =E27+F27+G27
A28: 2026-07-17 | B28: =COUNTIFS(Master_Orders!D2:D174, "2026-07-17", Master_Orders!J2:J174, "COD") | C28: =COUNTIFS(Master_Orders!D2:D174, "2026-07-17", Master_Orders!J2:J174, "Partial COD") | D28: =COUNTIFS(Master_Orders!D2:D174, "2026-07-17", Master_Orders!J2:J174, "Prepaid") | E28: =SUMIFS(Master_Orders!E2:E174, Master_Orders!D2:D174, "2026-07-17", Master_Orders!J2:J174, "COD") | F28: =SUMIFS(Master_Orders!E2:E174, Master_Orders!D2:D174, "2026-07-17", Master_Orders!J2:J174, "Partial COD") | G28: =SUMIFS(Master_Orders!E2:E174, Master_Orders!D2:D174, "2026-07-17", Master_Orders!J2:J174, "Prepaid") | H28: =COUNTIFS(Master_Orders!D2:D174, "2026-07-17", Master_Orders!J2:J174, "COD", Master_Orders!K2:K174, "Delivered") | I28: =COUNTIFS(Master_Orders!D2:D174, "2026-07-17", Master_Orders!J2:J174, "Partial COD", Master_Orders!K2:K174, "Delivered") | J28: =COUNTIFS(Master_Orders!D2:D174, "2026-07-17", Master_Orders!J2:J174, "Prepaid", Master_Orders!K2:K174, "Delivered") | K28: =COUNTIFS(Master_Orders!D2:D174, "2026-07-17", Master_Orders!J2:J174, "COD", Master_Orders!K2:K174, "RTO / Returned") | L28: =COUNTIFS(Master_Orders!D2:D174, "2026-07-17", Master_Orders!J2:J174, "Partial COD", Master_Orders!K2:K174, "RTO / Returned") | M28: =COUNTIFS(Master_Orders!D2:D174, "2026-07-17", Master_Orders!J2:J174, "Prepaid", Master_Orders!K2:K174, "RTO / Returned") | N28: =E28+F28+G28
A29: 2026-07-18 | B29: =COUNTIFS(Master_Orders!D2:D174, "2026-07-18", Master_Orders!J2:J174, "COD") | C29: =COUNTIFS(Master_Orders!D2:D174, "2026-07-18", Master_Orders!J2:J174, "Partial COD") | D29: =COUNTIFS(Master_Orders!D2:D174, "2026-07-18", Master_Orders!J2:J174, "Prepaid") | E29: =SUMIFS(Master_Orders!E2:E174, Master_Orders!D2:D174, "2026-07-18", Master_Orders!J2:J174, "COD") | F29: =SUMIFS(Master_Orders!E2:E174, Master_Orders!D2:D174, "2026-07-18", Master_Orders!J2:J174, "Partial COD") | G29: =SUMIFS(Master_Orders!E2:E174, Master_Orders!D2:D174, "2026-07-18", Master_Orders!J2:J174, "Prepaid") | H29: =COUNTIFS(Master_Orders!D2:D174, "2026-07-18", Master_Orders!J2:J174, "COD", Master_Orders!K2:K174, "Delivered") | I29: =COUNTIFS(Master_Orders!D2:D174, "2026-07-18", Master_Orders!J2:J174, "Partial COD", Master_Orders!K2:K174, "Delivered") | J29: =COUNTIFS(Master_Orders!D2:D174, "2026-07-18", Master_Orders!J2:J174, "Prepaid", Master_Orders!K2:K174, "Delivered") | K29: =COUNTIFS(Master_Orders!D2:D174, "2026-07-18", Master_Orders!J2:J174, "COD", Master_Orders!K2:K174, "RTO / Returned") | L29: =COUNTIFS(Master_Orders!D2:D174, "2026-07-18", Master_Orders!J2:J174, "Partial COD", Master_Orders!K2:K174, "RTO / Returned") | M29: =COUNTIFS(Master_Orders!D2:D174, "2026-07-18", Master_Orders!J2:J174, "Prepaid", Master_Orders!K2:K174, "RTO / Returned") | N29: =E29+F29+G29
A30: 2026-07-19 | B30: =COUNTIFS(Master_Orders!D2:D174, "2026-07-19", Master_Orders!J2:J174, "COD") | C30: =COUNTIFS(Master_Orders!D2:D174, "2026-07-19", Master_Orders!J2:J174, "Partial COD") | D30: =COUNTIFS(Master_Orders!D2:D174, "2026-07-19", Master_Orders!J2:J174, "Prepaid") | E30: =SUMIFS(Master_Orders!E2:E174, Master_Orders!D2:D174, "2026-07-19", Master_Orders!J2:J174, "COD") | F30: =SUMIFS(Master_Orders!E2:E174, Master_Orders!D2:D174, "2026-07-19", Master_Orders!J2:J174, "Partial COD") | G30: =SUMIFS(Master_Orders!E2:E174, Master_Orders!D2:D174, "2026-07-19", Master_Orders!J2:J174, "Prepaid") | H30: =COUNTIFS(Master_Orders!D2:D174, "2026-07-19", Master_Orders!J2:J174, "COD", Master_Orders!K2:K174, "Delivered") | I30: =COUNTIFS(Master_Orders!D2:D174, "2026-07-19", Master_Orders!J2:J174, "Partial COD", Master_Orders!K2:K174, "Delivered") | J30: =COUNTIFS(Master_Orders!D2:D174, "2026-07-19", Master_Orders!J2:J174, "Prepaid", Master_Orders!K2:K174, "Delivered") | K30: =COUNTIFS(Master_Orders!D2:D174, "2026-07-19", Master_Orders!J2:J174, "COD", Master_Orders!K2:K174, "RTO / Returned") | L30: =COUNTIFS(Master_Orders!D2:D174, "2026-07-19", Master_Orders!J2:J174, "Partial COD", Master_Orders!K2:K174, "RTO / Returned") | M30: =COUNTIFS(Master_Orders!D2:D174, "2026-07-19", Master_Orders!J2:J174, "Prepaid", Master_Orders!K2:K174, "RTO / Returned") | N30: =E30+F30+G30
A31: 2026-07-20 | B31: =COUNTIFS(Master_Orders!D2:D174, "2026-07-20", Master_Orders!J2:J174, "COD") | C31: =COUNTIFS(Master_Orders!D2:D174, "2026-07-20", Master_Orders!J2:J174, "Partial COD") | D31: =COUNTIFS(Master_Orders!D2:D174, "2026-07-20", Master_Orders!J2:J174, "Prepaid") | E31: =SUMIFS(Master_Orders!E2:E174, Master_Orders!D2:D174, "2026-07-20", Master_Orders!J2:J174, "COD") | F31: =SUMIFS(Master_Orders!E2:E174, Master_Orders!D2:D174, "2026-07-20", Master_Orders!J2:J174, "Partial COD") | G31: =SUMIFS(Master_Orders!E2:E174, Master_Orders!D2:D174, "2026-07-20", Master_Orders!J2:J174, "Prepaid") | H31: =COUNTIFS(Master_Orders!D2:D174, "2026-07-20", Master_Orders!J2:J174, "COD", Master_Orders!K2:K174, "Delivered") | I31: =COUNTIFS(Master_Orders!D2:D174, "2026-07-20", Master_Orders!J2:J174, "Partial COD", Master_Orders!K2:K174, "Delivered") | J31: =COUNTIFS(Master_Orders!D2:D174, "2026-07-20", Master_Orders!J2:J174, "Prepaid", Master_Orders!K2:K174, "Delivered") | K31: =COUNTIFS(Master_Orders!D2:D174, "2026-07-20", Master_Orders!J2:J174, "COD", Master_Orders!K2:K174, "RTO / Returned") | L31: =COUNTIFS(Master_Orders!D2:D174, "2026-07-20", Master_Orders!J2:J174, "Partial COD", Master_Orders!K2:K174, "RTO / Returned") | M31: =COUNTIFS(Master_Orders!D2:D174, "2026-07-20", Master_Orders!J2:J174, "Prepaid", Master_Orders!K2:K174, "RTO / Returned") | N31: =E31+F31+G31
A32: 2026-07-21 | B32: =COUNTIFS(Master_Orders!D2:D174, "2026-07-21", Master_Orders!J2:J174, "COD") | C32: =COUNTIFS(Master_Orders!D2:D174, "2026-07-21", Master_Orders!J2:J174, "Partial COD") | D32: =COUNTIFS(Master_Orders!D2:D174, "2026-07-21", Master_Orders!J2:J174, "Prepaid") | E32: =SUMIFS(Master_Orders!E2:E174, Master_Orders!D2:D174, "2026-07-21", Master_Orders!J2:J174, "COD") | F32: =SUMIFS(Master_Orders!E2:E174, Master_Orders!D2:D174, "2026-07-21", Master_Orders!J2:J174, "Partial COD") | G32: =SUMIFS(Master_Orders!E2:E174, Master_Orders!D2:D174, "2026-07-21", Master_Orders!J2:J174, "Prepaid") | H32: =COUNTIFS(Master_Orders!D2:D174, "2026-07-21", Master_Orders!J2:J174, "COD", Master_Orders!K2:K174, "Delivered") | I32: =COUNTIFS(Master_Orders!D2:D174, "2026-07-21", Master_Orders!J2:J174, "Partial COD", Master_Orders!K2:K174, "Delivered") | J32: =COUNTIFS(Master_Orders!D2:D174, "2026-07-21", Master_Orders!J2:J174, "Prepaid", Master_Orders!K2:K174, "Delivered") | K32: =COUNTIFS(Master_Orders!D2:D174, "2026-07-21", Master_Orders!J2:J174, "COD", Master_Orders!K2:K174, "RTO / Returned") | L32: =COUNTIFS(Master_Orders!D2:D174, "2026-07-21", Master_Orders!J2:J174, "Partial COD", Master_Orders!K2:K174, "RTO / Returned") | M32: =COUNTIFS(Master_Orders!D2:D174, "2026-07-21", Master_Orders!J2:J174, "Prepaid", Master_Orders!K2:K174, "RTO / Returned") | N32: =E32+F32+G32
A33: 2026-07-22 | B33: =COUNTIFS(Master_Orders!D2:D174, "2026-07-22", Master_Orders!J2:J174, "COD") | C33: =COUNTIFS(Master_Orders!D2:D174, "2026-07-22", Master_Orders!J2:J174, "Partial COD") | D33: =COUNTIFS(Master_Orders!D2:D174, "2026-07-22", Master_Orders!J2:J174, "Prepaid") | E33: =SUMIFS(Master_Orders!E2:E174, Master_Orders!D2:D174, "2026-07-22", Master_Orders!J2:J174, "COD") | F33: =SUMIFS(Master_Orders!E2:E174, Master_Orders!D2:D174, "2026-07-22", Master_Orders!J2:J174, "Partial COD") | G33: =SUMIFS(Master_Orders!E2:E174, Master_Orders!D2:D174, "2026-07-22", Master_Orders!J2:J174, "Prepaid") | H33: =COUNTIFS(Master_Orders!D2:D174, "2026-07-22", Master_Orders!J2:J174, "COD", Master_Orders!K2:K174, "Delivered") | I33: =COUNTIFS(Master_Orders!D2:D174, "2026-07-22", Master_Orders!J2:J174, "Partial COD", Master_Orders!K2:K174, "Delivered") | J33: =COUNTIFS(Master_Orders!D2:D174, "2026-07-22", Master_Orders!J2:J174, "Prepaid", Master_Orders!K2:K174, "Delivered") | K33: =COUNTIFS(Master_Orders!D2:D174, "2026-07-22", Master_Orders!J2:J174, "COD", Master_Orders!K2:K174, "RTO / Returned") | L33: =COUNTIFS(Master_Orders!D2:D174, "2026-07-22", Master_Orders!J2:J174, "Partial COD", Master_Orders!K2:K174, "RTO / Returned") | M33: =COUNTIFS(Master_Orders!D2:D174, "2026-07-22", Master_Orders!J2:J174, "Prepaid", Master_Orders!K2:K174, "RTO / Returned") | N33: =E33+F33+G33
A34: 2026-07-23 | B34: =COUNTIFS(Master_Orders!D2:D174, "2026-07-23", Master_Orders!J2:J174, "COD") | C34: =COUNTIFS(Master_Orders!D2:D174, "2026-07-23", Master_Orders!J2:J174, "Partial COD") | D34: =COUNTIFS(Master_Orders!D2:D174, "2026-07-23", Master_Orders!J2:J174, "Prepaid") | E34: =SUMIFS(Master_Orders!E2:E174, Master_Orders!D2:D174, "2026-07-23", Master_Orders!J2:J174, "COD") | F34: =SUMIFS(Master_Orders!E2:E174, Master_Orders!D2:D174, "2026-07-23", Master_Orders!J2:J174, "Partial COD") | G34: =SUMIFS(Master_Orders!E2:E174, Master_Orders!D2:D174, "2026-07-23", Master_Orders!J2:J174, "Prepaid") | H34: =COUNTIFS(Master_Orders!D2:D174, "2026-07-23", Master_Orders!J2:J174, "COD", Master_Orders!K2:K174, "Delivered") | I34: =COUNTIFS(Master_Orders!D2:D174, "2026-07-23", Master_Orders!J2:J174, "Partial COD", Master_Orders!K2:K174, "Delivered") | J34: =COUNTIFS(Master_Orders!D2:D174, "2026-07-23", Master_Orders!J2:J174, "Prepaid", Master_Orders!K2:K174, "Delivered") | K34: =COUNTIFS(Master_Orders!D2:D174, "2026-07-23", Master_Orders!J2:J174, "COD", Master_Orders!K2:K174, "RTO / Returned") | L34: =COUNTIFS(Master_Orders!D2:D174, "2026-07-23", Master_Orders!J2:J174, "Partial COD", Master_Orders!K2:K174, "RTO / Returned") | M34: =COUNTIFS(Master_Orders!D2:D174, "2026-07-23", Master_Orders!J2:J174, "Prepaid", Master_Orders!K2:K174, "RTO / Returned") | N34: =E34+F34+G34
A35: 2026-07-24 | B35: =COUNTIFS(Master_Orders!D2:D174, "2026-07-24", Master_Orders!J2:J174, "COD") | C35: =COUNTIFS(Master_Orders!D2:D174, "2026-07-24", Master_Orders!J2:J174, "Partial COD") | D35: =COUNTIFS(Master_Orders!D2:D174, "2026-07-24", Master_Orders!J2:J174, "Prepaid") | E35: =SUMIFS(Master_Orders!E2:E174, Master_Orders!D2:D174, "2026-07-24", Master_Orders!J2:J174, "COD") | F35: =SUMIFS(Master_Orders!E2:E174, Master_Orders!D2:D174, "2026-07-24", Master_Orders!J2:J174, "Partial COD") | G35: =SUMIFS(Master_Orders!E2:E174, Master_Orders!D2:D174, "2026-07-24", Master_Orders!J2:J174, "Prepaid") | H35: =COUNTIFS(Master_Orders!D2:D174, "2026-07-24", Master_Orders!J2:J174, "COD", Master_Orders!K2:K174, "Delivered") | I35: =COUNTIFS(Master_Orders!D2:D174, "2026-07-24", Master_Orders!J2:J174, "Partial COD", Master_Orders!K2:K174, "Delivered") | J35: =COUNTIFS(Master_Orders!D2:D174, "2026-07-24", Master_Orders!J2:J174, "Prepaid", Master_Orders!K2:K174, "Delivered") | K35: =COUNTIFS(Master_Orders!D2:D174, "2026-07-24", Master_Orders!J2:J174, "COD", Master_Orders!K2:K174, "RTO / Returned") | L35: =COUNTIFS(Master_Orders!D2:D174, "2026-07-24", Master_Orders!J2:J174, "Partial COD", Master_Orders!K2:K174, "RTO / Returned") | M35: =COUNTIFS(Master_Orders!D2:D174, "2026-07-24", Master_Orders!J2:J174, "Prepaid", Master_Orders!K2:K174, "RTO / Returned") | N35: =E35+F35+G35
A36: 2026-07-25 | B36: =COUNTIFS(Master_Orders!D2:D174, "2026-07-25", Master_Orders!J2:J174, "COD") | C36: =COUNTIFS(Master_Orders!D2:D174, "2026-07-25", Master_Orders!J2:J174, "Partial COD") | D36: =COUNTIFS(Master_Orders!D2:D174, "2026-07-25", Master_Orders!J2:J174, "Prepaid") | E36: =SUMIFS(Master_Orders!E2:E174, Master_Orders!D2:D174, "2026-07-25", Master_Orders!J2:J174, "COD") | F36: =SUMIFS(Master_Orders!E2:E174, Master_Orders!D2:D174, "2026-07-25", Master_Orders!J2:J174, "Partial COD") | G36: =SUMIFS(Master_Orders!E2:E174, Master_Orders!D2:D174, "2026-07-25", Master_Orders!J2:J174, "Prepaid") | H36: =COUNTIFS(Master_Orders!D2:D174, "2026-07-25", Master_Orders!J2:J174, "COD", Master_Orders!K2:K174, "Delivered") | I36: =COUNTIFS(Master_Orders!D2:D174, "2026-07-25", Master_Orders!J2:J174, "Partial COD", Master_Orders!K2:K174, "Delivered") | J36: =COUNTIFS(Master_Orders!D2:D174, "2026-07-25", Master_Orders!J2:J174, "Prepaid", Master_Orders!K2:K174, "Delivered") | K36: =COUNTIFS(Master_Orders!D2:D174, "2026-07-25", Master_Orders!J2:J174, "COD", Master_Orders!K2:K174, "RTO / Returned") | L36: =COUNTIFS(Master_Orders!D2:D174, "2026-07-25", Master_Orders!J2:J174, "Partial COD", Master_Orders!K2:K174, "RTO / Returned") | M36: =COUNTIFS(Master_Orders!D2:D174, "2026-07-25", Master_Orders!J2:J174, "Prepaid", Master_Orders!K2:K174, "RTO / Returned") | N36: =E36+F36+G36
A37: 2026-07-26 | B37: =COUNTIFS(Master_Orders!D2:D174, "2026-07-26", Master_Orders!J2:J174, "COD") | C37: =COUNTIFS(Master_Orders!D2:D174, "2026-07-26", Master_Orders!J2:J174, "Partial COD") | D37: =COUNTIFS(Master_Orders!D2:D174, "2026-07-26", Master_Orders!J2:J174, "Prepaid") | E37: =SUMIFS(Master_Orders!E2:E174, Master_Orders!D2:D174, "2026-07-26", Master_Orders!J2:J174, "COD") | F37: =SUMIFS(Master_Orders!E2:E174, Master_Orders!D2:D174, "2026-07-26", Master_Orders!J2:J174, "Partial COD") | G37: =SUMIFS(Master_Orders!E2:E174, Master_Orders!D2:D174, "2026-07-26", Master_Orders!J2:J174, "Prepaid") | H37: =COUNTIFS(Master_Orders!D2:D174, "2026-07-26", Master_Orders!J2:J174, "COD", Master_Orders!K2:K174, "Delivered") | I37: =COUNTIFS(Master_Orders!D2:D174, "2026-07-26", Master_Orders!J2:J174, "Partial COD", Master_Orders!K2:K174, "Delivered") | J37: =COUNTIFS(Master_Orders!D2:D174, "2026-07-26", Master_Orders!J2:J174, "Prepaid", Master_Orders!K2:K174, "Delivered") | K37: =COUNTIFS(Master_Orders!D2:D174, "2026-07-26", Master_Orders!J2:J174, "COD", Master_Orders!K2:K174, "RTO / Returned") | L37: =COUNTIFS(Master_Orders!D2:D174, "2026-07-26", Master_Orders!J2:J174, "Partial COD", Master_Orders!K2:K174, "RTO / Returned") | M37: =COUNTIFS(Master_Orders!D2:D174, "2026-07-26", Master_Orders!J2:J174, "Prepaid", Master_Orders!K2:K174, "RTO / Returned") | N37: =E37+F37+G37
A38: 2026-07-27 | B38: =COUNTIFS(Master_Orders!D2:D174, "2026-07-27", Master_Orders!J2:J174, "COD") | C38: =COUNTIFS(Master_Orders!D2:D174, "2026-07-27", Master_Orders!J2:J174, "Partial COD") | D38: =COUNTIFS(Master_Orders!D2:D174, "2026-07-27", Master_Orders!J2:J174, "Prepaid") | E38: =SUMIFS(Master_Orders!E2:E174, Master_Orders!D2:D174, "2026-07-27", Master_Orders!J2:J174, "COD") | F38: =SUMIFS(Master_Orders!E2:E174, Master_Orders!D2:D174, "2026-07-27", Master_Orders!J2:J174, "Partial COD") | G38: =SUMIFS(Master_Orders!E2:E174, Master_Orders!D2:D174, "2026-07-27", Master_Orders!J2:J174, "Prepaid") | H38: =COUNTIFS(Master_Orders!D2:D174, "2026-07-27", Master_Orders!J2:J174, "COD", Master_Orders!K2:K174, "Delivered") | I38: =COUNTIFS(Master_Orders!D2:D174, "2026-07-27", Master_Orders!J2:J174, "Partial COD", Master_Orders!K2:K174, "Delivered") | J38: =COUNTIFS(Master_Orders!D2:D174, "2026-07-27", Master_Orders!J2:J174, "Prepaid", Master_Orders!K2:K174, "Delivered") | K38: =COUNTIFS(Master_Orders!D2:D174, "2026-07-27", Master_Orders!J2:J174, "COD", Master_Orders!K2:K174, "RTO / Returned") | L38: =COUNTIFS(Master_Orders!D2:D174, "2026-07-27", Master_Orders!J2:J174, "Partial COD", Master_Orders!K2:K174, "RTO / Returned") | M38: =COUNTIFS(Master_Orders!D2:D174, "2026-07-27", Master_Orders!J2:J174, "Prepaid", Master_Orders!K2:K174, "RTO / Returned") | N38: =E38+F38+G38
A39: 2026-07-28 | B39: =COUNTIFS(Master_Orders!D2:D174, "2026-07-28", Master_Orders!J2:J174, "COD") | C39: =COUNTIFS(Master_Orders!D2:D174, "2026-07-28", Master_Orders!J2:J174, "Partial COD") | D39: =COUNTIFS(Master_Orders!D2:D174, "2026-07-28", Master_Orders!J2:J174, "Prepaid") | E39: =SUMIFS(Master_Orders!E2:E174, Master_Orders!D2:D174, "2026-07-28", Master_Orders!J2:J174, "COD") | F39: =SUMIFS(Master_Orders!E2:E174, Master_Orders!D2:D174, "2026-07-28", Master_Orders!J2:J174, "Partial COD") | G39: =SUMIFS(Master_Orders!E2:E174, Master_Orders!D2:D174, "2026-07-28", Master_Orders!J2:J174, "Prepaid") | H39: =COUNTIFS(Master_Orders!D2:D174, "2026-07-28", Master_Orders!J2:J174, "COD", Master_Orders!K2:K174, "Delivered") | I39: =COUNTIFS(Master_Orders!D2:D174, "2026-07-28", Master_Orders!J2:J174, "Partial COD", Master_Orders!K2:K174, "Delivered") | J39: =COUNTIFS(Master_Orders!D2:D174, "2026-07-28", Master_Orders!J2:J174, "Prepaid", Master_Orders!K2:K174, "Delivered") | K39: =COUNTIFS(Master_Orders!D2:D174, "2026-07-28", Master_Orders!J2:J174, "COD", Master_Orders!K2:K174, "RTO / Returned") | L39: =COUNTIFS(Master_Orders!D2:D174, "2026-07-28", Master_Orders!J2:J174, "Partial COD", Master_Orders!K2:K174, "RTO / Returned") | M39: =COUNTIFS(Master_Orders!D2:D174, "2026-07-28", Master_Orders!J2:J174, "Prepaid", Master_Orders!K2:K174, "RTO / Returned") | N39: =E39+F39+G39
A40: 2026-07-29 | B40: =COUNTIFS(Master_Orders!D2:D174, "2026-07-29", Master_Orders!J2:J174, "COD") | C40: =COUNTIFS(Master_Orders!D2:D174, "2026-07-29", Master_Orders!J2:J174, "Partial COD") | D40: =COUNTIFS(Master_Orders!D2:D174, "2026-07-29", Master_Orders!J2:J174, "Prepaid") | E40: =SUMIFS(Master_Orders!E2:E174, Master_Orders!D2:D174, "2026-07-29", Master_Orders!J2:J174, "COD") | F40: =SUMIFS(Master_Orders!E2:E174, Master_Orders!D2:D174, "2026-07-29", Master_Orders!J2:J174, "Partial COD") | G40: =SUMIFS(Master_Orders!E2:E174, Master_Orders!D2:D174, "2026-07-29", Master_Orders!J2:J174, "Prepaid") | H40: =COUNTIFS(Master_Orders!D2:D174, "2026-07-29", Master_Orders!J2:J174, "COD", Master_Orders!K2:K174, "Delivered") | I40: =COUNTIFS(Master_Orders!D2:D174, "2026-07-29", Master_Orders!J2:J174, "Partial COD", Master_Orders!K2:K174, "Delivered") | J40: =COUNTIFS(Master_Orders!D2:D174, "2026-07-29", Master_Orders!J2:J174, "Prepaid", Master_Orders!K2:K174, "Delivered") | K40: =COUNTIFS(Master_Orders!D2:D174, "2026-07-29", Master_Orders!J2:J174, "COD", Master_Orders!K2:K174, "RTO / Returned") | L40: =COUNTIFS(Master_Orders!D2:D174, "2026-07-29", Master_Orders!J2:J174, "Partial COD", Master_Orders!K2:K174, "RTO / Returned") | M40: =COUNTIFS(Master_Orders!D2:D174, "2026-07-29", Master_Orders!J2:J174, "Prepaid", Master_Orders!K2:K174, "RTO / Returned") | N40: =E40+F40+G40
A41: 2026-07-30 | B41: =COUNTIFS(Master_Orders!D2:D174, "2026-07-30", Master_Orders!J2:J174, "COD") | C41: =COUNTIFS(Master_Orders!D2:D174, "2026-07-30", Master_Orders!J2:J174, "Partial COD") | D41: =COUNTIFS(Master_Orders!D2:D174, "2026-07-30", Master_Orders!J2:J174, "Prepaid") | E41: =SUMIFS(Master_Orders!E2:E174, Master_Orders!D2:D174, "2026-07-30", Master_Orders!J2:J174, "COD") | F41: =SUMIFS(Master_Orders!E2:E174, Master_Orders!D2:D174, "2026-07-30", Master_Orders!J2:J174, "Partial COD") | G41: =SUMIFS(Master_Orders!E2:E174, Master_Orders!D2:D174, "2026-07-30", Master_Orders!J2:J174, "Prepaid") | H41: =COUNTIFS(Master_Orders!D2:D174, "2026-07-30", Master_Orders!J2:J174, "COD", Master_Orders!K2:K174, "Delivered") | I41: =COUNTIFS(Master_Orders!D2:D174, "2026-07-30", Master_Orders!J2:J174, "Partial COD", Master_Orders!K2:K174, "Delivered") | J41: =COUNTIFS(Master_Orders!D2:D174, "2026-07-30", Master_Orders!J2:J174, "Prepaid", Master_Orders!K2:K174, "Delivered") | K41: =COUNTIFS(Master_Orders!D2:D174, "2026-07-30", Master_Orders!J2:J174, "COD", Master_Orders!K2:K174, "RTO / Returned") | L41: =COUNTIFS(Master_Orders!D2:D174, "2026-07-30", Master_Orders!J2:J174, "Partial COD", Master_Orders!K2:K174, "RTO / Returned") | M41: =COUNTIFS(Master_Orders!D2:D174, "2026-07-30", Master_Orders!J2:J174, "Prepaid", Master_Orders!K2:K174, "RTO / Returned") | N41: =E41+F41+G41
A42: Total Portfolio | B42: =SUM(B5:B41) | C42: =SUM(C5:C41) | D42: =SUM(D5:D41) | E42: =SUM(E5:E41) | F42: =SUM(F5:F41) | G42: =SUM(G5:G41) | H42: =SUM(H5:H41) | I42: =SUM(I5:I41) | ... N42: =SUM(N5:N41)

Sheet COD_Day_Wise
A1: JANVI AIKA - INDIVIDUAL DAYWISE REPORT: CASH ON DELIVERY (COD)
A3: Order Date | B3: COD Orders | C3: COD Revenue (Rs.) | D3: AOV (Rs.) | E3: Delivered Count | F3: Delivered Rev (Rs.) | G3: RTO Count | H3: RTO Rev Loss (Rs.) | I3: Canceled Count | J3: In Transit Count | K3: Realization Rate %
A4: 2026-06-24 | B4: =COUNTIFS(Master_Orders!D2:D174, "2026-06-24", Master_Orders!J2:J174, "COD") | C4: =SUMIFS(Master_Orders!E2:E174, Master_Orders!D2:D174, "2026-06-24", Master_Orders!J2:J174, "COD") | D4: =C4/B4 | E4: =COUNTIFS(Master_Orders!D2:D174, "2026-06-24", Master_Orders!J2:J174, "COD", Master_Orders!K2:K174, "Delivered") | F4: =SUMIFS(Master_Orders!E2:E174, Master_Orders!D2:D174, "2026-06-24", Master_Orders!J2:J174, "COD", Master_Orders!K2:K174, "Delivered") | G4: =COUNTIFS(Master_Orders!D2:D174, "2026-06-24", Master_Orders!J2:J174, "COD", Master_Orders!K2:K174, "RTO / Returned") | H4: =SUMIFS(Master_Orders!E2:E174, Master_Orders!D2:D174, "2026-06-24", Master_Orders!J2:J174, "COD", Master_Orders!K2:K174, "RTO / Returned") | I4: =COUNTIFS(Master_Orders!D2:D174, "2026-06-24", Master_Orders!J2:J174, "COD", Master_Orders!K2:K174, "Canceled") | J4: =COUNTIFS(Master_Orders!D2:D174, "2026-06-24", Master_Orders!J2:J174, "COD", Master_Orders!K2:K174, "In Transit") | K4: =E4/B4
A5: 2026-06-25 | B5: =COUNTIFS(Master_Orders!D2:D174, "2026-06-25", Master_Orders!J2:J174, "COD") | C5: =SUMIFS(Master_Orders!E2:E174, Master_Orders!D2:D174, "2026-06-25", Master_Orders!J2:J174, "COD") | D5: =C5/B5 | E5: =COUNTIFS(Master_Orders!D2:D174, "2026-06-25", Master_Orders!J2:J174, "COD", Master_Orders!K2:K174, "Delivered") | F5: =SUMIFS(Master_Orders!E2:E174, Master_Orders!D2:D174, "2026-06-25", Master_Orders!J2:J174, "COD", Master_Orders!K2:K174, "Delivered") | G5: =COUNTIFS(Master_Orders!D2:D174, "2026-06-25", Master_Orders!J2:J174, "COD", Master_Orders!K2:K174, "RTO / Returned") | H5: =SUMIFS(Master_Orders!E2:E174, Master_Orders!D2:D174, "2026-06-25", Master_Orders!J2:J174, "COD", Master_Orders!K2:K174, "RTO / Returned") | I5: =COUNTIFS(Master_Orders!D2:D174, "2026-06-25", Master_Orders!J2:J174, "COD", Master_Orders!K2:K174, "Canceled") | J5: =COUNTIFS(Master_Orders!D2:D174, "2026-06-25", Master_Orders!J2:J174, "COD", Master_Orders!K2:K174, "In Transit") | K5: =E5/B5
A6: 2026-06-27 | B6: =COUNTIFS(Master_Orders!D2:D174, "2026-06-27", Master_Orders!J2:J174, "COD") | C6: =SUMIFS(Master_Orders!E2:E174, Master_Orders!D2:D174, "2026-06-27", Master_Orders!J2:J174, "COD") | D6: =C6/B6 | E6: =COUNTIFS(Master_Orders!D2:D174, "2026-06-27", Master_Orders!J2:J174, "COD", Master_Orders!K2:K174, "Delivered") | F6: =SUMIFS(Master_Orders!E2:E174, Master_Orders!D2:D174, "2026-06-27", Master_Orders!J2:J174, "COD", Master_Orders!K2:K174, "Delivered") | G6: =COUNTIFS(Master_Orders!D2:D174, "2026-06-27", Master_Orders!J2:J174, "COD", Master_Orders!K2:K174, "RTO / Returned") | H6: =SUMIFS(Master_Orders!E2:E174, Master_Orders!D2:D174, "2026-06-27", Master_Orders!J2:J174, "COD", Master_Orders!K2:K174, "RTO / Returned") | I6: =COUNTIFS(Master_Orders!D2:D174, "2026-06-27", Master_Orders!J2:J174, "COD", Master_Orders!K2:K174, "Canceled") | J6: =COUNTIFS(Master_Orders!D2:D174, "2026-06-27", Master_Orders!J2:J174, "COD", Master_Orders!K2:K174, "In Transit") | K6: =E6/B6
A7: 2026-06-28 | B7: =COUNTIFS(Master_Orders!D2:D174, "2026-06-28", Master_Orders!J2:J174, "COD") | C7: =SUMIFS(Master_Orders!E2:E174, Master_Orders!D2:D174, "2026-06-28", Master_Orders!J2:J174, "COD") | D7: =C7/B7 | E7: =COUNTIFS(Master_Orders!D2:D174, "2026-06-28", Master_Orders!J2:J174, "COD", Master_Orders!K2:K174, "Delivered") | F7: =SUMIFS(Master_Orders!E2:E174, Master_Orders!D2:D174, "2026-06-28", Master_Orders!J2:J174, "COD", Master_Orders!K2:K174, "Delivered") | G7: =COUNTIFS(Master_Orders!D2:D174, "2026-06-28", Master_Orders!J2:J174, "COD", Master_Orders!K2:K174, "RTO / Returned") | H7: =SUMIFS(Master_Orders!E2:E174, Master_Orders!D2:D174, "2026-06-28", Master_Orders!J2:J174, "COD", Master_Orders!K2:K174, "RTO / Returned") | I7: =COUNTIFS(Master_Orders!D2:D174, "2026-06-28", Master_Orders!J2:J174, "COD", Master_Orders!K2:K174, "Canceled") | J7: =COUNTIFS(Master_Orders!D2:D174, "2026-06-28", Master_Orders!J2:J174, "COD", Master_Orders!K2:K174, "In Transit") | K7: =E7/B7
A8: 2026-06-29 | B8: =COUNTIFS(Master_Orders!D2:D174, "2026-06-29", Master_Orders!J2:J174, "COD") | C8: =SUMIFS(Master_Orders!E2:E174, Master_Orders!D2:D174, "2026-06-29", Master_Orders!J2:J174, "COD") | D8: =C8/B8 | E8: =COUNTIFS(Master_Orders!D2:D174, "2026-06-29", Master_Orders!J2:J174, "COD", Master_Orders!K2:K174, "Delivered") | F8: =SUMIFS(Master_Orders!E2:E174, Master_Orders!D2:D174, "2026-06-29", Master_Orders!J2:J174, "COD", Master_Orders!K2:K174, "Delivered") | G8: =COUNTIFS(Master_Orders!D2:D174, "2026-06-29", Master_Orders!J2:J174, "COD", Master_Orders!K2:K174, "RTO / Returned") | H8: =SUMIFS(Master_Orders!E2:E174, Master_Orders!D2:D174, "2026-06-29", Master_Orders!J2:J174, "COD", Master_Orders!K2:K174, "RTO / Returned") | I8: =COUNTIFS(Master_Orders!D2:D174, "2026-06-29", Master_Orders!J2:J174, "COD", Master_Orders!K2:K174, "Canceled") | J8: =COUNTIFS(Master_Orders!D2:D174, "2026-06-29", Master_Orders!J2:J174, "COD", Master_Orders!K2:K174, "In Transit") | K8: =E8/B8
A9: 2026-06-30 | B9: =COUNTIFS(Master_Orders!D2:D174, "2026-06-30", Master_Orders!J2:J174, "COD") | C9: =SUMIFS(Master_Orders!E2:E174, Master_Orders!D2:D174, "2026-06-30", Master_Orders!J2:J174, "COD") | D9: =C9/B9 | E9: =COUNTIFS(Master_Orders!D2:D174, "2026-06-30", Master_Orders!J2:J174, "COD", Master_Orders!K2:K174, "Delivered") | F9: =SUMIFS(Master_Orders!E2:E174, Master_Orders!D2:D174, "2026-06-30", Master_Orders!J2:J174, "COD", Master_Orders!K2:K174, "Delivered") | G9: =COUNTIFS(Master_Orders!D2:D174, "2026-06-30", Master_Orders!J2:J174, "COD", Master_Orders!K2:K174, "RTO / Returned") | H9: =SUMIFS(Master_Orders!E2:E174, Master_Orders!D2:D174, "2026-06-30", Master_Orders!J2:J174, "COD", Master_Orders!K2:K174, "RTO / Returned") | I9: =COUNTIFS(Master_Orders!D2:D174, "2026-06-30", Master_Orders!J2:J174, "COD", Master_Orders!K2:K174, "Canceled") | J9: =COUNTIFS(Master_Orders!D2:D174, "2026-06-30", Master_Orders!J2:J174, "COD", Master_Orders!K2:K174, "In Transit") | K9: =E9/B9
A10: 2026-07-01 | B10: =COUNTIFS(Master_Orders!D2:D174, "2026-07-01", Master_Orders!J2:J174, "COD") | C10: =SUMIFS(Master_Orders!E2:E174, Master_Orders!D2:D174, "2026-07-01", Master_Orders!J2:J174, "COD") | D10: =C10/B10 | E10: =COUNTIFS(Master_Orders!D2:D174, "2026-07-01", Master_Orders!J2:J174, "COD", Master_Orders!K2:K174, "Delivered") | F10: =SUMIFS(Master_Orders!E2:E174, Master_Orders!D2:D174, "2026-07-01", Master_Orders!J2:J174, "COD", Master_Orders!K2:K174, "Delivered") | G10: =COUNTIFS(Master_Orders!D2:D174, "2026-07-01", Master_Orders!J2:J174, "COD", Master_Orders!K2:K174, "RTO / Returned") | H10: =SUMIFS(Master_Orders!E2:E174, Master_Orders!D2:D174, "2026-07-01", Master_Orders!J2:J174, "COD", Master_Orders!K2:K174, "RTO / Returned") | I10: =COUNTIFS(Master_Orders!D2:D174, "2026-07-01", Master_Orders!J2:J174, "COD", Master_Orders!K2:K174, "Canceled") | J10: =COUNTIFS(Master_Orders!D2:D174, "2026-07-01", Master_Orders!J2:J174, "COD", Master_Orders!K2:K174, "In Transit") | K10: =E10/B10
A11: 2026-07-02 | B11: =COUNTIFS(Master_Orders!D2:D174, "2026-07-02", Master_Orders!J2:J174, "COD") | C11: =SUMIFS(Master_Orders!E2:E174, Master_Orders!D2:D174, "2026-07-02", Master_Orders!J2:J174, "COD") | D11: =C11/B11 | E11: =COUNTIFS(Master_Orders!D2:D174, "2026-07-02", Master_Orders!J2:J174, "COD", Master_Orders!K2:K174, "Delivered") | F11: =SUMIFS(Master_Orders!E2:E174, Master_Orders!D2:D174, "2026-07-02", Master_Orders!J2:J174, "COD", Master_Orders!K2:K174, "Delivered") | G11: =COUNTIFS(Master_Orders!D2:D174, "2026-07-02", Master_Orders!J2:J174, "COD", Master_Orders!K2:K174, "RTO / Returned") | H11: =SUMIFS(Master_Orders!E2:E174, Master_Orders!D2:D174, "2026-07-02", Master_Orders!J2:J174, "COD", Master_Orders!K2:K174, "RTO / Returned") | I11: =COUNTIFS(Master_Orders!D2:D174, "2026-07-02", Master_Orders!J2:J174, "COD", Master_Orders!K2:K174, "Canceled") | J11: =COUNTIFS(Master_Orders!D2:D174, "2026-07-02", Master_Orders!J2:J174, "COD", Master_Orders!K2:K174, "In Transit") | K11: =E11/B11
A12: 2026-07-03 | B12: =COUNTIFS(Master_Orders!D2:D174, "2026-07-03", Master_Orders!J2:J174, "COD") | C12: =SUMIFS(Master_Orders!E2:E174, Master_Orders!D2:D174, "2026-07-03", Master_Orders!J2:J174, "COD") | D12: =C12/B12 | E12: =COUNTIFS(Master_Orders!D2:D174, "2026-07-03", Master_Orders!J2:J174, "COD", Master_Orders!K2:K174, "Delivered") | F12: =SUMIFS(Master_Orders!E2:E174, Master_Orders!D2:D174, "2026-07-03", Master_Orders!J2:J174, "COD", Master_Orders!K2:K174, "Delivered") | G12: =COUNTIFS(Master_Orders!D2:D174, "2026-07-03", Master_Orders!J2:J174, "COD", Master_Orders!K2:K174, "RTO / Returned") | H12: =SUMIFS(Master_Orders!E2:E174, Master_Orders!D2:D174, "2026-07-03", Master_Orders!J2:J174, "COD", Master_Orders!K2:K174, "RTO / Returned") | I12: =COUNTIFS(Master_Orders!D2:D174, "2026-07-03", Master_Orders!J2:J174, "COD", Master_Orders!K2:K174, "Canceled") | J12: =COUNTIFS(Master_Orders!D2:D174, "2026-07-03", Master_Orders!J2:J174, "COD", Master_Orders!K2:K174, "In Transit") | K12: =E12/B12
A13: 2026-07-04 | B13: =COUNTIFS(Master_Orders!D2:D174, "2026-07-04", Master_Orders!J2:J174, "COD") | C13: =SUMIFS(Master_Orders!E2:E174, Master_Orders!D2:D174, "2026-07-04", Master_Orders!J2:J174, "COD") | D13: =C13/B13 | E13: =COUNTIFS(Master_Orders!D2:D174, "2026-07-04", Master_Orders!J2:J174, "COD", Master_Orders!K2:K174, "Delivered") | F13: =SUMIFS(Master_Orders!E2:E174, Master_Orders!D2:D174, "2026-07-04", Master_Orders!J2:J174, "COD", Master_Orders!K2:K174, "Delivered") | G13: =COUNTIFS(Master_Orders!D2:D174, "2026-07-04", Master_Orders!J2:J174, "COD", Master_Orders!K2:K174, "RTO / Returned") | H13: =SUMIFS(Master_Orders!E2:E174, Master_Orders!D2:D174, "2026-07-04", Master_Orders!J2:J174, "COD", Master_Orders!K2:K174, "RTO / Returned") | I13: =COUNTIFS(Master_Orders!D2:D174, "2026-07-04", Master_Orders!J2:J174, "COD", Master_Orders!K2:K174, "Canceled") | J13: =COUNTIFS(Master_Orders!D2:D174, "2026-07-04", Master_Orders!J2:J174, "COD", Master_Orders!K2:K174, "In Transit") | K13: =E13/B13
A14: 2026-07-05 | B14: =COUNTIFS(Master_Orders!D2:D174, "2026-07-05", Master_Orders!J2:J174, "COD") | C14: =SUMIFS(Master_Orders!E2:E174, Master_Orders!D2:D174, "2026-07-05", Master_Orders!J2:J174, "COD") | D14: =C14/B14 | E14: =COUNTIFS(Master_Orders!D2:D174, "2026-07-05", Master_Orders!J2:J174, "COD", Master_Orders!K2:K174, "Delivered") | F14: =SUMIFS(Master_Orders!E2:E174, Master_Orders!D2:D174, "2026-07-05", Master_Orders!J2:J174, "COD", Master_Orders!K2:K174, "Delivered") | G14: =COUNTIFS(Master_Orders!D2:D174, "2026-07-05", Master_Orders!J2:J174, "COD", Master_Orders!K2:K174, "RTO / Returned") | H14: =SUMIFS(Master_Orders!E2:E174, Master_Orders!D2:D174, "2026-07-05", Master_Orders!J2:J174, "COD", Master_Orders!K2:K174, "RTO / Returned") | I14: =COUNTIFS(Master_Orders!D2:D174, "2026-07-05", Master_Orders!J2:J174, "COD", Master_Orders!K2:K174, "Canceled") | J14: =COUNTIFS(Master_Orders!D2:D174, "2026-07-05", Master_Orders!J2:J174, "COD", Master_Orders!K2:K174, "In Transit") | K14: =E14/B14
A15: 2026-07-06 | B15: =COUNTIFS(Master_Orders!D2:D174, "2026-07-06", Master_Orders!J2:J174, "COD") | C15: =SUMIFS(Master_Orders!E2:E174, Master_Orders!D2:D174, "2026-07-06", Master_Orders!J2:J174, "COD") | D15: =C15/B15 | E15: =COUNTIFS(Master_Orders!D2:D174, "2026-07-06", Master_Orders!J2:J174, "COD", Master_Orders!K2:K174, "Delivered") | F15: =SUMIFS(Master_Orders!E2:E174, Master_Orders!D2:D174, "2026-07-06", Master_Orders!J2:J174, "COD", Master_Orders!K2:K174, "Delivered") | G15: =COUNTIFS(Master_Orders!D2:D174, "2026-07-06", Master_Orders!J2:J174, "COD", Master_Orders!K2:K174, "RTO / Returned") | H15: =SUMIFS(Master_Orders!E2:E174, Master_Orders!D2:D174, "2026-07-06", Master_Orders!J2:J174, "COD", Master_Orders!K2:K174, "RTO / Returned") | I15: =COUNTIFS(Master_Orders!D2:D174, "2026-07-06", Master_Orders!J2:J174, "COD", Master_Orders!K2:K174, "Canceled") | J15: =COUNTIFS(Master_Orders!D2:D174, "2026-07-06", Master_Orders!J2:J174, "COD", Master_Orders!K2:K174, "In Transit") | K15: =E15/B15
A16: 2026-07-07 | B16: =COUNTIFS(Master_Orders!D2:D174, "2026-07-07", Master_Orders!J2:J174, "COD") | C16: =SUMIFS(Master_Orders!E2:E174, Master_Orders!D2:D174, "2026-07-07", Master_Orders!J2:J174, "COD") | D16: =C16/B16 | E16: =COUNTIFS(Master_Orders!D2:D174, "2026-07-07", Master_Orders!J2:J174, "COD", Master_Orders!K2:K174, "Delivered") | F16: =SUMIFS(Master_Orders!E2:E174, Master_Orders!D2:D174, "2026-07-07", Master_Orders!J2:J174, "COD", Master_Orders!K2:K174, "Delivered") | G16: =COUNTIFS(Master_Orders!D2:D174, "2026-07-07", Master_Orders!J2:J174, "COD", Master_Orders!K2:K174, "RTO / Returned") | H16: =SUMIFS(Master_Orders!E2:E174, Master_Orders!D2:D174, "2026-07-07", Master_Orders!J2:J174, "COD", Master_Orders!K2:K174, "RTO / Returned") | I16: =COUNTIFS(Master_Orders!D2:D174, "2026-07-07", Master_Orders!J2:J174, "COD", Master_Orders!K2:K174, "Canceled") | J16: =COUNTIFS(Master_Orders!D2:D174, "2026-07-07", Master_Orders!J2:J174, "COD", Master_Orders!K2:K174, "In Transit") | K16: =E16/B16
A17: 2026-07-08 | B17: =COUNTIFS(Master_Orders!D2:D174, "2026-07-08", Master_Orders!J2:J174, "COD") | C17: =SUMIFS(Master_Orders!E2:E174, Master_Orders!D2:D174, "2026-07-08", Master_Orders!J2:J174, "COD") | D17: =C17/B17 | E17: =COUNTIFS(Master_Orders!D2:D174, "2026-07-08", Master_Orders!J2:J174, "COD", Master_Orders!K2:K174, "Delivered") | F17: =SUMIFS(Master_Orders!E2:E174, Master_Orders!D2:D174, "2026-07-08", Master_Orders!J2:J174, "COD", Master_Orders!K2:K174, "Delivered") | G17: =COUNTIFS(Master_Orders!D2:D174, "2026-07-08", Master_Orders!J2:J174, "COD", Master_Orders!K2:K174, "RTO / Returned") | H17: =SUMIFS(Master_Orders!E2:E174, Master_Orders!D2:D174, "2026-07-08", Master_Orders!J2:J174, "COD", Master_Orders!K2:K174, "RTO / Returned") | I17: =COUNTIFS(Master_Orders!D2:D174, "2026-07-08", Master_Orders!J2:J174, "COD", Master_Orders!K2:K174, "Canceled") | J17: =COUNTIFS(Master_Orders!D2:D174, "2026-07-08", Master_Orders!J2:J174, "COD", Master_Orders!K2:K174, "In Transit") | K17: =E17/B17
A18: 2026-07-09 | B18: =COUNTIFS(Master_Orders!D2:D174, "2026-07-09", Master_Orders!J2:J174, "COD") | C18: =SUMIFS(Master_Orders!E2:E174, Master_Orders!D2:D174, "2026-07-09", Master_Orders!J2:J174, "COD") | D18: =C18/B18 | E18: =COUNTIFS(Master_Orders!D2:D174, "2026-07-09", Master_Orders!J2:J174, "COD", Master_Orders!K2:K174, "Delivered") | F18: =SUMIFS(Master_Orders!E2:E174, Master_Orders!D2:D174, "2026-07-09", Master_Orders!J2:J174, "COD", Master_Orders!K2:K174, "Delivered") | G18: =COUNTIFS(Master_Orders!D2:D174, "2026-07-09", Master_Orders!J2:J174, "COD", Master_Orders!K2:K174, "RTO / Returned") | H18: =SUMIFS(Master_Orders!E2:E174, Master_Orders!D2:D174, "2026-07-09", Master_Orders!J2:J174, "COD", Master_Orders!K2:K174, "RTO / Returned") | I18: =COUNTIFS(Master_Orders!D2:D174, "2026-07-09", Master_Orders!J2:J174, "COD", Master_Orders!K2:K174, "Canceled") | J18: =COUNTIFS(Master_Orders!D2:D174, "2026-07-09", Master_Orders!J2:J174, "COD", Master_Orders!K2:K174, "In Transit") | K18: =E18/B18
A19: 2026-07-10 | B19: =COUNTIFS(Master_Orders!D2:D174, "2026-07-10", Master_Orders!J2:J174, "COD") | C19: =SUMIFS(Master_Orders!E2:E174, Master_Orders!D2:D174, "2026-07-10", Master_Orders!J2:J174, "COD") | D19: =C19/B19 | E19: =COUNTIFS(Master_Orders!D2:D174, "2026-07-10", Master_Orders!J2:J174, "COD", Master_Orders!K2:K174, "Delivered") | F19: =SUMIFS(Master_Orders!E2:E174, Master_Orders!D2:D174, "2026-07-10", Master_Orders!J2:J174, "COD", Master_Orders!K2:K174, "Delivered") | G19: =COUNTIFS(Master_Orders!D2:D174, "2026-07-10", Master_Orders!J2:J174, "COD", Master_Orders!K2:K174, "RTO / Returned") | H19: =SUMIFS(Master_Orders!E2:E174, Master_Orders!D2:D174, "2026-07-10", Master_Orders!J2:J174, "COD", Master_Orders!K2:K174, "RTO / Returned") | I19: =COUNTIFS(Master_Orders!D2:D174, "2026-07-10", Master_Orders!J2:J174, "COD", Master_Orders!K2:K174, "Canceled") | J19: =COUNTIFS(Master_Orders!D2:D174, "2026-07-10", Master_Orders!J2:J174, "COD", Master_Orders!K2:K174, "In Transit") | K19: =E19/B19
A20: 2026-07-20 | B20: =COUNTIFS(Master_Orders!D2:D174, "2026-07-20", Master_Orders!J2:J174, "COD") | C20: =SUMIFS(Master_Orders!E2:E174, Master_Orders!D2:D174, "2026-07-20", Master_Orders!J2:J174, "COD") | D20: =C20/B20 | E20: =COUNTIFS(Master_Orders!D2:D174, "2026-07-20", Master_Orders!J2:J174, "COD", Master_Orders!K2:K174, "Delivered") | F20: =SUMIFS(Master_Orders!E2:E174, Master_Orders!D2:D174, "2026-07-20", Master_Orders!J2:J174, "COD", Master_Orders!K2:K174, "Delivered") | G20: =COUNTIFS(Master_Orders!D2:D174, "2026-07-20", Master_Orders!J2:J174, "COD", Master_Orders!K2:K174, "RTO / Returned") | H20: =SUMIFS(Master_Orders!E2:E174, Master_Orders!D2:D174, "2026-07-20", Master_Orders!J2:J174, "COD", Master_Orders!K2:K174, "RTO / Returned") | I20: =COUNTIFS(Master_Orders!D2:D174, "2026-07-20", Master_Orders!J2:J174, "COD", Master_Orders!K2:K174, "Canceled") | J20: =COUNTIFS(Master_Orders!D2:D174, "2026-07-20", Master_Orders!J2:J174, "COD", Master_Orders!K2:K174, "In Transit") | K20: =E20/B20
A21: Total COD Summary | B21: =SUM(B4:B20) | C21: =SUM(C4:C20) | D21: =C21/B21 | E21: =SUM(E4:E20) | F21: =SUM(F4:F20) | G21: =SUM(G4:G20) | H21: =SUM(H4:H20) | I21: =SUM(I4:I20) | J21: =SUM(J4:J20) | K21: =E21/B21

Sheet Partial_COD_Day_Wise
A1: JANVI AIKA - INDIVIDUAL DAYWISE REPORT: PARTIAL COD
A3: Order Date | B3: Partial COD Orders | C3: Partial COD Revenue (Rs.) | D3: AOV (Rs.) | E3: Delivered Count | F3: Delivered Rev (Rs.) | G3: RTO Count | H3: RTO Rev Loss (Rs.) | I3: Canceled Count | J3: In Transit Count | K3: Realization Rate %
A4: 2026-07-24 | B4: =COUNTIFS(Master_Orders!D2:D174, "2026-07-24", Master_Orders!J2:J174, "Partial COD") | C4: =SUMIFS(Master_Orders!E2:E174, Master_Orders!D2:D174, "2026-07-24", Master_Orders!J2:J174, "Partial COD") | D4: =C4/B4 | E4: =COUNTIFS(Master_Orders!D2:D174, "2026-07-24", Master_Orders!J2:J174, "Partial COD", Master_Orders!K2:K174, "Delivered") | F4: =SUMIFS(Master_Orders!E2:E174, Master_Orders!D2:D174, "2026-07-24", Master_Orders!J2:J174, "Partial COD", Master_Orders!K2:K174, "Delivered") | G4: =COUNTIFS(Master_Orders!D2:D174, "2026-07-24", Master_Orders!J2:J174, "Partial COD", Master_Orders!K2:K174, "RTO / Returned") | H4: =SUMIFS(Master_Orders!E2:E174, Master_Orders!D2:D174, "2026-07-24", Master_Orders!J2:J174, "Partial COD", Master_Orders!K2:K174, "RTO / Returned") | I4: =COUNTIFS(Master_Orders!D2:D174, "2026-07-24", Master_Orders!J2:J174, "Partial COD", Master_Orders!K2:K174, "Canceled") | J4: =COUNTIFS(Master_Orders!D2:D174, "2026-07-24", Master_Orders!J2:J174, "Partial COD", Master_Orders!K2:K174, "In Transit") | K4: =E4/B4
A5: 2026-07-26 | B5: =COUNTIFS(Master_Orders!D2:D174, "2026-07-26", Master_Orders!J2:J174, "Partial COD") | C5: =SUMIFS(Master_Orders!E2:E174, Master_Orders!D2:D174, "2026-07-26", Master_Orders!J2:J174, "Partial COD") | D5: =C5/B5 | E5: =COUNTIFS(Master_Orders!D2:D174, "2026-07-26", Master_Orders!J2:J174, "Partial COD", Master_Orders!K2:K174, "Delivered") | F5: =SUMIFS(Master_Orders!E2:E174, Master_Orders!D2:D174, "2026-07-26", Master_Orders!J2:J174, "Partial COD", Master_Orders!K2:K174, "Delivered") | G5: =COUNTIFS(Master_Orders!D2:D174, "2026-07-26", Master_Orders!J2:J174, "Partial COD", Master_Orders!K2:K174, "RTO / Returned") | H5: =SUMIFS(Master_Orders!E2:E174, Master_Orders!D2:D174, "2026-07-26", Master_Orders!J2:J174, "Partial COD", Master_Orders!K2:K174, "RTO / Returned") | I5: =COUNTIFS(Master_Orders!D2:D174, "2026-07-26", Master_Orders!J2:J174, "Partial COD", Master_Orders!K2:K174, "Canceled") | J5: =COUNTIFS(Master_Orders!D2:D174, "2026-07-26", Master_Orders!J2:J174, "Partial COD", Master_Orders!K2:K174, "In Transit") | K5: =E5/B5
A6: 2026-07-27 | B6: =COUNTIFS(Master_Orders!D2:D174, "2026-07-27", Master_Orders!J2:J174, "Partial COD") | C6: =SUMIFS(Master_Orders!E2:E174, Master_Orders!D2:D174, "2026-07-27", Master_Orders!J2:J174, "Partial COD") | D6: =C6/B6 | E6: =COUNTIFS(Master_Orders!D2:D174, "2026-07-27", Master_Orders!J2:J174, "Partial COD", Master_Orders!K2:K174, "Delivered") | F6: =SUMIFS(Master_Orders!E2:E174, Master_Orders!D2:D174, "2026-07-27", Master_Orders!J2:J174, "Partial COD", Master_Orders!K2:K174, "Delivered") | G6: =COUNTIFS(Master_Orders!D2:D174, "2026-07-27", Master_Orders!J2:J174, "Partial COD", Master_Orders!K2:K174, "RTO / Returned") | H6: =SUMIFS(Master_Orders!E2:E174, Master_Orders!D2:D174, "2026-07-27", Master_Orders!J2:J174, "Partial COD", Master_Orders!K2:K174, "RTO / Returned") | I6: =COUNTIFS(Master_Orders!D2:D174, "2026-07-27", Master_Orders!J2:J174, "Partial COD", Master_Orders!K2:K174, "Canceled") | J6: =COUNTIFS(Master_Orders!D2:D174, "2026-07-27", Master_Orders!J2:J174, "Partial COD", Master_Orders!K2:K174, "In Transit") | K6: =E6/B6
A7: 2026-07-28 | B7: =COUNTIFS(Master_Orders!D2:D174, "2026-07-28", Master_Orders!J2:J174, "Partial COD") | C7: =SUMIFS(Master_Orders!E2:E174, Master_Orders!D2:D174, "2026-07-28", Master_Orders!J2:J174, "Partial COD") | D7: =C7/B7 | E7: =COUNTIFS(Master_Orders!D2:D174, "2026-07-28", Master_Orders!J2:J174, "Partial COD", Master_Orders!K2:K174, "Delivered") | F7: =SUMIFS(Master_Orders!E2:E174, Master_Orders!D2:D174, "2026-07-28", Master_Orders!J2:J174, "Partial COD", Master_Orders!K2:K174, "Delivered") | G7: =COUNTIFS(Master_Orders!D2:D174, "2026-07-28", Master_Orders!J2:J174, "Partial COD", Master_Orders!K2:K174, "RTO / Returned") | H7: =SUMIFS(Master_Orders!E2:E174, Master_Orders!D2:D174, "2026-07-28", Master_Orders!J2:J174, "Partial COD", Master_Orders!K2:K174, "RTO / Returned") | I7: =COUNTIFS(Master_Orders!D2:D174, "2026-07-28", Master_Orders!J2:J174, "Partial COD", Master_Orders!K2:K174, "Canceled") | J7: =COUNTIFS(Master_Orders!D2:D174, "2026-07-28", Master_Orders!J2:J174, "Partial COD", Master_Orders!K2:K174, "In Transit") | K7: =E7/B7
A8: 2026-07-29 | B8: =COUNTIFS(Master_Orders!D2:D174, "2026-07-29", Master_Orders!J2:J174, "Partial COD") | C8: =SUMIFS(Master_Orders!E2:E174, Master_Orders!D2:D174, "2026-07-29", Master_Orders!J2:J174, "Partial COD") | D8: =C8/B8 | E8: =COUNTIFS(Master_Orders!D2:D174, "2026-07-29", Master_Orders!J2:J174, "Partial COD", Master_Orders!K2:K174, "Delivered") | F8: =SUMIFS(Master_Orders!E2:E174, Master_Orders!D2:D174, "2026-07-29", Master_Orders!J2:J174, "Partial COD", Master_Orders!K2:K174, "Delivered") | G8: =COUNTIFS(Master_Orders!D2:D174, "2026-07-29", Master_Orders!J2:J174, "Partial COD", Master_Orders!K2:K174, "RTO / Returned") | H8: =SUMIFS(Master_Orders!E2:E174, Master_Orders!D2:D174, "2026-07-29", Master_Orders!J2:J174, "Partial COD", Master_Orders!K2:K174, "RTO / Returned") | I8: =COUNTIFS(Master_Orders!D2:D174, "2026-07-29", Master_Orders!J2:J174, "Partial COD", Master_Orders!K2:K174, "Canceled") | J8: =COUNTIFS(Master_Orders!D2:D174, "2026-07-29", Master_Orders!J2:J174, "Partial COD", Master_Orders!K2:K174, "In Transit") | K8: =E8/B8
A9: 2026-07-30 | B9: =COUNTIFS(Master_Orders!D2:D174, "2026-07-30", Master_Orders!J2:J174, "Partial COD") | C9: =SUMIFS(Master_Orders!E2:E174, Master_Orders!D2:D174, "2026-07-30", Master_Orders!J2:J174, "Partial COD") | D9: =C9/B9 | E9: =COUNTIFS(Master_Orders!D2:D174, "2026-07-30", Master_Orders!J2:J174, "Partial COD", Master_Orders!K2:K174, "Delivered") | F9: =SUMIFS(Master_Orders!E2:E174, Master_Orders!D2:D174, "2026-07-30", Master_Orders!J2:J174, "Partial COD", Master_Orders!K2:K174, "Delivered") | G9: =COUNTIFS(Master_Orders!D2:D174, "2026-07-30", Master_Orders!J2:J174, "Partial COD", Master_Orders!K2:K174, "RTO / Returned") | H9: =SUMIFS(Master_Orders!E2:E174, Master_Orders!D2:D174, "2026-07-30", Master_Orders!J2:J174, "Partial COD", Master_Orders!K2:K174, "RTO / Returned") | I9: =COUNTIFS(Master_Orders!D2:D174, "2026-07-30", Master_Orders!J2:J174, "Partial COD", Master_Orders!K2:K174, "Canceled") | J9: =COUNTIFS(Master_Orders!D2:D174, "2026-07-30", Master_Orders!J2:J174, "Partial COD", Master_Orders!K2:K174, "In Transit") | K9: =E9/B9
A10: Total Partial COD Summary | B10: =SUM(B4:B9) | C10: =SUM(C4:C9) | D10: =C10/B10 | E10: =SUM(E4:E9) | F10: =SUM(F4:F9) | G10: =SUM(G4:G9) | H10: =SUM(H4:H9) | I10: =SUM(I4:I9) | J10: =SUM(J4:J9) | K10: =E10/B10

Sheet Prepaid_Day_Wise
A1: JANVI AIKA - INDIVIDUAL DAYWISE REPORT: PREPAID (RAZORPAY/UPI)
A3: Order Date | B3: Prepaid Orders | C3: Prepaid Revenue (Rs.) | D3: AOV (Rs.) | E3: Delivered Count | F3: Delivered Rev (Rs.) | G3: RTO Count | H3: RTO Rev Loss (Rs.) | I3: Canceled Count | J3: In Transit Count | K3: Realization Rate %
A4: 2026-06-22 | B4: =COUNTIFS(Master_Orders!D2:D174, "2026-06-22", Master_Orders!J2:J174, "Prepaid") | C4: =SUMIFS(Master_Orders!E2:E174, Master_Orders!D2:D174, "2026-06-22", Master_Orders!J2:J174, "Prepaid") | D4: =C4/B4 | E4: =COUNTIFS(Master_Orders!D2:D174, "2026-06-22", Master_Orders!J2:J174, "Prepaid", Master_Orders!K2:K174, "Delivered") | F4: =SUMIFS(Master_Orders!E2:E174, Master_Orders!D2:D174, "2026-06-22", Master_Orders!J2:J174, "Prepaid", Master_Orders!K2:K174, "Delivered") | G4: =COUNTIFS(Master_Orders!D2:D174, "2026-06-22", Master_Orders!J2:J174, "Prepaid", Master_Orders!K2:K174, "RTO / Returned") | H4: =SUMIFS(Master_Orders!E2:E174, Master_Orders!D2:D174, "2026-06-22", Master_Orders!J2:J174, "Prepaid", Master_Orders!K2:K174, "RTO / Returned") | I4: =COUNTIFS(Master_Orders!D2:D174, "2026-06-22", Master_Orders!J2:J174, "Prepaid", Master_Orders!K2:K174, "Canceled") | J4: =COUNTIFS(Master_Orders!D2:D174, "2026-06-22", Master_Orders!J2:J174, "Prepaid", Master_Orders!K2:K174, "In Transit") | K4: =E4/B4
A5: 2026-06-24 | B5: =COUNTIFS(Master_Orders!D2:D174, "2026-06-24", Master_Orders!J2:J174, "Prepaid") | C5: =SUMIFS(Master_Orders!E2:E174, Master_Orders!D2:D174, "2026-06-24", Master_Orders!J2:J174, "Prepaid") | D5: =C5/B5 | E5: =COUNTIFS(Master_Orders!D2:D174, "2026-06-24", Master_Orders!J2:J174, "Prepaid", Master_Orders!K2:K174, "Delivered") | F5: =SUMIFS(Master_Orders!E2:E174, Master_Orders!D2:D174, "2026-06-24", Master_Orders!J2:J174, "Prepaid", Master_Orders!K2:K174, "Delivered") | G5: =COUNTIFS(Master_Orders!D2:D174, "2026-06-24", Master_Orders!J2:J174, "Prepaid", Master_Orders!K2:K174, "RTO / Returned") | H5: =SUMIFS(Master_Orders!E2:E174, Master_Orders!D2:D174, "2026-06-24", Master_Orders!J2:J174, "Prepaid", Master_Orders!K2:K174, "RTO / Returned") | I5: =COUNTIFS(Master_Orders!D2:D174, "2026-06-24", Master_Orders!J2:J174, "Prepaid", Master_Orders!K2:K174, "Canceled") | J5: =COUNTIFS(Master_Orders!D2:D174, "2026-06-24", Master_Orders!J2:J174, "Prepaid", Master_Orders!K2:K174, "In Transit") | K5: =E5/B5
A6: 2026-06-25 | B6: =COUNTIFS(Master_Orders!D2:D174, "2026-06-25", Master_Orders!J2:J174, "Prepaid") | C6: =SUMIFS(Master_Orders!E2:E174, Master_Orders!D2:D174, "2026-06-25", Master_Orders!J2:J174, "Prepaid") | D6: =C6/B6 | E6: =COUNTIFS(Master_Orders!D2:D174, "2026-06-25", Master_Orders!J2:J174, "Prepaid", Master_Orders!K2:K174, "Delivered") | F6: =SUMIFS(Master_Orders!E2:E174, Master_Orders!D2:D174, "2026-06-25", Master_Orders!J2:J174, "Prepaid", Master_Orders!K2:K174, "Delivered") | G6: =COUNTIFS(Master_Orders!D2:D174, "2026-06-25", Master_Orders!J2:J174, "Prepaid", Master_Orders!K2:K174, "RTO / Returned") | H6: =SUMIFS(Master_Orders!E2:E174, Master_Orders!D2:D174, "2026-06-25", Master_Orders!J2:J174, "Prepaid", Master_Orders!K2:K174, "RTO / Returned") | I6: =COUNTIFS(Master_Orders!D2:D174, "2026-06-25", Master_Orders!J2:J174, "Prepaid", Master_Orders!K2:K174, "Canceled") | J6: =COUNTIFS(Master_Orders!D2:D174, "2026-06-25", Master_Orders!J2:J174, "Prepaid", Master_Orders!K2:K174, "In Transit") | K6: =E6/B6
A7: 2026-06-27 | B7: =COUNTIFS(Master_Orders!D2:D174, "2026-06-27", Master_Orders!J2:J174, "Prepaid") | C7: =SUMIFS(Master_Orders!E2:E174, Master_Orders!D2:D174, "2026-06-27", Master_Orders!J2:J174, "Prepaid") | D7: =C7/B7 | E7: =COUNTIFS(Master_Orders!D2:D174, "2026-06-27", Master_Orders!J2:J174, "Prepaid", Master_Orders!K2:K174, "Delivered") | F7: =SUMIFS(Master_Orders!E2:E174, Master_Orders!D2:D174, "2026-06-27", Master_Orders!J2:J174, "Prepaid", Master_Orders!K2:K174, "Delivered") | G7: =COUNTIFS(Master_Orders!D2:D174, "2026-06-27", Master_Orders!J2:J174, "Prepaid", Master_Orders!K2:K174, "RTO / Returned") | H7: =SUMIFS(Master_Orders!E2:E174, Master_Orders!D2:D174, "2026-06-27", Master_Orders!J2:J174, "Prepaid", Master_Orders!K2:K174, "RTO / Returned") | I7: =COUNTIFS(Master_Orders!D2:D174, "2026-06-27", Master_Orders!J2:J174, "Prepaid", Master_Orders!K2:K174, "Canceled") | J7: =COUNTIFS(Master_Orders!D2:D174, "2026-06-27", Master_Orders!J2:J174, "Prepaid", Master_Orders!K2:K174, "In Transit") | K7: =E7/B7
A8: 2026-06-29 | B8: =COUNTIFS(Master_Orders!D2:D174, "2026-06-29", Master_Orders!J2:J174, "Prepaid") | C8: =SUMIFS(Master_Orders!E2:E174, Master_Orders!D2:D174, "2026-06-29", Master_Orders!J2:J174, "Prepaid") | D8: =C8/B8 | E8: =COUNTIFS(Master_Orders!D2:D174, "2026-06-29", Master_Orders!J2:J174, "Prepaid", Master_Orders!K2:K174, "Delivered") | F8: =SUMIFS(Master_Orders!E2:E174, Master_Orders!D2:D174, "2026-06-29", Master_Orders!J2:J174, "Prepaid", Master_Orders!K2:K174, "Delivered") | G8: =COUNTIFS(Master_Orders!D2:D174, "2026-06-29", Master_Orders!J2:J174, "Prepaid", Master_Orders!K2:K174, "RTO / Returned") | H8: =SUMIFS(Master_Orders!E2:E174, Master_Orders!D2:D174, "2026-06-29", Master_Orders!J2:J174, "Prepaid", Master_Orders!K2:K174, "RTO / Returned") | I8: =COUNTIFS(Master_Orders!D2:D174, "2026-06-29", Master_Orders!J2:J174, "Prepaid", Master_Orders!K2:K174, "Canceled") | J8: =COUNTIFS(Master_Orders!D2:D174, "2026-06-29", Master_Orders!J2:J174, "Prepaid", Master_Orders!K2:K174, "In Transit") | K8: =E8/B8
A9: 2026-06-30 | B9: =COUNTIFS(Master_Orders!D2:D174, "2026-06-30", Master_Orders!J2:J174, "Prepaid") | C9: =SUMIFS(Master_Orders!E2:E174, Master_Orders!D2:D174, "2026-06-30", Master_Orders!J2:J174, "Prepaid") | D9: =C9/B9 | E9: =COUNTIFS(Master_Orders!D2:D174, "2026-06-30", Master_Orders!J2:J174, "Prepaid", Master_Orders!K2:K174, "Delivered") | F9: =SUMIFS(Master_Orders!E2:E174, Master_Orders!D2:D174, "2026-06-30", Master_Orders!J2:J174, "Prepaid", Master_Orders!K2:K174, "Delivered") | G9: =COUNTIFS(Master_Orders!D2:D174, "2026-06-30", Master_Orders!J2:J174, "Prepaid", Master_Orders!K2:K174, "RTO / Returned") | H9: =SUMIFS(Master_Orders!E2:E174, Master_Orders!D2:D174, "2026-06-30", Master_Orders!J2:J174, "Prepaid", Master_Orders!K2:K174, "RTO / Returned") | I9: =COUNTIFS(Master_Orders!D2:D174, "2026-06-30", Master_Orders!J2:J174, "Prepaid", Master_Orders!K2:K174, "Canceled") | J9: =COUNTIFS(Master_Orders!D2:D174, "2026-06-30", Master_Orders!J2:J174, "Prepaid", Master_Orders!K2:K174, "In Transit") | K9: =E9/B9
A10: 2026-07-01 | B10: =COUNTIFS(Master_Orders!D2:D174, "2026-07-01", Master_Orders!J2:J174, "Prepaid") | C10: =SUMIFS(Master_Orders!E2:E174, Master_Orders!D2:D174, "2026-07-01", Master_Orders!J2:J174, "Prepaid") | D10: =C10/B10 | E10: =COUNTIFS(Master_Orders!D2:D174, "2026-07-01", Master_Orders!J2:J174, "Prepaid", Master_Orders!K2:K174, "Delivered") | F10: =SUMIFS(Master_Orders!E2:E174, Master_Orders!D2:D174, "2026-07-01", Master_Orders!J2:J174, "Prepaid", Master_Orders!K2:K174, "Delivered") | G10: =COUNTIFS(Master_Orders!D2:D174, "2026-07-01", Master_Orders!J2:J174, "Prepaid", Master_Orders!K2:K174, "RTO / Returned") | H10: =SUMIFS(Master_Orders!E2:E174, Master_Orders!D2:D174, "2026-07-01", Master_Orders!J2:J174, "Prepaid", Master_Orders!K2:K174, "RTO / Returned") | I10: =COUNTIFS(Master_Orders!D2:D174, "2026-07-01", Master_Orders!J2:J174, "Prepaid", Master_Orders!K2:K174, "Canceled") | J10: =COUNTIFS(Master_Orders!D2:D174, "2026-07-01", Master_Orders!J2:J174, "Prepaid", Master_Orders!K2:K174, "In Transit") | K10: =E10/B10
A11: 2026-07-02 | B11: =COUNTIFS(Master_Orders!D2:D174, "2026-07-02", Master_Orders!J2:J174, "Prepaid") | C11: =SUMIFS(Master_Orders!E2:E174, Master_Orders!D2:D174, "2026-07-02", Master_Orders!J2:J174, "Prepaid") | D11: =C11/B11 | E11: =COUNTIFS(Master_Orders!D2:D174, "2026-07-02", Master_Orders!J2:J174, "Prepaid", Master_Orders!K2:K174, "Delivered") | F11: =SUMIFS(Master_Orders!E2:E174, Master_Orders!D2:D174, "2026-07-02", Master_Orders!J2:J174, "Prepaid", Master_Orders!K2:K174, "Delivered") | G11: =COUNTIFS(Master_Orders!D2:D174, "2026-07-02", Master_Orders!J2:J174, "Prepaid", Master_Orders!K2:K174, "RTO / Returned") | H11: =SUMIFS(Master_Orders!E2:E174, Master_Orders!D2:D174, "2026-07-02", Master_Orders!J2:J174, "Prepaid", Master_Orders!K2:K174, "RTO / Returned") | I11: =COUNTIFS(Master_Orders!D2:D174, "2026-07-02", Master_Orders!J2:J174, "Prepaid", Master_Orders!K2:K174, "Canceled") | J11: =COUNTIFS(Master_Orders!D2:D174, "2026-07-02", Master_Orders!J2:J174, "Prepaid", Master_Orders!K2:K174, "In Transit") | K11: =E11/B11
A12: 2026-07-03 | B12: =COUNTIFS(Master_Orders!D2:D174, "2026-07-03", Master_Orders!J2:J174, "Prepaid") | C12: =SUMIFS(Master_Orders!E2:E174, Master_Orders!D2:D174, "2026-07-03", Master_Orders!J2:J174, "Prepaid") | D12: =C12/B12 | E12: =COUNTIFS(Master_Orders!D2:D174, "2026-07-03", Master_Orders!J2:J174, "Prepaid", Master_Orders!K2:K174, "Delivered") | F12: =SUMIFS(Master_Orders!E2:E174, Master_Orders!D2:D174, "2026-07-03", Master_Orders!J2:J174, "Prepaid", Master_Orders!K2:K174, "Delivered") | G12: =COUNTIFS(Master_Orders!D2:D174, "2026-07-03", Master_Orders!J2:J174, "Prepaid", Master_Orders!K2:K174, "RTO / Returned") | H12: =SUMIFS(Master_Orders!E2:E174, Master_Orders!D2:D174, "2026-07-03", Master_Orders!J2:J174, "Prepaid", Master_Orders!K2:K174, "RTO / Returned") | I12: =COUNTIFS(Master_Orders!D2:D174, "2026-07-03", Master_Orders!J2:J174, "Prepaid", Master_Orders!K2:K174, "Canceled") | J12: =COUNTIFS(Master_Orders!D2:D174, "2026-07-03", Master_Orders!J2:J174, "Prepaid", Master_Orders!K2:K174, "In Transit") | K12: =E12/B12
A13: 2026-07-04 | B13: =COUNTIFS(Master_Orders!D2:D174, "2026-07-04", Master_Orders!J2:J174, "Prepaid") | C13: =SUMIFS(Master_Orders!E2:E174, Master_Orders!D2:D174, "2026-07-04", Master_Orders!J2:J174, "Prepaid") | D13: =C13/B13 | E13: =COUNTIFS(Master_Orders!D2:D174, "2026-07-04", Master_Orders!J2:J174, "Prepaid", Master_Orders!K2:K174, "Delivered") | F13: =SUMIFS(Master_Orders!E2:E174, Master_Orders!D2:D174, "2026-07-04", Master_Orders!J2:J174, "Prepaid", Master_Orders!K2:K174, "Delivered") | G13: =COUNTIFS(Master_Orders!D2:D174, "2026-07-04", Master_Orders!J2:J174, "Prepaid", Master_Orders!K2:K174, "RTO / Returned") | H13: =SUMIFS(Master_Orders!E2:E174, Master_Orders!D2:D174, "2026-07-04", Master_Orders!J2:J174, "Prepaid", Master_Orders!K2:K174, "RTO / Returned") | I13: =COUNTIFS(Master_Orders!D2:D174, "2026-07-04", Master_Orders!J2:J174, "Prepaid", Master_Orders!K2:K174, "Canceled") | J13: =COUNTIFS(Master_Orders!D2:D174, "2026-07-04", Master_Orders!J2:J174, "Prepaid", Master_Orders!K2:K174, "In Transit") | K13: =E13/B13
A14: 2026-07-05 | B14: =COUNTIFS(Master_Orders!D2:D174, "2026-07-05", Master_Orders!J2:J174, "Prepaid") | C14: =SUMIFS(Master_Orders!E2:E174, Master_Orders!D2:D174, "2026-07-05", Master_Orders!J2:J174, "Prepaid") | D14: =C14/B14 | E14: =COUNTIFS(Master_Orders!D2:D174, "2026-07-05", Master_Orders!J2:J174, "Prepaid", Master_Orders!K2:K174, "Delivered") | F14: =SUMIFS(Master_Orders!E2:E174, Master_Orders!D2:D174, "2026-07-05", Master_Orders!J2:J174, "Prepaid", Master_Orders!K2:K174, "Delivered") | G14: =COUNTIFS(Master_Orders!D2:D174, "2026-07-05", Master_Orders!J2:J174, "Prepaid", Master_Orders!K2:K174, "RTO / Returned") | H14: =SUMIFS(Master_Orders!E2:E174, Master_Orders!D2:D174, "2026-07-05", Master_Orders!J2:J174, "Prepaid", Master_Orders!K2:K174, "RTO / Returned") | I14: =COUNTIFS(Master_Orders!D2:D174, "2026-07-05", Master_Orders!J2:J174, "Prepaid", Master_Orders!K2:K174, "Canceled") | J14: =COUNTIFS(Master_Orders!D2:D174, "2026-07-05", Master_Orders!J2:J174, "Prepaid", Master_Orders!K2:K174, "In Transit") | K14: =E14/B14
A15: 2026-07-06 | B15: =COUNTIFS(Master_Orders!D2:D174, "2026-07-06", Master_Orders!J2:J174, "Prepaid") | C15: =SUMIFS(Master_Orders!E2:E174, Master_Orders!D2:D174, "2026-07-06", Master_Orders!J2:J174, "Prepaid") | D15: =C15/B15 | E15: =COUNTIFS(Master_Orders!D2:D174, "2026-07-06", Master_Orders!J2:J174, "Prepaid", Master_Orders!K2:K174, "Delivered") | F15: =SUMIFS(Master_Orders!E2:E174, Master_Orders!D2:D174, "2026-07-06", Master_Orders!J2:J174, "Prepaid", Master_Orders!K2:K174, "Delivered") | G15: =COUNTIFS(Master_Orders!D2:D174, "2026-07-06", Master_Orders!J2:J174, "Prepaid", Master_Orders!K2:K174, "RTO / Returned") | H15: =SUMIFS(Master_Orders!E2:E174, Master_Orders!D2:D174, "2026-07-06", Master_Orders!J2:J174, "Prepaid", Master_Orders!K2:K174, "RTO / Returned") | I15: =COUNTIFS(Master_Orders!D2:D174, "2026-07-06", Master_Orders!J2:J174, "Prepaid", Master_Orders!K2:K174, "Canceled") | J15: =COUNTIFS(Master_Orders!D2:D174, "2026-07-06", Master_Orders!J2:J174, "Prepaid", Master_Orders!K2:K174, "In Transit") | K15: =E15/B15
A16: 2026-07-07 | B16: =COUNTIFS(Master_Orders!D2:D174, "2026-07-07", Master_Orders!J2:J174, "Prepaid") | C16: =SUMIFS(Master_Orders!E2:E174, Master_Orders!D2:D174, "2026-07-07", Master_Orders!J2:J174, "Prepaid") | D16: =C16/B16 | E16: =COUNTIFS(Master_Orders!D2:D174, "2026-07-07", Master_Orders!J2:J174, "Prepaid", Master_Orders!K2:K174, "Delivered") | F16: =SUMIFS(Master_Orders!E2:E174, Master_Orders!D2:D174, "2026-07-07", Master_Orders!J2:J174, "Prepaid", Master_Orders!K2:K174, "Delivered") | G16: =COUNTIFS(Master_Orders!D2:D174, "2026-07-07", Master_Orders!J2:J174, "Prepaid", Master_Orders!K2:K174, "RTO / Returned") | H16: =SUMIFS(Master_Orders!E2:E174, Master_Orders!D2:D174, "2026-07-07", Master_Orders!J2:J174, "Prepaid", Master_Orders!K2:K174, "RTO / Returned") | I16: =COUNTIFS(Master_Orders!D2:D174, "2026-07-07", Master_Orders!J2:J174, "Prepaid", Master_Orders!K2:K174, "Canceled") | J16: =COUNTIFS(Master_Orders!D2:D174, "2026-07-07", Master_Orders!J2:J174, "Prepaid", Master_Orders!K2:K174, "In Transit") | K16: =E16/B16
A17: 2026-07-08 | B17: =COUNTIFS(Master_Orders!D2:D174, "2026-07-08", Master_Orders!J2:J174, "Prepaid") | C17: =SUMIFS(Master_Orders!E2:E174, Master_Orders!D2:D174, "2026-07-08", Master_Orders!J2:J174, "Prepaid") | D17: =C17/B17 | E17: =COUNTIFS(Master_Orders!D2:D174, "2026-07-08", Master_Orders!J2:J174, "Prepaid", Master_Orders!K2:K174, "Delivered") | F17: =SUMIFS(Master_Orders!E2:E174, Master_Orders!D2:D174, "2026-07-08", Master_Orders!J2:J174, "Prepaid", Master_Orders!K2:K174, "Delivered") | G17: =COUNTIFS(Master_Orders!D2:D174, "2026-07-08", Master_Orders!J2:J174, "Prepaid", Master_Orders!K2:K174, "RTO / Returned") | H17: =SUMIFS(Master_Orders!E2:E174, Master_Orders!D2:D174, "2026-07-08", Master_Orders!J2:J174, "Prepaid", Master_Orders!K2:K174, "RTO / Returned") | I17: =COUNTIFS(Master_Orders!D2:D174, "2026-07-08", Master_Orders!J2:J174, "Prepaid", Master_Orders!K2:K174, "Canceled") | J17: =COUNTIFS(Master_Orders!D2:D174, "2026-07-08", Master_Orders!J2:J174, "Prepaid", Master_Orders!K2:K174, "In Transit") | K17: =E17/B17
A18: 2026-07-09 | B18: =COUNTIFS(Master_Orders!D2:D174, "2026-07-09", Master_Orders!J2:J174, "Prepaid") | C18: =SUMIFS(Master_Orders!E2:E174, Master_Orders!D2:D174, "2026-07-09", Master_Orders!J2:J174, "Prepaid") | D18: =C18/B18 | E18: =COUNTIFS(Master_Orders!D2:D174, "2026-07-09", Master_Orders!J2:J174, "Prepaid", Master_Orders!K2:K174, "Delivered") | F18: =SUMIFS(Master_Orders!E2:E174, Master_Orders!D2:D174, "2026-07-09", Master_Orders!J2:J174, "Prepaid", Master_Orders!K2:K174, "Delivered") | G18: =COUNTIFS(Master_Orders!D2:D174, "2026-07-09", Master_Orders!J2:J174, "Prepaid", Master_Orders!K2:K174, "RTO / Returned") | H18: =SUMIFS(Master_Orders!E2:E174, Master_Orders!D2:D174, "2026-07-09", Master_Orders!J2:J174, "Prepaid", Master_Orders!K2:K174, "RTO / Returned") | I18: =COUNTIFS(Master_Orders!D2:D174, "2026-07-09", Master_Orders!J2:J174, "Prepaid", Master_Orders!K2:K174, "Canceled") | J18: =COUNTIFS(Master_Orders!D2:D174, "2026-07-09", Master_Orders!J2:J174, "Prepaid", Master_Orders!K2:K174, "In Transit") | K18: =E18/B18
A19: 2026-07-10 | B19: =COUNTIFS(Master_Orders!D2:D174, "2026-07-10", Master_Orders!J2:J174, "Prepaid") | C19: =SUMIFS(Master_Orders!E2:E174, Master_Orders!D2:D174, "2026-07-10", Master_Orders!J2:J174, "Prepaid") | D19: =C19/B19 | E19: =COUNTIFS(Master_Orders!D2:D174, "2026-07-10", Master_Orders!J2:J174, "Prepaid", Master_Orders!K2:K174, "Delivered") | F19: =SUMIFS(Master_Orders!E2:E174, Master_Orders!D2:D174, "2026-07-10", Master_Orders!J2:J174, "Prepaid", Master_Orders!K2:K174, "Delivered") | G19: =COUNTIFS(Master_Orders!D2:D174, "2026-07-10", Master_Orders!J2:J174, "Prepaid", Master_Orders!K2:K174, "RTO / Returned") | H19: =SUMIFS(Master_Orders!E2:E174, Master_Orders!D2:D174, "2026-07-10", Master_Orders!J2:J174, "Prepaid", Master_Orders!K2:K174, "RTO / Returned") | I19: =COUNTIFS(Master_Orders!D2:D174, "2026-07-10", Master_Orders!J2:J174, "Prepaid", Master_Orders!K2:K174, "Canceled") | J19: =COUNTIFS(Master_Orders!D2:D174, "2026-07-10", Master_Orders!J2:J174, "Prepaid", Master_Orders!K2:K174, "In Transit") | K19: =E19/B19
A20: 2026-07-11 | B20: =COUNTIFS(Master_Orders!D2:D174, "2026-07-11", Master_Orders!J2:J174, "Prepaid") | C20: =SUMIFS(Master_Orders!E2:E174, Master_Orders!D2:D174, "2026-07-11", Master_Orders!J2:J174, "Prepaid") | D20: =C20/B20 | E20: =COUNTIFS(Master_Orders!D2:D174, "2026-07-11", Master_Orders!J2:J174, "Prepaid", Master_Orders!K2:K174, "Delivered") | F20: =SUMIFS(Master_Orders!E2:E174, Master_Orders!D2:D174, "2026-07-11", Master_Orders!J2:J174, "Prepaid", Master_Orders!K2:K174, "Delivered") | G20: =COUNTIFS(Master_Orders!D2:D174, "2026-07-11", Master_Orders!J2:J174, "Prepaid", Master_Orders!K2:K174, "RTO / Returned") | H20: =SUMIFS(Master_Orders!E2:E174, Master_Orders!D2:D174, "2026-07-11", Master_Orders!J2:J174, "Prepaid", Master_Orders!K2:K174, "RTO / Returned") | I20: =COUNTIFS(Master_Orders!D2:D174, "2026-07-11", Master_Orders!J2:J174, "Prepaid", Master_Orders!K2:K174, "Canceled") | J20: =COUNTIFS(Master_Orders!D2:D174, "2026-07-11", Master_Orders!J2:J174, "Prepaid", Master_Orders!K2:K174, "In Transit") | K20: =E20/B20
A21: 2026-07-12 | B21: =COUNTIFS(Master_Orders!D2:D174, "2026-07-12", Master_Orders!J2:J174, "Prepaid") | C21: =SUMIFS(Master_Orders!E2:E174, Master_Orders!D2:D174, "2026-07-12", Master_Orders!J2:J174, "Prepaid") | D21: =C21/B21 | E21: =COUNTIFS(Master_Orders!D2:D174, "2026-07-12", Master_Orders!J2:J174, "Prepaid", Master_Orders!K2:K174, "Delivered") | F21: =SUMIFS(Master_Orders!E2:E174, Master_Orders!D2:D174, "2026-07-12", Master_Orders!J2:J174, "Prepaid", Master_Orders!K2:K174, "Delivered") | G21: =COUNTIFS(Master_Orders!D2:D174, "2026-07-12", Master_Orders!J2:J174, "Prepaid", Master_Orders!K2:K174, "RTO / Returned") | H21: =SUMIFS(Master_Orders!E2:E174, Master_Orders!D2:D174, "2026-07-12", Master_Orders!J2:J174, "Prepaid", Master_Orders!K2:K174, "RTO / Returned") | I21: =COUNTIFS(Master_Orders!D2:D174, "2026-07-12", Master_Orders!J2:J174, "Prepaid", Master_Orders!K2:K174, "Canceled") | J21: =COUNTIFS(Master_Orders!D2:D174, "2026-07-12", Master_Orders!J2:J174, "Prepaid", Master_Orders!K2:K174, "In Transit") | K21: =E21/B21
A22: 2026-07-13 | B22: =COUNTIFS(Master_Orders!D2:D174, "2026-07-13", Master_Orders!J2:J174, "Prepaid") | C22: =SUMIFS(Master_Orders!E2:E174, Master_Orders!D2:D174, "2026-07-13", Master_Orders!J2:J174, "Prepaid") | D22: =C22/B22 | E22: =COUNTIFS(Master_Orders!D2:D174, "2026-07-13", Master_Orders!J2:J174, "Prepaid", Master_Orders!K2:K174, "Delivered") | F22: =SUMIFS(Master_Orders!E2:E174, Master_Orders!D2:D174, "2026-07-13", Master_Orders!J2:J174, "Prepaid", Master_Orders!K2:K174, "Delivered") | G22: =COUNTIFS(Master_Orders!D2:D174, "2026-07-13", Master_Orders!J2:J174, "Prepaid", Master_Orders!K2:K174, "RTO / Returned") | H22: =SUMIFS(Master_Orders!E2:E174, Master_Orders!D2:D174, "2026-07-13", Master_Orders!J2:J174, "Prepaid", Master_Orders!K2:K174, "RTO / Returned") | I22: =COUNTIFS(Master_Orders!D2:D174, "2026-07-13", Master_Orders!J2:J174, "Prepaid", Master_Orders!K2:K174, "Canceled") | J22: =COUNTIFS(Master_Orders!D2:D174, "2026-07-13", Master_Orders!J2:J174, "Prepaid", Master_Orders!K2:K174, "In Transit") | K22: =E22/B22
A23: 2026-07-14 | B23: =COUNTIFS(Master_Orders!D2:D174, "2026-07-14", Master_Orders!J2:J174, "Prepaid") | C23: =SUMIFS(Master_Orders!E2:E174, Master_Orders!D2:D174, "2026-07-14", Master_Orders!J2:J174, "Prepaid") | D23: =C23/B23 | E23: =COUNTIFS(Master_Orders!D2:D174, "2026-07-14", Master_Orders!J2:J174, "Prepaid", Master_Orders!K2:K174, "Delivered") | F23: =SUMIFS(Master_Orders!E2:E174, Master_Orders!D2:D174, "2026-07-14", Master_Orders!J2:J174, "Prepaid", Master_Orders!K2:K174, "Delivered") | G23: =COUNTIFS(Master_Orders!D2:D174, "2026-07-14", Master_Orders!J2:J174, "Prepaid", Master_Orders!K2:K174, "RTO / Returned") | H23: =SUMIFS(Master_Orders!E2:E174, Master_Orders!D2:D174, "2026-07-14", Master_Orders!J2:J174, "Prepaid", Master_Orders!K2:K174, "RTO / Returned") | I23: =COUNTIFS(Master_Orders!D2:D174, "2026-07-14", Master_Orders!J2:J174, "Prepaid", Master_Orders!K2:K174, "Canceled") | J23: =COUNTIFS(Master_Orders!D2:D174, "2026-07-14", Master_Orders!J2:J174, "Prepaid", Master_Orders!K2:K174, "In Transit") | K23: =E23/B23
A24: 2026-07-15 | B24: =COUNTIFS(Master_Orders!D2:D174, "2026-07-15", Master_Orders!J2:J174, "Prepaid") | C24: =SUMIFS(Master_Orders!E2:E174, Master_Orders!D2:D174, "2026-07-15", Master_Orders!J2:J174, "Prepaid") | D24: =C24/B24 | E24: =COUNTIFS(Master_Orders!D2:D174, "2026-07-15", Master_Orders!J2:J174, "Prepaid", Master_Orders!K2:K174, "Delivered") | F24: =SUMIFS(Master_Orders!E2:E174, Master_Orders!D2:D174, "2026-07-15", Master_Orders!J2:J174, "Prepaid", Master_Orders!K2:K174, "Delivered") | G24: =COUNTIFS(Master_Orders!D2:D174, "2026-07-15", Master_Orders!J2:J174, "Prepaid", Master_Orders!K2:K174, "RTO / Returned") | H24: =SUMIFS(Master_Orders!E2:E174, Master_Orders!D2:D174, "2026-07-15", Master_Orders!J2:J174, "Prepaid", Master_Orders!K2:K174, "RTO / Returned") | I24: =COUNTIFS(Master_Orders!D2:D174, "2026-07-15", Master_Orders!J2:J174, "Prepaid", Master_Orders!K2:K174, "Canceled") | J24: =COUNTIFS(Master_Orders!D2:D174, "2026-07-15", Master_Orders!J2:J174, "Prepaid", Master_Orders!K2:K174, "In Transit") | K24: =E24/B24
A25: 2026-07-16 | B25: =COUNTIFS(Master_Orders!D2:D174, "2026-07-16", Master_Orders!J2:J174, "Prepaid") | C25: =SUMIFS(Master_Orders!E2:E174, Master_Orders!D2:D174, "2026-07-16", Master_Orders!J2:J174, "Prepaid") | D25: =C25/B25 | E25: =COUNTIFS(Master_Orders!D2:D174, "2026-07-16", Master_Orders!J2:J174, "Prepaid", Master_Orders!K2:K174, "Delivered") | F25: =SUMIFS(Master_Orders!E2:E174, Master_Orders!D2:D174, "2026-07-16", Master_Orders!J2:J174, "Prepaid", Master_Orders!K2:K174, "Delivered") | G25: =COUNTIFS(Master_Orders!D2:D174, "2026-07-16", Master_Orders!J2:J174, "Prepaid", Master_Orders!K2:K174, "RTO / Returned") | H25: =SUMIFS(Master_Orders!E2:E174, Master_Orders!D2:D174, "2026-07-16", Master_Orders!J2:J174, "Prepaid", Master_Orders!K2:K174, "RTO / Returned") | I25: =COUNTIFS(Master_Orders!D2:D174, "2026-07-16", Master_Orders!J2:J174, "Prepaid", Master_Orders!K2:K174, "Canceled") | J25: =COUNTIFS(Master_Orders!D2:D174, "2026-07-16", Master_Orders!J2:J174, "Prepaid", Master_Orders!K2:K174, "In Transit") | K25: =E25/B25
A26: 2026-07-17 | B26: =COUNTIFS(Master_Orders!D2:D174, "2026-07-17", Master_Orders!J2:J174, "Prepaid") | C26: =SUMIFS(Master_Orders!E2:E174, Master_Orders!D2:D174, "2026-07-17", Master_Orders!J2:J174, "Prepaid") | D26: =C26/B26 | E26: =COUNTIFS(Master_Orders!D2:D174, "2026-07-17", Master_Orders!J2:J174, "Prepaid", Master_Orders!K2:K174, "Delivered") | F26: =SUMIFS(Master_Orders!E2:E174, Master_Orders!D2:D174, "2026-07-17", Master_Orders!J2:J174, "Prepaid", Master_Orders!K2:K174, "Delivered") | G26: =COUNTIFS(Master_Orders!D2:D174, "2026-07-17", Master_Orders!J2:J174, "Prepaid", Master_Orders!K2:K174, "RTO / Returned") | H26: =SUMIFS(Master_Orders!E2:E174, Master_Orders!D2:D174, "2026-07-17", Master_Orders!J2:J174, "Prepaid", Master_Orders!K2:K174, "RTO / Returned") | I26: =COUNTIFS(Master_Orders!D2:D174, "2026-07-17", Master_Orders!J2:J174, "Prepaid", Master_Orders!K2:K174, "Canceled") | J26: =COUNTIFS(Master_Orders!D2:D174, "2026-07-17", Master_Orders!J2:J174, "Prepaid", Master_Orders!K2:K174, "In Transit") | K26: =E26/B26
A27: 2026-07-18 | B27: =COUNTIFS(Master_Orders!D2:D174, "2026-07-18", Master_Orders!J2:J174, "Prepaid") | C27: =SUMIFS(Master_Orders!E2:E174, Master_Orders!D2:D174, "2026-07-18", Master_Orders!J2:J174, "Prepaid") | D27: =C27/B27 | E27: =COUNTIFS(Master_Orders!D2:D174, "2026-07-18", Master_Orders!J2:J174, "Prepaid", Master_Orders!K2:K174, "Delivered") | F27: =SUMIFS(Master_Orders!E2:E174, Master_Orders!D2:D174, "2026-07-18", Master_Orders!J2:J174, "Prepaid", Master_Orders!K2:K174, "Delivered") | G27: =COUNTIFS(Master_Orders!D2:D174, "2026-07-18", Master_Orders!J2:J174, "Prepaid", Master_Orders!K2:K174, "RTO / Returned") | H27: =SUMIFS(Master_Orders!E2:E174, Master_Orders!D2:D174, "2026-07-18", Master_Orders!J2:J174, "Prepaid", Master_Orders!K2:K174, "RTO / Returned") | I27: =COUNTIFS(Master_Orders!D2:D174, "2026-07-18", Master_Orders!J2:J174, "Prepaid", Master_Orders!K2:K174, "Canceled") | J27: =COUNTIFS(Master_Orders!D2:D174, "2026-07-18", Master_Orders!J2:J174, "Prepaid", Master_Orders!K2:K174, "In Transit") | K27: =E27/B27
A28: 2026-07-19 | B28: =COUNTIFS(Master_Orders!D2:D174, "2026-07-19", Master_Orders!J2:J174, "Prepaid") | C28: =SUMIFS(Master_Orders!E2:E174, Master_Orders!D2:D174, "2026-07-19", Master_Orders!J2:J174, "Prepaid") | D28: =C28/B28 | E28: =COUNTIFS(Master_Orders!D2:D174, "2026-07-19", Master_Orders!J2:J174, "Prepaid", Master_Orders!K2:K174, "Delivered") | F28: =SUMIFS(Master_Orders!E2:E174, Master_Orders!D2:D174, "2026-07-19", Master_Orders!J2:J174, "Prepaid", Master_Orders!K2:K174, "Delivered") | G28: =COUNTIFS(Master_Orders!D2:D174, "2026-07-19", Master_Orders!J2:J174, "Prepaid", Master_Orders!K2:K174, "RTO / Returned") | H28: =SUMIFS(Master_Orders!E2:E174, Master_Orders!D2:D174, "2026-07-19", Master_Orders!J2:J174, "Prepaid", Master_Orders!K2:K174, "RTO / Returned") | I28: =COUNTIFS(Master_Orders!D2:D174, "2026-07-19", Master_Orders!J2:J174, "Prepaid", Master_Orders!K2:K174, "Canceled") | J28: =COUNTIFS(Master_Orders!D2:D174, "2026-07-19", Master_Orders!J2:J174, "Prepaid", Master_Orders!K2:K174, "In Transit") | K28: =E28/B28
A29: 2026-07-20 | B29: =COUNTIFS(Master_Orders!D2:D174, "2026-07-20", Master_Orders!J2:J174, "Prepaid") | C29: =SUMIFS(Master_Orders!E2:E174, Master_Orders!D2:D174, "2026-07-20", Master_Orders!J2:J174, "Prepaid") | D29: =C29/B29 | E29: =COUNTIFS(Master_Orders!D2:D174, "2026-07-20", Master_Orders!J2:J174, "Prepaid", Master_Orders!K2:K174, "Delivered") | F29: =SUMIFS(Master_Orders!E2:E174, Master_Orders!D2:D174, "2026-07-20", Master_Orders!J2:J174, "Prepaid", Master_Orders!K2:K174, "Delivered") | G29: =COUNTIFS(Master_Orders!D2:D174, "2026-07-20", Master_Orders!J2:J174, "Prepaid", Master_Orders!K2:K174, "RTO / Returned") | H29: =SUMIFS(Master_Orders!E2:E174, Master_Orders!D2:D174, "2026-07-20", Master_Orders!J2:J174, "Prepaid", Master_Orders!K2:K174, "RTO / Returned") | I29: =COUNTIFS(Master_Orders!D2:D174, "2026-07-20", Master_Orders!J2:J174, "Prepaid", Master_Orders!K2:K174, "Canceled") | J29: =COUNTIFS(Master_Orders!D2:D174, "2026-07-20", Master_Orders!J2:J174, "Prepaid", Master_Orders!K2:K174, "In Transit") | K29: =E29/B29
A30: 2026-07-21 | B30: =COUNTIFS(Master_Orders!D2:D174, "2026-07-21", Master_Orders!J2:J174, "Prepaid") | C30: =SUMIFS(Master_Orders!E2:E174, Master_Orders!D2:D174, "2026-07-21", Master_Orders!J2:J174, "Prepaid") | D30: =C30/B30 | E30: =COUNTIFS(Master_Orders!D2:D174, "2026-07-21", Master_Orders!J2:J174, "Prepaid", Master_Orders!K2:K174, "Delivered") | F30: =SUMIFS(Master_Orders!E2:E174, Master_Orders!D2:D174, "2026-07-21", Master_Orders!J2:J174, "Prepaid", Master_Orders!K2:K174, "Delivered") | G30: =COUNTIFS(Master_Orders!D2:D174, "2026-07-21", Master_Orders!J2:J174, "Prepaid", Master_Orders!K2:K174, "RTO / Returned") | H30: =SUMIFS(Master_Orders!E2:E174, Master_Orders!D2:D174, "2026-07-21", Master_Orders!J2:J174, "Prepaid", Master_Orders!K2:K174, "RTO / Returned") | I30: =COUNTIFS(Master_Orders!D2:D174, "2026-07-21", Master_Orders!J2:J174, "Prepaid", Master_Orders!K2:K174, "Canceled") | J30: =COUNTIFS(Master_Orders!D2:D174, "2026-07-21", Master_Orders!J2:J174, "Prepaid", Master_Orders!K2:K174, "In Transit") | K30: =E30/B30
A31: 2026-07-22 | B31: =COUNTIFS(Master_Orders!D2:D174, "2026-07-22", Master_Orders!J2:J174, "Prepaid") | C31: =SUMIFS(Master_Orders!E2:E174, Master_Orders!D2:D174, "2026-07-22", Master_Orders!J2:J174, "Prepaid") | D31: =C31/B31 | E31: =COUNTIFS(Master_Orders!D2:D174, "2026-07-22", Master_Orders!J2:J174, "Prepaid", Master_Orders!K2:K174, "Delivered") | F31: =SUMIFS(Master_Orders!E2:E174, Master_Orders!D2:D174, "2026-07-22", Master_Orders!J2:J174, "Prepaid", Master_Orders!K2:K174, "Delivered") | G31: =COUNTIFS(Master_Orders!D2:D174, "2026-07-22", Master_Orders!J2:J174, "Prepaid", Master_Orders!K2:K174, "RTO / Returned") | H31: =SUMIFS(Master_Orders!E2:E174, Master_Orders!D2:D174, "2026-07-22", Master_Orders!J2:J174, "Prepaid", Master_Orders!K2:K174, "RTO / Returned") | I31: =COUNTIFS(Master_Orders!D2:D174, "2026-07-22", Master_Orders!J2:J174, "Prepaid", Master_Orders!K2:K174, "Canceled") | J31: =COUNTIFS(Master_Orders!D2:D174, "2026-07-22", Master_Orders!J2:J174, "Prepaid", Master_Orders!K2:K174, "In Transit") | K31: =E31/B31
A32: 2026-07-23 | B32: =COUNTIFS(Master_Orders!D2:D174, "2026-07-23", Master_Orders!J2:J174, "Prepaid") | C32: =SUMIFS(Master_Orders!E2:E174, Master_Orders!D2:D174, "2026-07-23", Master_Orders!J2:J174, "Prepaid") | D32: =C32/B32 | E32: =COUNTIFS(Master_Orders!D2:D174, "2026-07-23", Master_Orders!J2:J174, "Prepaid", Master_Orders!K2:K174, "Delivered") | F32: =SUMIFS(Master_Orders!E2:E174, Master_Orders!D2:D174, "2026-07-23", Master_Orders!J2:J174, "Prepaid", Master_Orders!K2:K174, "Delivered") | G32: =COUNTIFS(Master_Orders!D2:D174, "2026-07-23", Master_Orders!J2:J174, "Prepaid", Master_Orders!K2:K174, "RTO / Returned") | H32: =SUMIFS(Master_Orders!E2:E174, Master_Orders!D2:D174, "2026-07-23", Master_Orders!J2:J174, "Prepaid", Master_Orders!K2:K174, "RTO / Returned") | I32: =COUNTIFS(Master_Orders!D2:D174, "2026-07-23", Master_Orders!J2:J174, "Prepaid", Master_Orders!K2:K174, "Canceled") | J32: =COUNTIFS(Master_Orders!D2:D174, "2026-07-23", Master_Orders!J2:J174, "Prepaid", Master_Orders!K2:K174, "In Transit") | K32: =E32/B32
A33: 2026-07-24 | B33: =COUNTIFS(Master_Orders!D2:D174, "2026-07-24", Master_Orders!J2:J174, "Prepaid") | C33: =SUMIFS(Master_Orders!E2:E174, Master_Orders!D2:D174, "2026-07-24", Master_Orders!J2:J174, "Prepaid") | D33: =C33/B33 | E33: =COUNTIFS(Master_Orders!D2:D174, "2026-07-24", Master_Orders!J2:J174, "Prepaid", Master_Orders!K2:K174, "Delivered") | F33: =SUMIFS(Master_Orders!E2:E174, Master_Orders!D2:D174, "2026-07-24", Master_Orders!J2:J174, "Prepaid", Master_Orders!K2:K174, "Delivered") | G33: =COUNTIFS(Master_Orders!D2:D174, "2026-07-24", Master_Orders!J2:J174, "Prepaid", Master_Orders!K2:K174, "RTO / Returned") | H33: =SUMIFS(Master_Orders!E2:E174, Master_Orders!D2:D174, "2026-07-24", Master_Orders!J2:J174, "Prepaid", Master_Orders!K2:K174, "RTO / Returned") | I33: =COUNTIFS(Master_Orders!D2:D174, "2026-07-24", Master_Orders!J2:J174, "Prepaid", Master_Orders!K2:K174, "Canceled") | J33: =COUNTIFS(Master_Orders!D2:D174, "2026-07-24", Master_Orders!J2:J174, "Prepaid", Master_Orders!K2:K174, "In Transit") | K33: =E33/B33
A34: 2026-07-25 | B34: =COUNTIFS(Master_Orders!D2:D174, "2026-07-25", Master_Orders!J2:J174, "Prepaid") | C34: =SUMIFS(Master_Orders!E2:E174, Master_Orders!D2:D174, "2026-07-25", Master_Orders!J2:J174, "Prepaid") | D34: =C34/B34 | E34: =COUNTIFS(Master_Orders!D2:D174, "2026-07-25", Master_Orders!J2:J174, "Prepaid", Master_Orders!K2:K174, "Delivered") | F34: =SUMIFS(Master_Orders!E2:E174, Master_Orders!D2:D174, "2026-07-25", Master_Orders!J2:J174, "Prepaid", Master_Orders!K2:K174, "Delivered") | G34: =COUNTIFS(Master_Orders!D2:D174, "2026-07-25", Master_Orders!J2:J174, "Prepaid", Master_Orders!K2:K174, "RTO / Returned") | H34: =SUMIFS(Master_Orders!E2:E174, Master_Orders!D2:D174, "2026-07-25", Master_Orders!J2:J174, "Prepaid", Master_Orders!K2:K174, "RTO / Returned") | I34: =COUNTIFS(Master_Orders!D2:D174, "2026-07-25", Master_Orders!J2:J174, "Prepaid", Master_Orders!K2:K174, "Canceled") | J34: =COUNTIFS(Master_Orders!D2:D174, "2026-07-25", Master_Orders!J2:J174, "Prepaid", Master_Orders!K2:K174, "In Transit") | K34: =E34/B34
A35: 2026-07-26 | B35: =COUNTIFS(Master_Orders!D2:D174, "2026-07-26", Master_Orders!J2:J174, "Prepaid") | C35: =SUMIFS(Master_Orders!E2:E174, Master_Orders!D2:D174, "2026-07-26", Master_Orders!J2:J174, "Prepaid") | D35: =C35/B35 | E35: =COUNTIFS(Master_Orders!D2:D174, "2026-07-26", Master_Orders!J2:J174, "Prepaid", Master_Orders!K2:K174, "Delivered") | F35: =SUMIFS(Master_Orders!E2:E174, Master_Orders!D2:D174, "2026-07-26", Master_Orders!J2:J174, "Prepaid", Master_Orders!K2:K174, "Delivered") | G35: =COUNTIFS(Master_Orders!D2:D174, "2026-07-26", Master_Orders!J2:J174, "Prepaid", Master_Orders!K2:K174, "RTO / Returned") | H35: =SUMIFS(Master_Orders!E2:E174, Master_Orders!D2:D174, "2026-07-26", Master_Orders!J2:J174, "Prepaid", Master_Orders!K2:K174, "RTO / Returned") | I35: =COUNTIFS(Master_Orders!D2:D174, "2026-07-26", Master_Orders!J2:J174, "Prepaid", Master_Orders!K2:K174, "Canceled") | J35: =COUNTIFS(Master_Orders!D2:D174, "2026-07-26", Master_Orders!J2:J174, "Prepaid", Master_Orders!K2:K174, "In Transit") | K35: =E35/B35
A36: 2026-07-27 | B36: =COUNTIFS(Master_Orders!D2:D174, "2026-07-27", Master_Orders!J2:J174, "Prepaid") | C36: =SUMIFS(Master_Orders!E2:E174, Master_Orders!D2:D174, "2026-07-27", Master_Orders!J2:J174, "Prepaid") | D36: =C36/B36 | E36: =COUNTIFS(Master_Orders!D2:D174, "2026-07-27", Master_Orders!J2:J174, "Prepaid", Master_Orders!K2:K174, "Delivered") | F36: =SUMIFS(Master_Orders!E2:E174, Master_Orders!D2:D174, "2026-07-27", Master_Orders!J2:J174, "Prepaid", Master_Orders!K2:K174, "Delivered") | G36: =COUNTIFS(Master_Orders!D2:D174, "2026-07-27", Master_Orders!J2:J174, "Prepaid", Master_Orders!K2:K174, "RTO / Returned") | H36: =SUMIFS(Master_Orders!E2:E174, Master_Orders!D2:D174, "2026-07-27", Master_Orders!J2:J174, "Prepaid", Master_Orders!K2:K174, "RTO / Returned") | I36: =COUNTIFS(Master_Orders!D2:D174, "2026-07-27", Master_Orders!J2:J174, "Prepaid", Master_Orders!K2:K174, "Canceled") | J36: =COUNTIFS(Master_Orders!D2:D174, "2026-07-27", Master_Orders!J2:J174, "Prepaid", Master_Orders!K2:K174, "In Transit") | K36: =E36/B36
A37: 2026-07-28 | B37: =COUNTIFS(Master_Orders!D2:D174, "2026-07-28", Master_Orders!J2:J174, "Prepaid") | C37: =SUMIFS(Master_Orders!E2:E174, Master_Orders!D2:D174, "2026-07-28", Master_Orders!J2:J174, "Prepaid") | D37: =C37/B37 | E37: =COUNTIFS(Master_Orders!D2:D174, "2026-07-28", Master_Orders!J2:J174, "Prepaid", Master_Orders!K2:K174, "Delivered") | F37: =SUMIFS(Master_Orders!E2:E174, Master_Orders!D2:D174, "2026-07-28", Master_Orders!J2:J174, "Prepaid", Master_Orders!K2:K174, "Delivered") | G37: =COUNTIFS(Master_Orders!D2:D174, "2026-07-28", Master_Orders!J2:J174, "Prepaid", Master_Orders!K2:K174, "RTO / Returned") | H37: =SUMIFS(Master_Orders!E2:E174, Master_Orders!D2:D174, "2026-07-28", Master_Orders!J2:J174, "Prepaid", Master_Orders!K2:K174, "RTO / Returned") | I37: =COUNTIFS(Master_Orders!D2:D174, "2026-07-28", Master_Orders!J2:J174, "Prepaid", Master_Orders!K2:K174, "Canceled") | J37: =COUNTIFS(Master_Orders!D2:D174, "2026-07-28", Master_Orders!J2:J174, "Prepaid", Master_Orders!K2:K174, "In Transit") | K37: =E37/B37
A38: 2026-07-29 | B38: =COUNTIFS(Master_Orders!D2:D174, "2026-07-29", Master_Orders!J2:J174, "Prepaid") | C38: =SUMIFS(Master_Orders!E2:E174, Master_Orders!D2:D174, "2026-07-29", Master_Orders!J2:J174, "Prepaid") | D38: =C38/B38 | E38: =COUNTIFS(Master_Orders!D2:D174, "2026-07-29", Master_Orders!J2:J174, "Prepaid", Master_Orders!K2:K174, "Delivered") | F38: =SUMIFS(Master_Orders!E2:E174, Master_Orders!D2:D174, "2026-07-29", Master_Orders!J2:J174, "Prepaid", Master_Orders!K2:K174, "Delivered") | G38: =COUNTIFS(Master_Orders!D2:D174, "2026-07-29", Master_Orders!J2:J174, "Prepaid", Master_Orders!K2:K174, "RTO / Returned") | H38: =SUMIFS(Master_Orders!E2:E174, Master_Orders!D2:D174, "2026-07-29", Master_Orders!J2:J174, "Prepaid", Master_Orders!K2:K174, "RTO / Returned") | I38: =COUNTIFS(Master_Orders!D2:D174, "2026-07-29", Master_Orders!J2:J174, "Prepaid", Master_Orders!K2:K174, "Canceled") | J38: =COUNTIFS(Master_Orders!D2:D174, "2026-07-29", Master_Orders!J2:J174, "Prepaid", Master_Orders!K2:K174, "In Transit") | K38: =E38/B38
A39: 2026-07-30 | B39: =COUNTIFS(Master_Orders!D2:D174, "2026-07-30", Master_Orders!J2:J174, "Prepaid") | C39: =SUMIFS(Master_Orders!E2:E174, Master_Orders!D2:D174, "2026-07-30", Master_Orders!J2:J174, "Prepaid") | D39: =C39/B39 | E39: =COUNTIFS(Master_Orders!D2:D174, "2026-07-30", Master_Orders!J2:J174, "Prepaid", Master_Orders!K2:K174, "Delivered") | F39: =SUMIFS(Master_Orders!E2:E174, Master_Orders!D2:D174, "2026-07-30", Master_Orders!J2:J174, "Prepaid", Master_Orders!K2:K174, "Delivered") | G39: =COUNTIFS(Master_Orders!D2:D174, "2026-07-30", Master_Orders!J2:J174, "Prepaid", Master_Orders!K2:K174, "RTO / Returned") | H39: =SUMIFS(Master_Orders!E2:E174, Master_Orders!D2:D174, "2026-07-30", Master_Orders!J2:J174, "Prepaid", Master_Orders!K2:K174, "RTO / Returned") | I39: =COUNTIFS(Master_Orders!D2:D174, "2026-07-30", Master_Orders!J2:J174, "Prepaid", Master_Orders!K2:K174, "Canceled") | J39: =COUNTIFS(Master_Orders!D2:D174, "2026-07-30", Master_Orders!J2:J174, "Prepaid", Master_Orders!K2:K174, "In Transit") | K39: =E39/B39
A40: Total Prepaid Summary | B40: =SUM(B4:B39) | C40: =SUM(C4:C39) | D40: =C40/B40 | E40: =SUM(E4:E39) | F40: =SUM(F4:F39) | G40: =SUM(G4:G39) | H40: =SUM(H4:H39) | I40: =SUM(I4:I39) | J40: =SUM(J4:J39) | K40: =E40/B40

Sheet Day_Wise_Report
A1: JANVI AIKA - DAILY ORDER PERFORMANCE: COD vs. PARTIAL COD vs. PREPAID
A3: Order Date | B3: Total Orders | C3: COD Orders | D3: Partial COD Orders | E3: Prepaid Orders | F3: Total Revenue (Rs.) | G3: COD Revenue (Rs.) | H3: Partial COD Revenue (Rs.) | I3: Prepaid Revenue (Rs.) | J3: Delivered Count | K3: RTO Count | L3: Canceled Count | M3: In Transit Count
A4: 2026-06-22 | B4: =COUNTIF(Master_Orders!D2:D174, "2026-06-22") | C4: =COUNTIFS(Master_Orders!D2:D174, "2026-06-22", Master_Orders!J2:J174, "COD") | D4: =COUNTIFS(Master_Orders!D2:D174, "2026-06-22", Master_Orders!J2:J174, "Partial COD") | E4: =COUNTIFS(Master_Orders!D2:D174, "2026-06-22", Master_Orders!J2:J174, "Prepaid") | F4: =SUMIF(Master_Orders!D2:D174, "2026-06-22", Master_Orders!E2:E174) | G4: =SUMIFS(Master_Orders!E2:E174, Master_Orders!D2:D174, "2026-06-22", Master_Orders!J2:J174, "COD") | H4: =SUMIFS(Master_Orders!E2:E174, Master_Orders!D2:D174, "2026-06-22", Master_Orders!J2:J174, "Partial COD") | I4: =SUMIFS(Master_Orders!E2:E174, Master_Orders!D2:D174, "2026-06-22", Master_Orders!J2:J174, "Prepaid") | J4: =COUNTIFS(Master_Orders!D2:D174, "2026-06-22", Master_Orders!K2:K174, "Delivered") | K4: =COUNTIFS(Master_Orders!D2:D174, "2026-06-22", Master_Orders!K2:K174, "RTO / Returned") | L4: =COUNTIFS(Master_Orders!D2:D174, "2026-06-22", Master_Orders!K2:K174, "Canceled") | M4: =COUNTIFS(Master_Orders!D2:D174, "2026-06-22", Master_Orders!K2:K174, "In Transit")
A5: 2026-06-24 | B5: =COUNTIF(Master_Orders!D2:D174, "2026-06-24") | C5: =COUNTIFS(Master_Orders!D2:D174, "2026-06-24", Master_Orders!J2:J174, "COD") | D5: =COUNTIFS(Master_Orders!D2:D174, "2026-06-24", Master_Orders!J2:J174, "Partial COD") | E5: =COUNTIFS(Master_Orders!D2:D174, "2026-06-24", Master_Orders!J2:J174, "Prepaid") | F5: =SUMIF(Master_Orders!D2:D174, "2026-06-24", Master_Orders!E2:E174) | G5: =SUMIFS(Master_Orders!E2:E174, Master_Orders!D2:D174, "2026-06-24", Master_Orders!J2:J174, "COD") | H5: =SUMIFS(Master_Orders!E2:E174, Master_Orders!D2:D174, "2026-06-24", Master_Orders!J2:J174, "Partial COD") | I5: =SUMIFS(Master_Orders!E2:E174, Master_Orders!D2:D174, "2026-06-24", Master_Orders!J2:J174, "Prepaid") | J5: =COUNTIFS(Master_Orders!D2:D174, "2026-06-24", Master_Orders!K2:K174, "Delivered") | K5: =COUNTIFS(Master_Orders!D2:D174, "2026-06-24", Master_Orders!K2:K174, "RTO / Returned") | L5: =COUNTIFS(Master_Orders!D2:D174, "2026-06-24", Master_Orders!K2:K174, "Canceled") | M5: =COUNTIFS(Master_Orders!D2:D174, "2026-06-24", Master_Orders!K2:K174, "In Transit")
A6: 2026-06-25 | B6: =COUNTIF(Master_Orders!D2:D174, "2026-06-25") | C6: =COUNTIFS(Master_Orders!D2:D174, "2026-06-25", Master_Orders!J2:J174, "COD") | D6: =COUNTIFS(Master_Orders!D2:D174, "2026-06-25", Master_Orders!J2:J174, "Partial COD") | E6: =COUNTIFS(Master_Orders!D2:D174, "2026-06-25", Master_Orders!J2:J174, "Prepaid") | F6: =SUMIF(Master_Orders!D2:D174, "2026-06-25", Master_Orders!E2:E174) | G6: =SUMIFS(Master_Orders!E2:E174, Master_Orders!D2:D174, "2026-06-25", Master_Orders!J2:J174, "COD") | H6: =SUMIFS(Master_Orders!E2:E174, Master_Orders!D2:D174, "2026-06-25", Master_Orders!J2:J174, "Partial COD") | I6: =SUMIFS(Master_Orders!E2:E174, Master_Orders!D2:D174, "2026-06-25", Master_Orders!J2:J174, "Prepaid") | J6: =COUNTIFS(Master_Orders!D2:D174, "2026-06-25", Master_Orders!K2:K174, "Delivered") | K6: =COUNTIFS(Master_Orders!D2:D174, "2026-06-25", Master_Orders!K2:K174, "RTO / Returned") | L6: =COUNTIFS(Master_Orders!D2:D174, "2026-06-25", Master_Orders!K2:K174, "Canceled") | M6: =COUNTIFS(Master_Orders!D2:D174, "2026-06-25", Master_Orders!K2:K174, "In Transit")
A7: 2026-06-27 | B7: =COUNTIF(Master_Orders!D2:D174, "2026-06-27") | C7: =COUNTIFS(Master_Orders!D2:D174, "2026-06-27", Master_Orders!J2:J174, "COD") | D7: =COUNTIFS(Master_Orders!D2:D174, "2026-06-27", Master_Orders!J2:J174, "Partial COD") | E7: =COUNTIFS(Master_Orders!D2:D174, "2026-06-27", Master_Orders!J2:J174, "Prepaid") | F7: =SUMIF(Master_Orders!D2:D174, "2026-06-27", Master_Orders!E2:E174) | G7: =SUMIFS(Master_Orders!E2:E174, Master_Orders!D2:D174, "2026-06-27", Master_Orders!J2:J174, "COD") | H7: =SUMIFS(Master_Orders!E2:E174, Master_Orders!D2:D174, "2026-06-27", Master_Orders!J2:J174, "Partial COD") | I7: =SUMIFS(Master_Orders!E2:E174, Master_Orders!D2:D174, "2026-06-27", Master_Orders!J2:J174, "Prepaid") | J7: =COUNTIFS(Master_Orders!D2:D174, "2026-06-27", Master_Orders!K2:K174, "Delivered") | K7: =COUNTIFS(Master_Orders!D2:D174, "2026-06-27", Master_Orders!K2:K174, "RTO / Returned") | L7: =COUNTIFS(Master_Orders!D2:D174, "2026-06-27", Master_Orders!K2:K174, "Canceled") | M7: =COUNTIFS(Master_Orders!D2:D174, "2026-06-27", Master_Orders!K2:K174, "In Transit")
A8: 2026-06-28 | B8: =COUNTIF(Master_Orders!D2:D174, "2026-06-28") | C8: =COUNTIFS(Master_Orders!D2:D174, "2026-06-28", Master_Orders!J2:J174, "COD") | D8: =COUNTIFS(Master_Orders!D2:D174, "2026-06-28", Master_Orders!J2:J174, "Partial COD") | E8: =COUNTIFS(Master_Orders!D2:D174, "2026-06-28", Master_Orders!J2:J174, "Prepaid") | F8: =SUMIF(Master_Orders!D2:D174, "2026-06-28", Master_Orders!E2:E174) | G8: =SUMIFS(Master_Orders!E2:E174, Master_Orders!D2:D174, "2026-06-28", Master_Orders!J2:J174, "COD") | H8: =SUMIFS(Master_Orders!E2:E174, Master_Orders!D2:D174, "2026-06-28", Master_Orders!J2:J174, "Partial COD") | I8: =SUMIFS(Master_Orders!E2:E174, Master_Orders!D2:D174, "2026-06-28", Master_Orders!J2:J174, "Prepaid") | J8: =COUNTIFS(Master_Orders!D2:D174, "2026-06-28", Master_Orders!K2:K174, "Delivered") | K8: =COUNTIFS(Master_Orders!D2:D174, "2026-06-28", Master_Orders!K2:K174, "RTO / Returned") | L8: =COUNTIFS(Master_Orders!D2:D174, "2026-06-28", Master_Orders!K2:K174, "Canceled") | M8: =COUNTIFS(Master_Orders!D2:D174, "2026-06-28", Master_Orders!K2:K174, "In Transit")
A9: 2026-06-29 | B9: =COUNTIF(Master_Orders!D2:D174, "2026-06-29") | C9: =COUNTIFS(Master_Orders!D2:D174, "2026-06-29", Master_Orders!J2:J174, "COD") | D9: =COUNTIFS(Master_Orders!D2:D174, "2026-06-29", Master_Orders!J2:J174, "Partial COD") | E9: =COUNTIFS(Master_Orders!D2:D174, "2026-06-29", Master_Orders!J2:J174, "Prepaid") | F9: =SUMIF(Master_Orders!D2:D174, "2026-06-29", Master_Orders!E2:E174) | G9: =SUMIFS(Master_Orders!E2:E174, Master_Orders!D2:D174, "2026-06-29", Master_Orders!J2:J174, "COD") | H9: =SUMIFS(Master_Orders!E2:E174, Master_Orders!D2:D174, "2026-06-29", Master_Orders!J2:J174, "Partial COD") | I9: =SUMIFS(Master_Orders!E2:E174, Master_Orders!D2:D174, "2026-06-29", Master_Orders!J2:J174, "Prepaid") | J9: =COUNTIFS(Master_Orders!D2:D174, "2026-06-29", Master_Orders!K2:K174, "Delivered") | K9: =COUNTIFS(Master_Orders!D2:D174, "2026-06-29", Master_Orders!K2:K174, "RTO / Returned") | L9: =COUNTIFS(Master_Orders!D2:D174, "2026-06-29", Master_Orders!K2:K174, "Canceled") | M9: =COUNTIFS(Master_Orders!D2:D174, "2026-06-29", Master_Orders!K2:K174, "In Transit")
A10: 2026-06-30 | B10: =COUNTIF(Master_Orders!D2:D174, "2026-06-30") | C10: =COUNTIFS(Master_Orders!D2:D174, "2026-06-30", Master_Orders!J2:J174, "COD") | D10: =COUNTIFS(Master_Orders!D2:D174, "2026-06-30", Master_Orders!J2:J174, "Partial COD") | E10: =COUNTIFS(Master_Orders!D2:D174, "2026-06-30", Master_Orders!J2:J174, "Prepaid") | F10: =SUMIF(Master_Orders!D2:D174, "2026-06-30", Master_Orders!E2:E174) | G10: =SUMIFS(Master_Orders!E2:E174, Master_Orders!D2:D174, "2026-06-30", Master_Orders!J2:J174, "COD") | H10: =SUMIFS(Master_Orders!E2:E174, Master_Orders!D2:D174, "2026-06-30", Master_Orders!J2:J174, "Partial COD") | I10: =SUMIFS(Master_Orders!E2:E174, Master_Orders!D2:D174, "2026-06-30", Master_Orders!J2:J174, "Prepaid") | J10: =COUNTIFS(Master_Orders!D2:D174, "2026-06-30", Master_Orders!K2:K174, "Delivered") | K10: =COUNTIFS(Master_Orders!D2:D174, "2026-06-30", Master_Orders!K2:K174, "RTO / Returned") | L10: =COUNTIFS(Master_Orders!D2:D174, "2026-06-30", Master_Orders!K2:K174, "Canceled") | M10: =COUNTIFS(Master_Orders!D2:D174, "2026-06-30", Master_Orders!K2:K174, "In Transit")
A11: 2026-07-01 | B11: =COUNTIF(Master_Orders!D2:D174, "2026-07-01") | C11: =COUNTIFS(Master_Orders!D2:D174, "2026-07-01", Master_Orders!J2:J174, "COD") | D11: =COUNTIFS(Master_Orders!D2:D174, "2026-07-01", Master_Orders!J2:J174, "Partial COD") | E11: =COUNTIFS(Master_Orders!D2:D174, "2026-07-01", Master_Orders!J2:J174, "Prepaid") | F11: =SUMIF(Master_Orders!D2:D174, "2026-07-01", Master_Orders!E2:E174) | G11: =SUMIFS(Master_Orders!E2:E174, Master_Orders!D2:D174, "2026-07-01", Master_Orders!J2:J174, "COD") | H11: =SUMIFS(Master_Orders!E2:E174, Master_Orders!D2:D174, "2026-07-01", Master_Orders!J2:J174, "Partial COD") | I11: =SUMIFS(Master_Orders!E2:E174, Master_Orders!D2:D174, "2026-07-01", Master_Orders!J2:J174, "Prepaid") | J11: =COUNTIFS(Master_Orders!D2:D174, "2026-07-01", Master_Orders!K2:K174, "Delivered") | K11: =COUNTIFS(Master_Orders!D2:D174, "2026-07-01", Master_Orders!K2:K174, "RTO / Returned") | L11: =COUNTIFS(Master_Orders!D2:D174, "2026-07-01", Master_Orders!K2:K174, "Canceled") | M11: =COUNTIFS(Master_Orders!D2:D174, "2026-07-01", Master_Orders!K2:K174, "In Transit")
A12: 2026-07-02 | B12: =COUNTIF(Master_Orders!D2:D174, "2026-07-02") | C12: =COUNTIFS(Master_Orders!D2:D174, "2026-07-02", Master_Orders!J2:J174, "COD") | D12: =COUNTIFS(Master_Orders!D2:D174, "2026-07-02", Master_Orders!J2:J174, "Partial COD") | E12: =COUNTIFS(Master_Orders!D2:D174, "2026-07-02", Master_Orders!J2:J174, "Prepaid") | F12: =SUMIF(Master_Orders!D2:D174, "2026-07-02", Master_Orders!E2:E174) | G12: =SUMIFS(Master_Orders!E2:E174, Master_Orders!D2:D174, "2026-07-02", Master_Orders!J2:J174, "COD") | H12: =SUMIFS(Master_Orders!E2:E174, Master_Orders!D2:D174, "2026-07-02", Master_Orders!J2:J174, "Partial COD") | I12: =SUMIFS(Master_Orders!E2:E174, Master_Orders!D2:D174, "2026-07-02", Master_Orders!J2:J174, "Prepaid") | J12: =COUNTIFS(Master_Orders!D2:D174, "2026-07-02", Master_Orders!K2:K174, "Delivered") | K12: =COUNTIFS(Master_Orders!D2:D174, "2026-07-02", Master_Orders!K2:K174, "RTO / Returned") | L12: =COUNTIFS(Master_Orders!D2:D174, "2026-07-02", Master_Orders!K2:K174, "Canceled") | M12: =COUNTIFS(Master_Orders!D2:D174, "2026-07-02", Master_Orders!K2:K174, "In Transit")
A13: 2026-07-03 | B13: =COUNTIF(Master_Orders!D2:D174, "2026-07-03") | C13: =COUNTIFS(Master_Orders!D2:D174, "2026-07-03", Master_Orders!J2:J174, "COD") | D13: =COUNTIFS(Master_Orders!D2:D174, "2026-07-03", Master_Orders!J2:J174, "Partial COD") | E13: =COUNTIFS(Master_Orders!D2:D174, "2026-07-03", Master_Orders!J2:J174, "Prepaid") | F13: =SUMIF(Master_Orders!D2:D174, "2026-07-03", Master_Orders!E2:E174) | G13: =SUMIFS(Master_Orders!E2:E174, Master_Orders!D2:D174, "2026-07-03", Master_Orders!J2:J174, "COD") | H13: =SUMIFS(Master_Orders!E2:E174, Master_Orders!D2:D174, "2026-07-03", Master_Orders!J2:J174, "Partial COD") | I13: =SUMIFS(Master_Orders!E2:E174, Master_Orders!D2:D174, "2026-07-03", Master_Orders!J2:J174, "Prepaid") | J13: =COUNTIFS(Master_Orders!D2:D174, "2026-07-03", Master_Orders!K2:K174, "Delivered") | K13: =COUNTIFS(Master_Orders!D2:D174, "2026-07-03", Master_Orders!K2:K174, "RTO / Returned") | L13: =COUNTIFS(Master_Orders!D2:D174, "2026-07-03", Master_Orders!K2:K174, "Canceled") | M13: =COUNTIFS(Master_Orders!D2:D174, "2026-07-03", Master_Orders!K2:K174, "In Transit")
A14: 2026-07-04 | B14: =COUNTIF(Master_Orders!D2:D174, "2026-07-04") | C14: =COUNTIFS(Master_Orders!D2:D174, "2026-07-04", Master_Orders!J2:J174, "COD") | D14: =COUNTIFS(Master_Orders!D2:D174, "2026-07-04", Master_Orders!J2:J174, "Partial COD") | E14: =COUNTIFS(Master_Orders!D2:D174, "2026-07-04", Master_Orders!J2:J174, "Prepaid") | F14: =SUMIF(Master_Orders!D2:D174, "2026-07-04", Master_Orders!E2:E174) | G14: =SUMIFS(Master_Orders!E2:E174, Master_Orders!D2:D174, "2026-07-04", Master_Orders!J2:J174, "COD") | H14: =SUMIFS(Master_Orders!E2:E174, Master_Orders!D2:D174, "2026-07-04", Master_Orders!J2:J174, "Partial COD") | I14: =SUMIFS(Master_Orders!E2:E174, Master_Orders!D2:D174, "2026-07-04", Master_Orders!J2:J174, "Prepaid") | J14: =COUNTIFS(Master_Orders!D2:D174, "2026-07-04", Master_Orders!K2:K174, "Delivered") | K14: =COUNTIFS(Master_Orders!D2:D174, "2026-07-04", Master_Orders!K2:K174, "RTO / Returned") | L14: =COUNTIFS(Master_Orders!D2:D174, "2026-07-04", Master_Orders!K2:K174, "Canceled") | M14: =COUNTIFS(Master_Orders!D2:D174, "2026-07-04", Master_Orders!K2:K174, "In Transit")
A15: 2026-07-05 | B15: =COUNTIF(Master_Orders!D2:D174, "2026-07-05") | C15: =COUNTIFS(Master_Orders!D2:D174, "2026-07-05", Master_Orders!J2:J174, "COD") | D15: =COUNTIFS(Master_Orders!D2:D174, "2026-07-05", Master_Orders!J2:J174, "Partial COD") | E15: =COUNTIFS(Master_Orders!D2:D174, "2026-07-05", Master_Orders!J2:J174, "Prepaid") | F15: =SUMIF(Master_Orders!D2:D174, "2026-07-05", Master_Orders!E2:E174) | G15: =SUMIFS(Master_Orders!E2:E174, Master_Orders!D2:D174, "2026-07-05", Master_Orders!J2:J174, "COD") | H15: =SUMIFS(Master_Orders!E2:E174, Master_Orders!D2:D174, "2026-07-05", Master_Orders!J2:J174, "Partial COD") | I15: =SUMIFS(Master_Orders!E2:E174, Master_Orders!D2:D174, "2026-07-05", Master_Orders!J2:J174, "Prepaid") | J15: =COUNTIFS(Master_Orders!D2:D174, "2026-07-05", Master_Orders!K2:K174, "Delivered") | K15: =COUNTIFS(Master_Orders!D2:D174, "2026-07-05", Master_Orders!K2:K174, "RTO / Returned") | L15: =COUNTIFS(Master_Orders!D2:D174, "2026-07-05", Master_Orders!K2:K174, "Canceled") | M15: =COUNTIFS(Master_Orders!D2:D174, "2026-07-05", Master_Orders!K2:K174, "In Transit")
A16: 2026-07-06 | B16: =COUNTIF(Master_Orders!D2:D174, "2026-07-06") | C16: =COUNTIFS(Master_Orders!D2:D174, "2026-07-06", Master_Orders!J2:J174, "COD") | D16: =COUNTIFS(Master_Orders!D2:D174, "2026-07-06", Master_Orders!J2:J174, "Partial COD") | E16: =COUNTIFS(Master_Orders!D2:D174, "2026-07-06", Master_Orders!J2:J174, "Prepaid") | F16: =SUMIF(Master_Orders!D2:D174, "2026-07-06", Master_Orders!E2:E174) | G16: =SUMIFS(Master_Orders!E2:E174, Master_Orders!D2:D174, "2026-07-06", Master_Orders!J2:J174, "COD") | H16: =SUMIFS(Master_Orders!E2:E174, Master_Orders!D2:D174, "2026-07-06", Master_Orders!J2:J174, "Partial COD") | I16: =SUMIFS(Master_Orders!E2:E174, Master_Orders!D2:D174, "2026-07-06", Master_Orders!J2:J174, "Prepaid") | J16: =COUNTIFS(Master_Orders!D2:D174, "2026-07-06", Master_Orders!K2:K174, "Delivered") | K16: =COUNTIFS(Master_Orders!D2:D174, "2026-07-06", Master_Orders!K2:K174, "RTO / Returned") | L16: =COUNTIFS(Master_Orders!D2:D174, "2026-07-06", Master_Orders!K2:K174, "Canceled") | M16: =COUNTIFS(Master_Orders!D2:D174, "2026-07-06", Master_Orders!K2:K174, "In Transit")
A17: 2026-07-07 | B17: =COUNTIF(Master_Orders!D2:D174, "2026-07-07") | C17: =COUNTIFS(Master_Orders!D2:D174, "2026-07-07", Master_Orders!J2:J174, "COD") | D17: =COUNTIFS(Master_Orders!D2:D174, "2026-07-07", Master_Orders!J2:J174, "Partial COD") | E17: =COUNTIFS(Master_Orders!D2:D174, "2026-07-07", Master_Orders!J2:J174, "Prepaid") | F17: =SUMIF(Master_Orders!D2:D174, "2026-07-07", Master_Orders!E2:E174) | G17: =SUMIFS(Master_Orders!E2:E174, Master_Orders!D2:D174, "2026-07-07", Master_Orders!J2:J174, "COD") | H17: =SUMIFS(Master_Orders!E2:E174, Master_Orders!D2:D174, "2026-07-07", Master_Orders!J2:J174, "Partial COD") | I17: =SUMIFS(Master_Orders!E2:E174, Master_Orders!D2:D174, "2026-07-07", Master_Orders!J2:J174, "Prepaid") | J17: =COUNTIFS(Master_Orders!D2:D174, "2026-07-07", Master_Orders!K2:K174, "Delivered") | K17: =COUNTIFS(Master_Orders!D2:D174, "2026-07-07", Master_Orders!K2:K174, "RTO / Returned") | L17: =COUNTIFS(Master_Orders!D2:D174, "2026-07-07", Master_Orders!K2:K174, "Canceled") | M17: =COUNTIFS(Master_Orders!D2:D174, "2026-07-07", Master_Orders!K2:K174, "In Transit")
A18: 2026-07-08 | B18: =COUNTIF(Master_Orders!D2:D174, "2026-07-08") | C18: =COUNTIFS(Master_Orders!D2:D174, "2026-07-08", Master_Orders!J2:J174, "COD") | D18: =COUNTIFS(Master_Orders!D2:D174, "2026-07-08", Master_Orders!J2:J174, "Partial COD") | E18: =COUNTIFS(Master_Orders!D2:D174, "2026-07-08", Master_Orders!J2:J174, "Prepaid") | F18: =SUMIF(Master_Orders!D2:D174, "2026-07-08", Master_Orders!E2:E174) | G18: =SUMIFS(Master_Orders!E2:E174, Master_Orders!D2:D174, "2026-07-08", Master_Orders!J2:J174, "COD") | H18: =SUMIFS(Master_Orders!E2:E174, Master_Orders!D2:D174, "2026-07-08", Master_Orders!J2:J174, "Partial COD") | I18: =SUMIFS(Master_Orders!E2:E174, Master_Orders!D2:D174, "2026-07-08", Master_Orders!J2:J174, "Prepaid") | J18: =COUNTIFS(Master_Orders!D2:D174, "2026-07-08", Master_Orders!K2:K174, "Delivered") | K18: =COUNTIFS(Master_Orders!D2:D174, "2026-07-08", Master_Orders!K2:K174, "RTO / Returned") | L18: =COUNTIFS(Master_Orders!D2:D174, "2026-07-08", Master_Orders!K2:K174, "Canceled") | M18: =COUNTIFS(Master_Orders!D2:D174, "2026-07-08", Master_Orders!K2:K174, "In Transit")
A19: 2026-07-09 | B19: =COUNTIF(Master_Orders!D2:D174, "2026-07-09") | C19: =COUNTIFS(Master_Orders!D2:D174, "2026-07-09", Master_Orders!J2:J174, "COD") | D19: =COUNTIFS(Master_Orders!D2:D174, "2026-07-09", Master_Orders!J2:J174, "Partial COD") | E19: =COUNTIFS(Master_Orders!D2:D174, "2026-07-09", Master_Orders!J2:J174, "Prepaid") | F19: =SUMIF(Master_Orders!D2:D174, "2026-07-09", Master_Orders!E2:E174) | G19: =SUMIFS(Master_Orders!E2:E174, Master_Orders!D2:D174, "2026-07-09", Master_Orders!J2:J174, "COD") | H19: =SUMIFS(Master_Orders!E2:E174, Master_Orders!D2:D174, "2026-07-09", Master_Orders!J2:J174, "Partial COD") | I19: =SUMIFS(Master_Orders!E2:E174, Master_Orders!D2:D174, "2026-07-09", Master_Orders!J2:J174, "Prepaid") | J19: =COUNTIFS(Master_Orders!D2:D174, "2026-07-09", Master_Orders!K2:K174, "Delivered") | K19: =COUNTIFS(Master_Orders!D2:D174, "2026-07-09", Master_Orders!K2:K174, "RTO / Returned") | L19: =COUNTIFS(Master_Orders!D2:D174, "2026-07-09", Master_Orders!K2:K174, "Canceled") | M19: =COUNTIFS(Master_Orders!D2:D174, "2026-07-09", Master_Orders!K2:K174, "In Transit")
A20: 2026-07-10 | B20: =COUNTIF(Master_Orders!D2:D174, "2026-07-10") | C20: =COUNTIFS(Master_Orders!D2:D174, "2026-07-10", Master_Orders!J2:J174, "COD") | D20: =COUNTIFS(Master_Orders!D2:D174, "2026-07-10", Master_Orders!J2:J174, "Partial COD") | E20: =COUNTIFS(Master_Orders!D2:D174, "2026-07-10", Master_Orders!J2:J174, "Prepaid") | F20: =SUMIF(Master_Orders!D2:D174, "2026-07-10", Master_Orders!E2:E174) | G20: =SUMIFS(Master_Orders!E2:E174, Master_Orders!D2:D174, "2026-07-10", Master_Orders!J2:J174, "COD") | H20: =SUMIFS(Master_Orders!E2:E174, Master_Orders!D2:D174, "2026-07-10", Master_Orders!J2:J174, "Partial COD") | I20: =SUMIFS(Master_Orders!E2:E174, Master_Orders!D2:D174, "2026-07-10", Master_Orders!J2:J174, "Prepaid") | J20: =COUNTIFS(Master_Orders!D2:D174, "2026-07-10", Master_Orders!K2:K174, "Delivered") | K20: =COUNTIFS(Master_Orders!D2:D174, "2026-07-10", Master_Orders!K2:K174, "RTO / Returned") | L20: =COUNTIFS(Master_Orders!D2:D174, "2026-07-10", Master_Orders!K2:K174, "Canceled") | M20: =COUNTIFS(Master_Orders!D2:D174, "2026-07-10", Master_Orders!K2:K174, "In Transit")
A21: 2026-07-11 | B21: =COUNTIF(Master_Orders!D2:D174, "2026-07-11") | C21: =COUNTIFS(Master_Orders!D2:D174, "2026-07-11", Master_Orders!J2:J174, "COD") | D21: =COUNTIFS(Master_Orders!D2:D174, "2026-07-11", Master_Orders!J2:J174, "Partial COD") | E21: =COUNTIFS(Master_Orders!D2:D174, "2026-07-11", Master_Orders!J2:J174, "Prepaid") | F21: =SUMIF(Master_Orders!D2:D174, "2026-07-11", Master_Orders!E2:E174) | G21: =SUMIFS(Master_Orders!E2:E174, Master_Orders!D2:D174, "2026-07-11", Master_Orders!J2:J174, "COD") | H21: =SUMIFS(Master_Orders!E2:E174, Master_Orders!D2:D174, "2026-07-11", Master_Orders!J2:J174, "Partial COD") | I21: =SUMIFS(Master_Orders!E2:E174, Master_Orders!D2:D174, "2026-07-11", Master_Orders!J2:J174, "Prepaid") | J21: =COUNTIFS(Master_Orders!D2:D174, "2026-07-11", Master_Orders!K2:K174, "Delivered") | K21: =COUNTIFS(Master_Orders!D2:D174, "2026-07-11", Master_Orders!K2:K174, "RTO / Returned") | L21: =COUNTIFS(Master_Orders!D2:D174, "2026-07-11", Master_Orders!K2:K174, "Canceled") | M21: =COUNTIFS(Master_Orders!D2:D174, "2026-07-11", Master_Orders!K2:K174, "In Transit")
A22: 2026-07-12 | B22: =COUNTIF(Master_Orders!D2:D174, "2026-07-12") | C22: =COUNTIFS(Master_Orders!D2:D174, "2026-07-12", Master_Orders!J2:J174, "COD") | D22: =COUNTIFS(Master_Orders!D2:D174, "2026-07-12", Master_Orders!J2:J174, "Partial COD") | E22: =COUNTIFS(Master_Orders!D2:D174, "2026-07-12", Master_Orders!J2:J174, "Prepaid") | F22: =SUMIF(Master_Orders!D2:D174, "2026-07-12", Master_Orders!E2:E174) | G22: =SUMIFS(Master_Orders!E2:E174, Master_Orders!D2:D174, "2026-07-12", Master_Orders!J2:J174, "COD") | H22: =SUMIFS(Master_Orders!E2:E174, Master_Orders!D2:D174, "2026-07-12", Master_Orders!J2:J174, "Partial COD") | I22: =SUMIFS(Master_Orders!E2:E174, Master_Orders!D2:D174, "2026-07-12", Master_Orders!J2:J174, "Prepaid") | J22: =COUNTIFS(Master_Orders!D2:D174, "2026-07-12", Master_Orders!K2:K174, "Delivered") | K22: =COUNTIFS(Master_Orders!D2:D174, "2026-07-12", Master_Orders!K2:K174, "RTO / Returned") | L22: =COUNTIFS(Master_Orders!D2:D174, "2026-07-12", Master_Orders!K2:K174, "Canceled") | M22: =COUNTIFS(Master_Orders!D2:D174, "2026-07-12", Master_Orders!K2:K174, "In Transit")
A23: 2026-07-13 | B23: =COUNTIF(Master_Orders!D2:D174, "2026-07-13") | C23: =COUNTIFS(Master_Orders!D2:D174, "2026-07-13", Master_Orders!J2:J174, "COD") | D23: =COUNTIFS(Master_Orders!D2:D174, "2026-07-13", Master_Orders!J2:J174, "Partial COD") | E23: =COUNTIFS(Master_Orders!D2:D174, "2026-07-13", Master_Orders!J2:J174, "Prepaid") | F23: =SUMIF(Master_Orders!D2:D174, "2026-07-13", Master_Orders!E2:E174) | G23: =SUMIFS(Master_Orders!E2:E174, Master_Orders!D2:D174, "2026-07-13", Master_Orders!J2:J174, "COD") | H23: =SUMIFS(Master_Orders!E2:E174, Master_Orders!D2:D174, "2026-07-13", Master_Orders!J2:J174, "Partial COD") | I23: =SUMIFS(Master_Orders!E2:E174, Master_Orders!D2:D174, "2026-07-13", Master_Orders!J2:J174, "Prepaid") | J23: =COUNTIFS(Master_Orders!D2:D174, "2026-07-13", Master_Orders!K2:K174, "Delivered") | K23: =COUNTIFS(Master_Orders!D2:D174, "2026-07-13", Master_Orders!K2:K174, "RTO / Returned") | L23: =COUNTIFS(Master_Orders!D2:D174, "2026-07-13", Master_Orders!K2:K174, "Canceled") | M23: =COUNTIFS(Master_Orders!D2:D174, "2026-07-13", Master_Orders!K2:K174, "In Transit")
A24: 2026-07-14 | B24: =COUNTIF(Master_Orders!D2:D174, "2026-07-14") | C24: =COUNTIFS(Master_Orders!D2:D174, "2026-07-14", Master_Orders!J2:J174, "COD") | D24: =COUNTIFS(Master_Orders!D2:D174, "2026-07-14", Master_Orders!J2:J174, "Partial COD") | E24: =COUNTIFS(Master_Orders!D2:D174, "2026-07-14", Master_Orders!J2:J174, "Prepaid") | F24: =SUMIF(Master_Orders!D2:D174, "2026-07-14", Master_Orders!E2:E174) | G24: =SUMIFS(Master_Orders!E2:E174, Master_Orders!D2:D174, "2026-07-14", Master_Orders!J2:J174, "COD") | H24: =SUMIFS(Master_Orders!E2:E174, Master_Orders!D2:D174, "2026-07-14", Master_Orders!J2:J174, "Partial COD") | I24: =SUMIFS(Master_Orders!E2:E174, Master_Orders!D2:D174, "2026-07-14", Master_Orders!J2:J174, "Prepaid") | J24: =COUNTIFS(Master_Orders!D2:D174, "2026-07-14", Master_Orders!K2:K174, "Delivered") | K24: =COUNTIFS(Master_Orders!D2:D174, "2026-07-14", Master_Orders!K2:K174, "RTO / Returned") | L24: =COUNTIFS(Master_Orders!D2:D174, "2026-07-14", Master_Orders!K2:K174, "Canceled") | M24: =COUNTIFS(Master_Orders!D2:D174, "2026-07-14", Master_Orders!K2:K174, "In Transit")
A25: 2026-07-15 | B25: =COUNTIF(Master_Orders!D2:D174, "2026-07-15") | C25: =COUNTIFS(Master_Orders!D2:D174, "2026-07-15", Master_Orders!J2:J174, "COD") | D25: =COUNTIFS(Master_Orders!D2:D174, "2026-07-15", Master_Orders!J2:J174, "Partial COD") | E25: =COUNTIFS(Master_Orders!D2:D174, "2026-07-15", Master_Orders!J2:J174, "Prepaid") | F25: =SUMIF(Master_Orders!D2:D174, "2026-07-15", Master_Orders!E2:E174) | G25: =SUMIFS(Master_Orders!E2:E174, Master_Orders!D2:D174, "2026-07-15", Master_Orders!J2:J174, "COD") | H25: =SUMIFS(Master_Orders!E2:E174, Master_Orders!D2:D174, "2026-07-15", Master_Orders!J2:J174, "Partial COD") | I25: =SUMIFS(Master_Orders!E2:E174, Master_Orders!D2:D174, "2026-07-15", Master_Orders!J2:J174, "Prepaid") | J25: =COUNTIFS(Master_Orders!D2:D174, "2026-07-15", Master_Orders!K2:K174, "Delivered") | K25: =COUNTIFS(Master_Orders!D2:D174, "2026-07-15", Master_Orders!K2:K174, "RTO / Returned") | L25: =COUNTIFS(Master_Orders!D2:D174, "2026-07-15", Master_Orders!K2:K174, "Canceled") | M25: =COUNTIFS(Master_Orders!D2:D174, "2026-07-15", Master_Orders!K2:K174, "In Transit")
A26: 2026-07-16 | B26: =COUNTIF(Master_Orders!D2:D174, "2026-07-16") | C26: =COUNTIFS(Master_Orders!D2:D174, "2026-07-16", Master_Orders!J2:J174, "COD") | D26: =COUNTIFS(Master_Orders!D2:D174, "2026-07-16", Master_Orders!J2:J174, "Partial COD") | E26: =COUNTIFS(Master_Orders!D2:D174, "2026-07-16", Master_Orders!J2:J174, "Prepaid") | F26: =SUMIF(Master_Orders!D2:D174, "2026-07-16", Master_Orders!E2:E174) | G26: =SUMIFS(Master_Orders!E2:E174, Master_Orders!D2:D174, "2026-07-16", Master_Orders!J2:J174, "COD") | H26: =SUMIFS(Master_Orders!E2:E174, Master_Orders!D2:D174, "2026-07-16", Master_Orders!J2:J174, "Partial COD") | I26: =SUMIFS(Master_Orders!E2:E174, Master_Orders!D2:D174, "2026-07-16", Master_Orders!J2:J174, "Prepaid") | J26: =COUNTIFS(Master_Orders!D2:D174, "2026-07-16", Master_Orders!K2:K174, "Delivered") | K26: =COUNTIFS(Master_Orders!D2:D174, "2026-07-16", Master_Orders!K2:K174, "RTO / Returned") | L26: =COUNTIFS(Master_Orders!D2:D174, "2026-07-16", Master_Orders!K2:K174, "Canceled") | M26: =COUNTIFS(Master_Orders!D2:D174, "2026-07-16", Master_Orders!K2:K174, "In Transit")
A27: 2026-07-17 | B27: =COUNTIF(Master_Orders!D2:D174, "2026-07-17") | C27: =COUNTIFS(Master_Orders!D2:D174, "2026-07-17", Master_Orders!J2:J174, "COD") | D27: =COUNTIFS(Master_Orders!D2:D174, "2026-07-17", Master_Orders!J2:J174, "Partial COD") | E27: =COUNTIFS(Master_Orders!D2:D174, "2026-07-17", Master_Orders!J2:J174, "Prepaid") | F27: =SUMIF(Master_Orders!D2:D174, "2026-07-17", Master_Orders!E2:E174) | G27: =SUMIFS(Master_Orders!E2:E174, Master_Orders!D2:D174, "2026-07-17", Master_Orders!J2:J174, "COD") | H27: =SUMIFS(Master_Orders!E2:E174, Master_Orders!D2:D174, "2026-07-17", Master_Orders!J2:J174, "Partial COD") | I27: =SUMIFS(Master_Orders!E2:E174, Master_Orders!D2:D174, "2026-07-17", Master_Orders!J2:J174, "Prepaid") | J27: =COUNTIFS(Master_Orders!D2:D174, "2026-07-17", Master_Orders!K2:K174, "Delivered") | K27: =COUNTIFS(Master_Orders!D2:D174, "2026-07-17", Master_Orders!K2:K174, "RTO / Returned") | L27: =COUNTIFS(Master_Orders!D2:D174, "2026-07-17", Master_Orders!K2:K174, "Canceled") | M27: =COUNTIFS(Master_Orders!D2:D174, "2026-07-17", Master_Orders!K2:K174, "In Transit")
A28: 2026-07-18 | B28: =COUNTIF(Master_Orders!D2:D174, "2026-07-18") | C28: =COUNTIFS(Master_Orders!D2:D174, "2026-07-18", Master_Orders!J2:J174, "COD") | D28: =COUNTIFS(Master_Orders!D2:D174, "2026-07-18", Master_Orders!J2:J174, "Partial COD") | E28: =COUNTIFS(Master_Orders!D2:D174, "2026-07-18", Master_Orders!J2:J174, "Prepaid") | F28: =SUMIF(Master_Orders!D2:D174, "2026-07-18", Master_Orders!E2:E174) | G28: =SUMIFS(Master_Orders!E2:E174, Master_Orders!D2:D174, "2026-07-18", Master_Orders!J2:J174, "COD") | H28: =SUMIFS(Master_Orders!E2:E174, Master_Orders!D2:D174, "2026-07-18", Master_Orders!J2:J174, "Partial COD") | I28: =SUMIFS(Master_Orders!E2:E174, Master_Orders!D2:D174, "2026-07-18", Master_Orders!J2:J174, "Prepaid") | J28: =COUNTIFS(Master_Orders!D2:D174, "2026-07-18", Master_Orders!K2:K174, "Delivered") | K28: =COUNTIFS(Master_Orders!D2:D174, "2026-07-18", Master_Orders!K2:K174, "RTO / Returned") | L28: =COUNTIFS(Master_Orders!D2:D174, "2026-07-18", Master_Orders!K2:K174, "Canceled") | M28: =COUNTIFS(Master_Orders!D2:D174, "2026-07-18", Master_Orders!K2:K174, "In Transit")
A29: 2026-07-19 | B29: =COUNTIF(Master_Orders!D2:D174, "2026-07-19") | C29: =COUNTIFS(Master_Orders!D2:D174, "2026-07-19", Master_Orders!J2:J174, "COD") | D29: =COUNTIFS(Master_Orders!D2:D174, "2026-07-19", Master_Orders!J2:J174, "Partial COD") | E29: =COUNTIFS(Master_Orders!D2:D174, "2026-07-19", Master_Orders!J2:J174, "Prepaid") | F29: =SUMIF(Master_Orders!D2:D174, "2026-07-19", Master_Orders!E2:E174) | G29: =SUMIFS(Master_Orders!E2:E174, Master_Orders!D2:D174, "2026-07-19", Master_Orders!J2:J174, "COD") | H29: =SUMIFS(Master_Orders!E2:E174, Master_Orders!D2:D174, "2026-07-19", Master_Orders!J2:J174, "Partial COD") | I29: =SUMIFS(Master_Orders!E2:E174, Master_Orders!D2:D174, "2026-07-19", Master_Orders!J2:J174, "Prepaid") | J29: =COUNTIFS(Master_Orders!D2:D174, "2026-07-19", Master_Orders!K2:K174, "Delivered") | K29: =COUNTIFS(Master_Orders!D2:D174, "2026-07-19", Master_Orders!K2:K174, "RTO / Returned") | L29: =COUNTIFS(Master_Orders!D2:D174, "2026-07-19", Master_Orders!K2:K174, "Canceled") | M29: =COUNTIFS(Master_Orders!D2:D174, "2026-07-19", Master_Orders!K2:K174, "In Transit")
A30: 2026-07-20 | B30: =COUNTIF(Master_Orders!D2:D174, "2026-07-20") | C30: =COUNTIFS(Master_Orders!D2:D174, "2026-07-20", Master_Orders!J2:J174, "COD") | D30: =COUNTIFS(Master_Orders!D2:D174, "2026-07-20", Master_Orders!J2:J174, "Partial COD") | E30: =COUNTIFS(Master_Orders!D2:D174, "2026-07-20", Master_Orders!J2:J174, "Prepaid") | F30: =SUMIF(Master_Orders!D2:D174, "2026-07-20", Master_Orders!E2:E174) | G30: =SUMIFS(Master_Orders!E2:E174, Master_Orders!D2:D174, "2026-07-20", Master_Orders!J2:J174, "COD") | H30: =SUMIFS(Master_Orders!E2:E174, Master_Orders!D2:D174, "2026-07-20", Master_Orders!J2:J174, "Partial COD") | I30: =SUMIFS(Master_Orders!E2:E174, Master_Orders!D2:D174, "2026-07-20", Master_Orders!J2:J174, "Prepaid") | J30: =COUNTIFS(Master_Orders!D2:D174, "2026-07-20", Master_Orders!K2:K174, "Delivered") | K30: =COUNTIFS(Master_Orders!D2:D174, "2026-07-20", Master_Orders!K2:K174, "RTO / Returned") | L30: =COUNTIFS(Master_Orders!D2:D174, "2026-07-20", Master_Orders!K2:K174, "Canceled") | M30: =COUNTIFS(Master_Orders!D2:D174, "2026-07-20", Master_Orders!K2:K174, "In Transit")
A31: 2026-07-21 | B31: =COUNTIF(Master_Orders!D2:D174, "2026-07-21") | C31: =COUNTIFS(Master_Orders!D2:D174, "2026-07-21", Master_Orders!J2:J174, "COD") | D31: =COUNTIFS(Master_Orders!D2:D174, "2026-07-21", Master_Orders!J2:J174, "Partial COD") | E31: =COUNTIFS(Master_Orders!D2:D174, "2026-07-21", Master_Orders!J2:J174, "Prepaid") | F31: =SUMIF(Master_Orders!D2:D174, "2026-07-21", Master_Orders!E2:E174) | G31: =SUMIFS(Master_Orders!E2:E174, Master_Orders!D2:D174, "2026-07-21", Master_Orders!J2:J174, "COD") | H31: =SUMIFS(Master_Orders!E2:E174, Master_Orders!D2:D174, "2026-07-21", Master_Orders!J2:J174, "Partial COD") | I31: =SUMIFS(Master_Orders!E2:E174, Master_Orders!D2:D174, "2026-07-21", Master_Orders!J2:J174, "Prepaid") | J31: =COUNTIFS(Master_Orders!D2:D174, "2026-07-21", Master_Orders!K2:K174, "Delivered") | K31: =COUNTIFS(Master_Orders!D2:D174, "2026-07-21", Master_Orders!K2:K174, "RTO / Returned") | L31: =COUNTIFS(Master_Orders!D2:D174, "2026-07-21", Master_Orders!K2:K174, "Canceled") | M31: =COUNTIFS(Master_Orders!D2:D174, "2026-07-21", Master_Orders!K2:K174, "In Transit")
A32: 2026-07-22 | B32: =COUNTIF(Master_Orders!D2:D174, "2026-07-22") | C32: =COUNTIFS(Master_Orders!D2:D174, "2026-07-22", Master_Orders!J2:J174, "COD") | D32: =COUNTIFS(Master_Orders!D2:D174, "2026-07-22", Master_Orders!J2:J174, "Partial COD") | E32: =COUNTIFS(Master_Orders!D2:D174, "2026-07-22", Master_Orders!J2:J174, "Prepaid") | F32: =SUMIF(Master_Orders!D2:D174, "2026-07-22", Master_Orders!E2:E174) | G32: =SUMIFS(Master_Orders!E2:E174, Master_Orders!D2:D174, "2026-07-22", Master_Orders!J2:J174, "COD") | H32: =SUMIFS(Master_Orders!E2:E174, Master_Orders!D2:D174, "2026-07-22", Master_Orders!J2:J174, "Partial COD") | I32: =SUMIFS(Master_Orders!E2:E174, Master_Orders!D2:D174, "2026-07-22", Master_Orders!J2:J174, "Prepaid") | J32: =COUNTIFS(Master_Orders!D2:D174, "2026-07-22", Master_Orders!K2:K174, "Delivered") | K32: =COUNTIFS(Master_Orders!D2:D174, "2026-07-22", Master_Orders!K2:K174, "RTO / Returned") | L32: =COUNTIFS(Master_Orders!D2:D174, "2026-07-22", Master_Orders!K2:K174, "Canceled") | M32: =COUNTIFS(Master_Orders!D2:D174, "2026-07-22", Master_Orders!K2:K174, "In Transit")
A33: 2026-07-23 | B33: =COUNTIF(Master_Orders!D2:D174, "2026-07-23") | C33: =COUNTIFS(Master_Orders!D2:D174, "2026-07-23", Master_Orders!J2:J174, "COD") | D33: =COUNTIFS(Master_Orders!D2:D174, "2026-07-23", Master_Orders!J2:J174, "Partial COD") | E33: =COUNTIFS(Master_Orders!D2:D174, "2026-07-23", Master_Orders!J2:J174, "Prepaid") | F33: =SUMIF(Master_Orders!D2:D174, "2026-07-23", Master_Orders!E2:E174) | G33: =SUMIFS(Master_Orders!E2:E174, Master_Orders!D2:D174, "2026-07-23", Master_Orders!J2:J174, "COD") | H33: =SUMIFS(Master_Orders!E2:E174, Master_Orders!D2:D174, "2026-07-23", Master_Orders!J2:J174, "Partial COD") | I33: =SUMIFS(Master_Orders!E2:E174, Master_Orders!D2:D174, "2026-07-23", Master_Orders!J2:J174, "Prepaid") | J33: =COUNTIFS(Master_Orders!D2:D174, "2026-07-23", Master_Orders!K2:K174, "Delivered") | K33: =COUNTIFS(Master_Orders!D2:D174, "2026-07-23", Master_Orders!K2:K174, "RTO / Returned") | L33: =COUNTIFS(Master_Orders!D2:D174, "2026-07-23", Master_Orders!K2:K174, "Canceled") | M33: =COUNTIFS(Master_Orders!D2:D174, "2026-07-23", Master_Orders!K2:K174, "In Transit")
A34: 2026-07-24 | B34: =COUNTIF(Master_Orders!D2:D174, "2026-07-24") | C34: =COUNTIFS(Master_Orders!D2:D174, "2026-07-24", Master_Orders!J2:J174, "COD") | D34: =COUNTIFS(Master_Orders!D2:D174, "2026-07-24", Master_Orders!J2:J174, "Partial COD") | E34: =COUNTIFS(Master_Orders!D2:D174, "2026-07-24", Master_Orders!J2:J174, "Prepaid") | F34: =SUMIF(Master_Orders!D2:D174, "2026-07-24", Master_Orders!E2:E174) | G34: =SUMIFS(Master_Orders!E2:E174, Master_Orders!D2:D174, "2026-07-24", Master_Orders!J2:J174, "COD") | H34: =SUMIFS(Master_Orders!E2:E174, Master_Orders!D2:D174, "2026-07-24", Master_Orders!J2:J174, "Partial COD") | I34: =SUMIFS(Master_Orders!E2:E174, Master_Orders!D2:D174, "2026-07-24", Master_Orders!J2:J174, "Prepaid") | J34: =COUNTIFS(Master_Orders!D2:D174, "2026-07-24", Master_Orders!K2:K174, "Delivered") | K34: =COUNTIFS(Master_Orders!D2:D174, "2026-07-24", Master_Orders!K2:K174, "RTO / Returned") | L34: =COUNTIFS(Master_Orders!D2:D174, "2026-07-24", Master_Orders!K2:K174, "Canceled") | M34: =COUNTIFS(Master_Orders!D2:D174, "2026-07-24", Master_Orders!K2:K174, "In Transit")
A35: 2026-07-25 | B35: =COUNTIF(Master_Orders!D2:D174, "2026-07-25") | C35: =COUNTIFS(Master_Orders!D2:D174, "2026-07-25", Master_Orders!J2:J174, "COD") | D35: =COUNTIFS(Master_Orders!D2:D174, "2026-07-25", Master_Orders!J2:J174, "Partial COD") | E35: =COUNTIFS(Master_Orders!D2:D174, "2026-07-25", Master_Orders!J2:J174, "Prepaid") | F35: =SUMIF(Master_Orders!D2:D174, "2026-07-25", Master_Orders!E2:E174) | G35: =SUMIFS(Master_Orders!E2:E174, Master_Orders!D2:D174, "2026-07-25", Master_Orders!J2:J174, "COD") | H35: =SUMIFS(Master_Orders!E2:E174, Master_Orders!D2:D174, "2026-07-25", Master_Orders!J2:J174, "Partial COD") | I35: =SUMIFS(Master_Orders!E2:E174, Master_Orders!D2:D174, "2026-07-25", Master_Orders!J2:J174, "Prepaid") | J35: =COUNTIFS(Master_Orders!D2:D174, "2026-07-25", Master_Orders!K2:K174, "Delivered") | K35: =COUNTIFS(Master_Orders!D2:D174, "2026-07-25", Master_Orders!K2:K174, "RTO / Returned") | L35: =COUNTIFS(Master_Orders!D2:D174, "2026-07-25", Master_Orders!K2:K174, "Canceled") | M35: =COUNTIFS(Master_Orders!D2:D174, "2026-07-25", Master_Orders!K2:K174, "In Transit")
A36: 2026-07-26 | B36: =COUNTIF(Master_Orders!D2:D174, "2026-07-26") | C36: =COUNTIFS(Master_Orders!D2:D174, "2026-07-26", Master_Orders!J2:J174, "COD") | D36: =COUNTIFS(Master_Orders!D2:D174, "2026-07-26", Master_Orders!J2:J174, "Partial COD") | E36: =COUNTIFS(Master_Orders!D2:D174, "2026-07-26", Master_Orders!J2:J174, "Prepaid") | F36: =SUMIF(Master_Orders!D2:D174, "2026-07-26", Master_Orders!E2:E174) | G36: =SUMIFS(Master_Orders!E2:E174, Master_Orders!D2:D174, "2026-07-26", Master_Orders!J2:J174, "COD") | H36: =SUMIFS(Master_Orders!E2:E174, Master_Orders!D2:D174, "2026-07-26", Master_Orders!J2:J174, "Partial COD") | I36: =SUMIFS(Master_Orders!E2:E174, Master_Orders!D2:D174, "2026-07-26", Master_Orders!J2:J174, "Prepaid") | J36: =COUNTIFS(Master_Orders!D2:D174, "2026-07-26", Master_Orders!K2:K174, "Delivered") | K36: =COUNTIFS(Master_Orders!D2:D174, "2026-07-26", Master_Orders!K2:K174, "RTO / Returned") | L36: =COUNTIFS(Master_Orders!D2:D174, "2026-07-26", Master_Orders!K2:K174, "Canceled") | M36: =COUNTIFS(Master_Orders!D2:D174, "2026-07-26", Master_Orders!K2:K174, "In Transit")
A37: 2026-07-27 | B37: =COUNTIF(Master_Orders!D2:D174, "2026-07-27") | C37: =COUNTIFS(Master_Orders!D2:D174, "2026-07-27", Master_Orders!J2:J174, "COD") | D37: =COUNTIFS(Master_Orders!D2:D174, "2026-07-27", Master_Orders!J2:J174, "Partial COD") | E37: =COUNTIFS(Master_Orders!D2:D174, "2026-07-27", Master_Orders!J2:J174, "Prepaid") | F37: =SUMIF(Master_Orders!D2:D174, "2026-07-27", Master_Orders!E2:E174) | G37: =SUMIFS(Master_Orders!E2:E174, Master_Orders!D2:D174, "2026-07-27", Master_Orders!J2:J174, "COD") | H37: =SUMIFS(Master_Orders!E2:E174, Master_Orders!D2:D174, "2026-07-27", Master_Orders!J2:J174, "Partial COD") | I37: =SUMIFS(Master_Orders!E2:E174, Master_Orders!D2:D174, "2026-07-27", Master_Orders!J2:J174, "Prepaid") | J37: =COUNTIFS(Master_Orders!D2:D174, "2026-07-27", Master_Orders!K2:K174, "Delivered") | K37: =COUNTIFS(Master_Orders!D2:D174, "2026-07-27", Master_Orders!K2:K174, "RTO / Returned") | L37: =COUNTIFS(Master_Orders!D2:D174, "2026-07-27", Master_Orders!K2:K174, "Canceled") | M37: =COUNTIFS(Master_Orders!D2:D174, "2026-07-27", Master_Orders!K2:K174, "In Transit")
A38: 2026-07-28 | B38: =COUNTIF(Master_Orders!D2:D174, "2026-07-28") | C38: =COUNTIFS(Master_Orders!D2:D174, "2026-07-28", Master_Orders!J2:J174, "COD") | D38: =COUNTIFS(Master_Orders!D2:D174, "2026-07-28", Master_Orders!J2:J174, "Partial COD") | E38: =COUNTIFS(Master_Orders!D2:D174, "2026-07-28", Master_Orders!J2:J174, "Prepaid") | F38: =SUMIF(Master_Orders!D2:D174, "2026-07-28", Master_Orders!E2:E174) | G38: =SUMIFS(Master_Orders!E2:E174, Master_Orders!D2:D174, "2026-07-28", Master_Orders!J2:J174, "COD") | H38: =SUMIFS(Master_Orders!E2:E174, Master_Orders!D2:D174, "2026-07-28", Master_Orders!J2:J174, "Partial COD") | I38: =SUMIFS(Master_Orders!E2:E174, Master_Orders!D2:D174, "2026-07-28", Master_Orders!J2:J174, "Prepaid") | J38: =COUNTIFS(Master_Orders!D2:D174, "2026-07-28", Master_Orders!K2:K174, "Delivered") | K38: =COUNTIFS(Master_Orders!D2:D174, "2026-07-28", Master_Orders!K2:K174, "RTO / Returned") | L38: =COUNTIFS(Master_Orders!D2:D174, "2026-07-28", Master_Orders!K2:K174, "Canceled") | M38: =COUNTIFS(Master_Orders!D2:D174, "2026-07-28", Master_Orders!K2:K174, "In Transit")
A39: 2026-07-29 | B39: =COUNTIF(Master_Orders!D2:D174, "2026-07-29") | C39: =COUNTIFS(Master_Orders!D2:D174, "2026-07-29", Master_Orders!J2:J174, "COD") | D39: =COUNTIFS(Master_Orders!D2:D174, "2026-07-29", Master_Orders!J2:J174, "Partial COD") | E39: =COUNTIFS(Master_Orders!D2:D174, "2026-07-29", Master_Orders!J2:J174, "Prepaid") | F39: =SUMIF(Master_Orders!D2:D174, "2026-07-29", Master_Orders!E2:E174) | G39: =SUMIFS(Master_Orders!E2:E174, Master_Orders!D2:D174, "2026-07-29", Master_Orders!J2:J174, "COD") | H39: =SUMIFS(Master_Orders!E2:E174, Master_Orders!D2:D174, "2026-07-29", Master_Orders!J2:J174, "Partial COD") | I39: =SUMIFS(Master_Orders!E2:E174, Master_Orders!D2:D174, "2026-07-29", Master_Orders!J2:J174, "Prepaid") | J39: =COUNTIFS(Master_Orders!D2:D174, "2026-07-29", Master_Orders!K2:K174, "Delivered") | K39: =COUNTIFS(Master_Orders!D2:D174, "2026-07-29", Master_Orders!K2:K174, "RTO / Returned") | L39: =COUNTIFS(Master_Orders!D2:D174, "2026-07-29", Master_Orders!K2:K174, "Canceled") | M39: =COUNTIFS(Master_Orders!D2:D174, "2026-07-29", Master_Orders!K2:K174, "In Transit")
A40: 2026-07-30 | B40: =COUNTIF(Master_Orders!D2:D174, "2026-07-30") | C40: =COUNTIFS(Master_Orders!D2:D174, "2026-07-30", Master_Orders!J2:J174, "COD") | D40: =COUNTIFS(Master_Orders!D2:D174, "2026-07-30", Master_Orders!J2:J174, "Partial COD") | E40: =COUNTIFS(Master_Orders!D2:D174, "2026-07-30", Master_Orders!J2:J174, "Prepaid") | F40: =SUMIF(Master_Orders!D2:D174, "2026-07-30", Master_Orders!E2:E174) | G40: =SUMIFS(Master_Orders!E2:E174, Master_Orders!D2:D174, "2026-07-30", Master_Orders!J2:J174, "COD") | H40: =SUMIFS(Master_Orders!E2:E174, Master_Orders!D2:D174, "2026-07-30", Master_Orders!J2:J174, "Partial COD") | I40: =SUMIFS(Master_Orders!E2:E174, Master_Orders!D2:D174, "2026-07-30", Master_Orders!J2:J174, "Prepaid") | J40: =COUNTIFS(Master_Orders!D2:D174, "2026-07-30", Master_Orders!K2:K174, "Delivered") | K40: =COUNTIFS(Master_Orders!D2:D174, "2026-07-30", Master_Orders!K2:K174, "RTO / Returned") | L40: =COUNTIFS(Master_Orders!D2:D174, "2026-07-30", Master_Orders!K2:K174, "Canceled") | M40: =COUNTIFS(Master_Orders!D2:D174, "2026-07-30", Master_Orders!K2:K174, "In Transit")
A41: Total Portfolio / All Days | B41: =SUM(B4:B40) | C41: =SUM(C4:C40) | D41: =SUM(D4:D40) | E41: =SUM(E4:E40) | F41: =SUM(F4:F40) | G41: =SUM(G4:G40) | H41: =SUM(H4:H40) | I41: =SUM(I4:I40) | ... M41: =SUM(M4:M40)

Sheet Master_Orders
A1: Order ID | B1: Shopify Order # | C1: Customer Name | D1: Order Date | E1: Total Price (Rs.) | F1: Financial Status | G1: Fulfillment Status | H1: Shopify Payment Method | I1: Shiprocket Payment Method | J1: Assigned Payment Category | K1: Standard Delivery Status | L1: Shiprocket Status | M1: Shipping City | N1: Shipping State | O1: Shipping Pincode | P1: Lineitems Ordered | Q1: Refunded Amount (Rs.) | R1: RTO / Cancellation Reason
A2: 1071 | B2: #1071 | C2: Soumya Shetty | D2: 2026-06-22 | E2: 1112 | F2: paid | G2: fulfilled | H2: 01 Cards, UPI, NB, Wallets by Razorpay | I2: prepaid | J2: Prepaid | K2: Delivered | L2: DELIVERED | M2: Bijapur | N2: Karnataka | O2: '586101 | P2: Sapphire Charm Top - M | Q2: 0 | R2: NonDeliveredDispute
A3: 1078 | B3: #1078 | C3: Gomathi Dhanapal | D3: 2026-06-24 | E3: 1112 | F3: paid | G3: fulfilled | H3: 01 Cards, UPI, NB, Wallets by Razorpay | I3: prepaid | J3: Prepaid | K3: Delivered | L3: DELIVERED | M3: Chennai | N3: Tamil Nadu | O3: '600073 | P3: Wine Blossom Top - XL | Q3: 0
A4: 1079 | B4: #1079 | C4: Mohana Mona | D4: 2026-06-24 | E4: 1032 | F4: voided | G4: unfulfilled | H4: Cash on Delivery (COD) | I4: cod | J4: COD | K4: Canceled | L4: CANCELED | M4: Dharmapuri | N4: Tamil Nadu | O4: '636705 | P4: Moss Majesty - M | Q4: 0
A5: 1080 | B5: #1080 | C5: Chandraelectro Corporation | D5: 2026-06-24 | E5: 3176 | F5: paid | G5: fulfilled | H5: 01 Cards, UPI, NB, Wallets by Razorpay | I5: prepaid | J5: Prepaid | K5: Delivered | L5: DELIVERED | M5: Madurai | N5: Tamil Nadu | O5: '625001 | P5: Teal Tempo - 2XL, Mystic Mist Red - 2XL, Rustara - XXL | Q5: 0
A6: 1081 | B6: #1081 | C6: Harshini Rajendran | D6: 2026-06-24 | E6: 1290 | F6: pending | G6: fulfilled | H6: Cash on Delivery (COD) | I6: cod | J6: COD | K6: RTO / Returned | L6: RTO DELIVERED | M6: Karaikudi | N6: Tamil Nadu | O6: '630003 | P6: Mystic Mist Red - S | Q6: 0 | R6: Customer Refused To Accept - OTP Verified
A7: 1082 | B7: #1082 | C7: Harshini Rajendran | D7: 2026-06-24 | E7: 1290 | F7: pending | G7: fulfilled | H7: Cash on Delivery (COD) | I7: cod | J7: COD | K7: RTO / Returned | L7: RTO DELIVERED | M7: Karaikudi | N7: Tamil Nadu | O7: '630003 | P7: Urban Ruby - XL | Q7: 0 | R7: Customer Refused To Accept - OTP Verified
A8: 1083 | B8: #1083 | C8: Sukanya R | D8: 2026-06-24 | E8: 2144 | F8: paid | G8: fulfilled | H8: Cash on Delivery (COD) | I8: cod | J8: COD | K8: SELF FULFILED | L8: SELF FULFILED | M8: Chennai | N8: Tamil Nadu | O8: '600095 | P8: Coral Bloom Top - M, Purple Panache - M | Q8: 0
A9: 1084 | B9: #1084 | C9: Gowri R | D9: 2026-06-25 | E9: 1112 | F9: paid | G9: fulfilled | H9: 01 Cards, UPI, NB, Wallets by Razorpay | I9: prepaid | J9: Prepaid | K9: Delivered | L9: DELIVERED | M9: Chennai | N9: Tamil Nadu | O9: '600096 | P9: Sunset Petal - XL | Q9: 0 | R9: Customer Not Responding
A10: 1085 | B10: #1085 | C10: Mohanakrishnan Devanathan | D10: 2026-06-25 | E10: 1032 | F10: paid | G10: fulfilled | H10: Cash on Delivery (COD) | I10: cod | J10: COD | K10: Delivered | L10: DELIVERED | M10: Puducherry | N10: Puducherry | O10: '605006 | P10: Purple Panache - M | Q10: 0
A11: 1086 | B11: #1086 | C11: D Keerthi | D11: 2026-06-25 | E11: 1032 | F11: paid | G11: fulfilled | H11: Cash on Delivery (COD) | I11: cod | J11: COD | K11: Delivered | L11: DELIVERED | M11: Chittoor | N11: Andhra Pradesh | O11: '517234 | P11: Bold Basil - 3XL | Q11: 0
A12: 1087 | B12: #1087 | C12: Devi Rv | D12: 2026-06-25 | E12: 1290 | F12: pending | G12: fulfilled | H12: Cash on Delivery (COD) | I12: cod | J12: COD | K12: RTO / Returned | L12: RTO DELIVERED | M12: Chennai | N12: Tamil Nadu | O12: '600110 | P12: Bold Basil - 2XL | Q12: 0 | R12: Customer not contactable
A13: 1088 | B13: #1088 | C13: Nutan Manerkar | D13: 2026-06-25 | E13: 1112 | F13: paid | G13: fulfilled | H13: 01 Cards, UPI, NB, Wallets by Razorpay | I13: prepaid | J13: Prepaid | K13: SELF FULFILED | L13: SELF FULFILED | M13: Margao | N13: Goa | O13: '403601 | P13: Wine Blossom Top - 2XL | Q13: 0
A14: 1089 | B14: #1089 | C14: Divya Divya | D14: 2026-06-25 | E14: 1290 | F14: paid | G14: fulfilled | H14: Cash on Delivery (COD) | I14: cod | J14: COD | K14: Delivered | L14: DELIVERED | M14: Kuppatti | N14: Tamil Nadu | O14: '635118 | P14: Moss Majesty - L | Q14: 0
A15: 1090 | B15: #1090 | C15: Kamal Thiyagarajan | D15: 2026-06-25 | E15: 1112 | F15: paid | G15: fulfilled | H15: Cash on Delivery (COD) | I15: cod | J15: COD | K15: Delivered | L15: DELIVERED | M15: Tirupur | N15: Tamil Nadu | O15: '641606 | P15: Vanya Bloom Top - S | Q15: 0
A16: 1091 | B16: #1091 | C16: Vijay Aadarsh Adarsh | D16: 2026-06-27 | E16: 1112 | F16: pending | G16: fulfilled | H16: Cash on Delivery (COD) | I16: cod | J16: COD | K16: RTO / Returned | L16: RTO DELIVERED | M16: Coimbatore | N16: Tamil Nadu | O16: '641107 | P16: Wine Blossom Top - XL | Q16: 0 | R16: PNA|RECEIVER NOT AVAILABLE/REACHABLE OVER PHONE
A17: 1092 | B17: #1092 | C17: Kowsalya | D17: 2026-06-27 | E17: 1290 | F17: pending | G17: fulfilled | H17: Cash on Delivery (COD) | I17: cod | J17: COD | K17: RTO / Returned | L17: RTO DELIVERED | M17: Chennai | N17: Tamil Nadu | O17: '600096 | P17: Moss Majesty - S | Q17: 0 | R17: Customer not available x Office or Residence closed
A18: 1093 | B18: #1093 | C18: Ramya Gowda | D18: 2026-06-27 | E18: 1032 | F18: pending | G18: fulfilled | H18: Cash on Delivery (COD) | I18: cod | J18: COD | K18: RTO / Returned | L18: RTO DELIVERED | M18: Bengaluru | N18: Karnataka | O18: '560091 | P18: Bold Basil - 2XL | Q18: 0 | R18: CustomerUnavailable_DeliveryAttempted
A19: 1094 | B19: #1094 | C19: Usha .R | D19: 2026-06-27 | E19: 1032 | F19: paid | G19: fulfilled | H19: 01 Cards, UPI, NB, Wallets by Razorpay | I19: prepaid | J19: Prepaid | K19: Delivered | L19: DELIVERED | M19: Hosur | N19: Tamil Nadu | O19: '635109 | P19: Dainty Dots Teal - 3XL | Q19: 0
A20: 1095 | B20: #1095 | C20: Priya Dharshini Pd | D20: 2026-06-27 | E20: 1112 | F20: paid | G20: fulfilled | H20: Cash on Delivery (COD) | I20: cod | J20: COD | K20: Delivered | L20: DELIVERED | M20: Villupuram | N20: Tamil Nadu | O20: '604204 | P20: Wine Blossom Top - 2XL | Q20: 0
A21: 1096 | B21: #1096 | C21: Indu Rekha | D21: 2026-06-27 | E21: 2224 | F21: paid | G21: fulfilled | H21: 01 Cards, UPI, NB, Wallets by Razorpay | I21: prepaid | J21: Prepaid | K21: Delivered | L21: DELIVERED | M21: Anantapur Urban | N21: Andhra Pradesh | O21: '515001 | P21: Honey Bloom Top - 3XL, Ocean Elegance Top - 3XL | Q21: 0
A22: 1097 | B22: #1097 | C22: Krishna | D22: 2026-06-27 | E22: 1112 | F22: paid | G22: fulfilled | H22: 01 Cards, UPI, NB, Wallets by Razorpay | I22: prepaid | J22: Prepaid | K22: Delivered | L22: DELIVERED | M22: Guntur | N22: Andhra Pradesh | O22: '522007 | P22: Grape Leaf Glam - M | Q22: 0 | R22: CustomerUnavailable_DeliveryAttempted
A23: 1098 | B23: #1098 | C23: B Padmapriya | D23: 2026-06-27 | E23: 1032 | F23: paid | G23: fulfilled | H23: Cash on Delivery (COD) | I23: cod | J23: COD | K23: Delivered | L23: DELIVERED | M23: Secunderabad | N23: Telangana | O23: '500017 | P23: Bold Basil - L | Q23: 0
A24: 1099 | B24: #1099 | C24: Durai Kannan | D24: 2026-06-27 | E24: 1032 | F24: paid | G24: fulfilled | H24: 01 Cards, UPI, NB, Wallets by Razorpay | I24: prepaid | J24: Prepaid | K24: Delivered | L24: DELIVERED | M24: Coimbatore | N24: Tamil Nadu | O24: '641008 | P24: Moss Majesty - L | Q24: 0
A25: 1100 | B25: #1100 | C25: Shailu Reddy | D25: 2026-06-27 | E25: 1290 | F25: paid | G25: fulfilled | H25: Cash on Delivery (COD) | I25: cod | J25: COD | K25: Delivered | L25: DELIVERED | M25: Warangal | N25: Telangana | O25: '506002 | P25: Purple Panache - 2XL | Q25: 0
A26: 1101 | B26: #1101 | C26: Apsara reddy | D26: 2026-06-27 | E26: 3176 | F26: paid | G26: fulfilled | H26: 01 Cards, UPI, NB, Wallets by Razorpay | I26: prepaid | J26: Prepaid | K26: Delivered | L26: DELIVERED | M26: Kurnool | N26: Andhra Pradesh | O26: '518003 | P26: Sunset Petal - L, Teal Tempo - L, Purple Panache - L | Q26: 0
A27: 1102 | B27: #1102 | C27: smitha AG | D27: 2026-06-27 | E27: 1032 | F27: pending | G27: fulfilled | H27: Cash on Delivery (COD) | I27: cod | J27: COD | K27: RTO / Returned | L27: RTO DELIVERED | M27: Muvattupuzha | N27: Kerala | O27: '686661 | P27: Mystic Mist Red - L | Q27: 0 | R27: Customer not available x Office or Residence closed
A28: 1103 | B28: #1103 | C28: Praveena Manoharan | D28: 2026-06-28 | E28: 1290 | F28: paid | G28: fulfilled | H28: Cash on Delivery (COD) | I28: cod | J28: COD | K28: Delivered | L28: DELIVERED | M28: Chennai | N28: Tamil Nadu | O28: '600100 | P28: Purple Panache - XL | Q28: 0
A29: 1104 | B29: #1104 | C29: Gopal Kowsi | D29: 2026-06-29 | E29: 1112 | F29: paid | G29: fulfilled | H29: Cash on Delivery (COD) | I29: cod | J29: COD | K29: Delivered | L29: DELIVERED | M29: Vanavasi | N29: Tamil Nadu | O29: '636457 | P29: Sunset Petal - XL | Q29: 0
A30: 1105 | B30: #1105 | C30: Akila Senthil | D30: 2026-06-29 | E30: 2144 | F30: pending | G30: fulfilled | H30: Cash on Delivery (COD) | I30: cod | J30: COD | K30: RTO / Returned | L30: RTO DELIVERED | M30: Salem | N30: Tamil Nadu | O30: '636005 | P30: Dainty Dots Teal - 2XL, Sunset Petal - XXL | Q30: 0 | R30: Customer Refused To Accept - OTP Verified
A31: 1107 | B31: #1107 | C31: Meghana R | D31: 2026-06-29 | E31: 2680 | F31: pending | G31: fulfilled | H31: Cash on Delivery (COD) | I31: cod | J31: COD | K31: RTO / Returned | L31: RTO DELIVERED | M31: KOLAR | N31: Karnataka | O31: '563102 | P31: Aranya Grace Anarkali Dress - XL | Q31: 0 | R31: Customer Cancelled OTP Verified
A32: 1108 | B32: #1108 | C32: Bharathi Dinesh | D32: 2026-06-29 | E32: 1032 | F32: pending | G32: fulfilled | H32: Cash on Delivery (COD) | I32: cod | J32: COD | K32: RTO / Returned | L32: RTO DELIVERED | M32: Chennai | N32: Tamil Nadu | O32: '600077 | P32: Bold Basil - 3XL | Q32: 0
A33: 1109 | B33: #1109 | C33: Anusha Anusha | D33: 2026-06-29 | E33: 1032 | F33: paid | G33: fulfilled | H33: Cash on Delivery (COD) | I33: cod | J33: COD | K33: Delivered | L33: DELIVERED | M33: Hyderbad | N33: Telangana | O33: '500086 | P33: Purple Panache - 3XL | Q33: 0
A34: 1110 | B34: #1110 | C34: Sharanyaa K | D34: 2026-06-29 | E34: 2144 | F34: paid | G34: fulfilled | H34: 01 Cards, UPI, NB, Wallets by Razorpay | I34: prepaid | J34: Prepaid | K34: Delivered | L34: DELIVERED | M34: Pondicherry | N34: Puducherry | O34: '605011 | P34: Moss Majesty - M, Sunset Petal - M | Q34: 0 | R34: CustomerUnavailable_DeliveryAttempted
A35: 1111 | B35: #1111 | C35: Jeeva Ramprabu | D35: 2026-06-30 | E35: 2784 | F35: paid | G35: fulfilled | H35: Cash on Delivery (COD) | I35: cod | J35: COD | K35: Delivered | L35: DELIVERED | M35: Paramakudi , Ramanathapuram | N35: Tamil Nadu | O35: '626707 | P35: Purple Panache - L, Karunguyil Chudidhar Set - L | Q35: 0
A36: 1112 | B36: #1112 | C36: PERIKALA VIVEKANANDA | D36: 2026-06-30 | E36: 1112 | F36: paid | G36: fulfilled | H36: 01 Cards, UPI, NB, Wallets by Razorpay | I36: prepaid | J36: Prepaid | K36: Delivered | L36: DELIVERED | M36: Tenali | N36: Andhra Pradesh | O36: '522201 | P36: Daisy Dusk Yellow - S | Q36: 0
A37: 1113 | B37: #1113 | C37: Maha Jayaraman | D37: 2026-06-30 | E37: 1032 | F37: refunded | G37: fulfilled | H37: 01 Cards, UPI, NB, Wallets by Razorpay | I37: prepaid | J37: Prepaid | K37: RTO / Returned | L37: DELIVERED | M37: Pondicherry | N37: Puducherry | O37: '605008 | P37: Dainty Dots Teal - XL | Q37: 1032 | R37: UnableToContactRecipient_DeliveryAttempted
A38: 1114 | B38: #1114 | C38: Kruthika Vignesh | D38: 2026-06-30 | E38: 1112 | F38: paid | G38: fulfilled | H38: 01 Cards, UPI, NB, Wallets by Razorpay | I38: prepaid | J38: Prepaid | K38: Delivered | L38: DELIVERED | M38: Chennai | N38: Tamil Nadu | O38: '600078 | P38: Wine Blossom Top - XL | Q38: 0
A39: 1115 | B39: #1115 | C39: Vidya Jothi | D39: 2026-07-01 | E39: 1390 | F39: paid | G39: fulfilled | H39: Cash on Delivery (COD) | I39: cod | J39: COD | K39: Delivered | L39: DELIVERED | M39: Coimbatore | N39: Tamil Nadu | O39: '641062 | P39: Daisy Dusk Yellow - XL | Q39: 0 | R39: DeliveryAttempted_UnableToContactRecipient
A40: 1117 | B40: #1117 | C40: Dr Jovin Jose | D40: 2026-07-01 | E40: 1112 | F40: paid | G40: fulfilled | H40: 01 Cards, UPI, NB, Wallets by Razorpay | I40: prepaid | J40: Prepaid | K40: Delivered | L40: DELIVERED | M40: Kanhangad | N40: Kerala | O40: '671326 | P40: Daisy Dusk Yellow - M | Q40: 0
A41: 1118 | B41: #1118 | C41: Aswathy P | D41: 2026-07-01 | E41: 1032 | F41: paid | G41: fulfilled | H41: 01 Cards, UPI, NB, Wallets by Razorpay | I41: prepaid | J41: Prepaid | K41: Delivered | L41: DELIVERED | M41: Ernakulam | N41: Kerala | O41: '682030 | P41: Urban Ruby - M | Q41: 0
A42: 1119 | B42: #1119 | C42: Vijayasri S Narendran | D42: 2026-07-02 | E42: 1890 | F42: paid | G42: fulfilled | H42: Cash on Delivery (COD) | I42: cod | J42: COD | K42: Delivered | L42: DELIVERED | M42: Avadi | N42: Tamil Nadu | O42: '600062 | P42: Blossom Taupe Chic Set - 2XL | Q42: 0
A43: 1120 | B43: #1120 | C43: nisha J | D43: 2026-07-02 | E43: 1032 | F43: refunded | G43: fulfilled | H43: 01 Cards, UPI, NB, Wallets by Razorpay | I43: prepaid | J43: Prepaid | K43: Canceled | L43: CANCELED | M43: Chengalpattu | N43: Tamil Nadu | O43: '603002 | P43: Dainty Dots Teal - 2XL | Q43: 1032
A44: 1121 | B44: #1121 | C44: Salla Mahesh | D44: 2026-07-02 | E44: 2144 | F44: paid | G44: fulfilled | H44: Cash on Delivery (COD) | I44: cod | J44: COD | K44: Delivered | L44: DELIVERED | M44: Godavarikhani | N44: Telangana | O44: '505210 | P44: Mystic Mist Red - L, Ocean Elegance Top - L | Q44: 0
A45: 1122 | B45: #1122 | C45: Suganya Suganyasridhar | D45: 2026-07-02 | E45: 2064 | F45: pending | G45: fulfilled | H45: Cash on Delivery (COD) | I45: cod | J45: COD | K45: RTO / Returned | L45: RTO DELIVERED | M45: Tiruvannamalai | N45: Tamil Nadu | O45: '606902 | P45: Bold Basil - XL, Purple Panache - XL | Q45: 0 | R45: RejectedByRecipientWithVerification_NotRequired
A46: 1123 | B46: #1123 | C46: Ujwala Gajula | D46: 2026-07-02 | E46: 2064 | F46: paid | G46: fulfilled | H46: 01 Cards, UPI, NB, Wallets by Razorpay | I46: prepaid | J46: Prepaid | K46: Delivered | L46: DELIVERED | M46: Nallagandla | N46: Telangana | O46: '500019 | P46: Moss Majesty - 2XL, Purple Panache - 2XL | Q46: 0
A47: 1124 | B47: #1124 | C47: Anusha Madhukar | D47: 2026-07-02 | E47: 1112 | F47: paid | G47: fulfilled | H47: Cash on Delivery (COD) | I47: cod | J47: COD | K47: Delivered | L47: DELIVERED | M47: Hyderabad | N47: Telangana | O47: '500035 | P47: Sunset Petal - S | Q47: 0
A48: 1125 | B48: #1125 | C48: Subha A.R | D48: 2026-07-02 | E48: 2680 | F48: paid | G48: fulfilled | H48: Cash on Delivery (COD) | I48: cod | J48: COD | K48: Delivered | L48: DELIVERED | M48: Chennai 600107 | N48: Tamil Nadu | O48: '600107 | P48: Sunset Petal - L, Teal Tempo - S | Q48: 0 | R48: Consignee unavailable
A49: 1126 | B49: #1126 | C49: SULOCHANA N | D49: 2026-07-02 | E49: 1890 | F49: paid | G49: fulfilled | H49: 01 Cards, UPI, NB, Wallets by Razorpay | I49: prepaid | J49: Prepaid | K49: Delivered | L49: DELIVERED | M49: Anantapur | N49: Andhra Pradesh | O49: '515002 | P49: Rosy Mist - M | Q49: 0
A50: 1127 | B50: #1127 | C50: Rajani Reddy | D50: 2026-07-02 | E50: 1112 | F50: paid | G50: fulfilled | H50: Cash on Delivery (COD) | I50: cod | J50: COD | K50: Delivered | L50: DELIVERED | M50: Bengaluru | N50: Karnataka | O50: '560076 | P50: Sunset Petal - M | Q50: 0
A51: 1128 | B51: #1128 | C51: Shanmuga priya Priya | D51: 2026-07-02 | E51: 1032 | F51: paid | G51: fulfilled | H51: Cash on Delivery (COD) | I51: cod | J51: COD | K51: Delivered | L51: DELIVERED | M51: Vellore | N51: Tamil Nadu | O51: '632009 | P51: Moss Majesty - M | Q51: 0
A52: 1129 | B52: #1129 | C52: Mamillapalli Sivakumari | D52: 2026-07-02 | E52: 1112 | F52: paid | G52: fulfilled | H52: Cash on Delivery (COD) | I52: cod | J52: COD | K52: Delivered | L52: DELIVERED | M52: Thiruvallur | N52: Tamil Nadu | O52: '601204 | P52: Daisy Dusk Yellow - L | Q52: 0 | R52: UnableToContactRecipient_DeliveryAttempted
A53: 1130 | B53: #1130 | C53: Sudha G | D53: 2026-07-02 | E53: 3336 | F53: paid | G53: fulfilled | H53: 01 Cards, UPI, NB, Wallets by Razorpay | I53: prepaid | J53: Prepaid | K53: Delivered | L53: DELIVERED | M53: Karur | N53: Tamil Nadu | O53: '639001 | P53: Wine Blossom Top - XL, Dahlia Dusk - XL, Daisy Dusk Yellow - XL | Q53: 0
A54: 1131 | B54: #1131 | C54: Sindhuri Kalidindi | D54: 2026-07-03 | E54: 1032 | F54: paid | G54: fulfilled | H54: Cash on Delivery (COD) | I54: cod | J54: COD | K54: Delivered | L54: DELIVERED | M54: Hoshiarpur | N54: Punjab | O54: '146024 | P54: Plum Pinstripe - 2XL | Q54: 0
A55: 1132 | B55: #1132 | C55: Sudha Manikandan | D55: 2026-07-03 | E55: 2144 | F55: paid | G55: fulfilled | H55: Cash on Delivery (COD) | I55: cod | J55: COD | K55: Delivered | L55: DELIVERED | M55: Madurai | N55: Tamil Nadu | O55: '625016 | P55: Mystic Mist Red - XL, Daisy Dusk Yellow - XL | Q55: 0 | R55: UnableToContactRecipient_DeliveryAttempted
A56: 1133 | B56: #1133 | C56: Deva E | D56: 2026-07-03 | E56: 3096 | F56: paid | G56: fulfilled | H56: Cash on Delivery (COD) | I56: cod | J56: COD | K56: Delivered | L56: DELIVERED | M56: Chennai | N56: Tamil Nadu | O56: '600056 | P56: Plum Pinstripe - 3XL, Purple Panache - 3XL, Bold Basil - 3XL | Q56: 0 | R56: Customer not available x Office or Residence closed
A57: 1134 | B57: #1134 | C57: Kaylash Pinkky | D57: 2026-07-03 | E57: 1131 | F57: pending | G57: fulfilled | H57: Cash on Delivery (COD) | I57: cod | J57: COD | K57: RTO / Returned | L57: RTO DELIVERED | M57: Secunderabad | N57: Telangana | O57: '500010 | P57: Purple Panache - L | Q57: 0 | R57: OTP verified cancellation
A58: 1135 | B58: #1135 | C58: ANUSHA Bekkanti | D58: 2026-07-03 | E58: 1112 | F58: paid | G58: fulfilled | H58: 01 Cards, UPI, NB, Wallets by Razorpay | I58: prepaid | J58: Prepaid | K58: Delivered | L58: DELIVERED | M58: Harlur Bengaluru | N58: Karnataka | O58: '560102 | P58: Wine Blossom Top - XL | Q58: 0
A59: 1136 | B59: #1136 | C59: Bala Murali | D59: 2026-07-03 | E59: 1290 | F59: paid | G59: fulfilled | H59: 01 Cards, UPI, NB, Wallets by Razorpay | I59: prepaid | J59: Prepaid | K59: Delivered | L59: DELIVERED | M59: Paramakudi , Ramanathapuram District | N59: Tamil Nadu | O59: '623707 | P59: Bold Basil - 2XL | Q59: 0
A60: 1137 | B60: #1137 | C60: Sasi Gouru | D60: 2026-07-04 | E60: 1211 | F60: paid | G60: fulfilled | H60: Cash on Delivery (COD) | I60: cod | J60: COD | K60: Delivered | L60: DELIVERED | M60: Hyderabad | N60: Telangana | O60: '500090 | P60: Daisy Dusk Yellow - L | Q60: 0
A61: 1138 | B61: #1138 | C61: Preeti Niranjan | D61: 2026-07-04 | E61: 1211 | F61: paid | G61: fulfilled | H61: Cash on Delivery (COD) | I61: cod | J61: COD | K61: Delivered | L61: DELIVERED | M61: Karwar Uttar kannada | N61: Karnataka | O61: '581400 | P61: Wine Blossom Top - S | Q61: 0
A62: 1139 | B62: #1139 | C62: Keerthana C | D62: 2026-07-04 | E62: 1112 | F62: paid | G62: fulfilled | H62: 01 Cards, UPI, NB, Wallets by Razorpay | I62: prepaid | J62: Prepaid | K62: Delivered | L62: DELIVERED | M62: Chennai | N62: Tamil Nadu | O62: '600091 | P62: Daisy Dusk Yellow - XL | Q62: 0
A63: 1141 | B63: #1141 | C63: priya kathiravan | D63: 2026-07-04 | E63: 1211 | F63: paid | G63: fulfilled | H63: Cash on Delivery (COD) | I63: cod | J63: COD | K63: Delivered | L63: DELIVERED | M63: Sathyamoorthy Nagar | N63: Tamil Nadu | O63: '614804 | P63: Sunset Petal - S | Q63: 0
A64: 1142 | B64: #1142 | C64: Sunanda P | D64: 2026-07-04 | E64: 2779 | F64: paid | G64: fulfilled | H64: Cash on Delivery (COD) | I64: cod | J64: COD | K64: Delivered | L64: DELIVERED | M64: Bengaluru | N64: Karnataka | O64: '560011 | P64: Azure Bloom Top - XXL, Plum Pinstripe - 2XL | Q64: 0
A65: 1143 | B65: #1143 | C65: Nandhini V | D65: 2026-07-04 | E65: 1112 | F65: paid | G65: fulfilled | H65: 01 Cards, UPI, NB, Wallets by Razorpay | I65: prepaid | J65: Prepaid | K65: Delivered | L65: DELIVERED | M65: Kanchipuram | N65: Tamil Nadu | O65: '631601 | P65: Wine Blossom Top - M | Q65: 0
A66: 1144 | B66: #1144 | C66: Deepak Raj | D66: 2026-07-05 | E66: 1211 | F66: paid | G66: fulfilled | H66: Cash on Delivery (COD) | I66: cod | J66: COD | K66: Delivered | L66: DELIVERED | M66: Chennai | N66: Tamil Nadu | O66: '600045 | P66: Rose Charm Top - S | Q66: 0
A67: 1146 | B67: #1146 | C67: Astin | D67: 2026-07-05 | E67: 2243 | F67: paid | G67: fulfilled | H67: Cash on Delivery (COD) | I67: cod | J67: COD | K67: Delivered | L67: DELIVERED | M67: Thanjavur | N67: Tamil Nadu | O67: '613007 | P67: Geometric Glam - L, Purple Panache - L | Q67: 0
A68: 1147 | B68: #1147 | C68: vishalini priya | D68: 2026-07-05 | E68: 2780 | F68: paid | G68: fulfilled | H68: 01 Cards, UPI, NB, Wallets by Razorpay | I68: prepaid | J68: Prepaid | K68: Delivered | L68: DELIVERED | M68: Kanchipuram | N68: Tamil Nadu | O68: '600117 | P68: Geometric Glam - 3XL, Daisy Dusk Yellow - 3XL | Q68: 0
A69: 1148 | B69: #1148 | C69: Amirtha Varshini | D69: 2026-07-06 | E69: 1131 | F69: pending | G69: fulfilled | H69: Cash on Delivery (COD) | I69: cod | J69: COD | K69: RTO / Returned | L69: RTO DELIVERED | M69: Tirunelveli | N69: Tamil Nadu | O69: '627007 | P69: Plum Pinstripe - L | Q69: 0 | R69: OTP verified cancellation
A70: 1149 | B70: #1149 | C70: Princy Raj | D70: 2026-07-06 | E70: 1290 | F70: paid | G70: fulfilled | H70: 01 Cards, UPI, NB, Wallets by Razorpay | I70: prepaid | J70: Prepaid | K70: Delivered | L70: DELIVERED | M70: Thanjavur | N70: Tamil Nadu | O70: '613204 | P70: Purple Panache - L | Q70: 0
A71: 1150 | B71: #1150 | C71: Kavitha Sharma | D71: 2026-07-06 | E71: 1211 | F71: paid | G71: fulfilled | H71: Cash on Delivery (COD) | I71: cod | J71: COD | K71: Delivered | L71: DELIVERED | M71: Vizianagaram District | N71: Andhra Pradesh | O71: '535558 | P71: Sunset Petal - XL | Q71: 0
A72: 1151 | B72: #1151 | C72: Subha Chandrasekar | D72: 2026-07-06 | E72: 1390 | F72: paid | G72: fulfilled | H72: 01 Cards, UPI, NB, Wallets by Razorpay | I72: prepaid | J72: Prepaid | K72: Delivered | L72: DELIVERED | M72: Chennai | N72: Tamil Nadu | O72: '600083 | P72: Cocoa Elegance Top - XL | Q72: 0
A73: 1152 | B73: #1152 | C73: Pooja Akiwate | D73: 2026-07-07 | E73: 1211 | F73: voided | G73: unfulfilled | H73: Cash on Delivery (COD) | I73: prepaid | J73: COD | K73: Canceled | L73: CANCELED | M73: Shirol | N73: Maharashtra | O73: '416122 | P73: Daisy Dusk Yellow - XXL | Q73: 0
A74: 1153 | B74: #1153 | C74: Chellakumar Duraisamy | D74: 2026-07-07 | E74: 1390 | F74: paid | G74: fulfilled | H74: 01 Cards, UPI, NB, Wallets by Razorpay | I74: prepaid | J74: Prepaid | K74: Delivered | L74: DELIVERED | M74: Ponnamaravathy | N74: Tamil Nadu | O74: '622408 | P74: Daisy Dusk Yellow - S | Q74: 0
A75: 1154 | B75: #1154 | C75: Sagar reddy | D75: 2026-07-07 | E75: 2144 | F75: refunded | G75: fulfilled | H75: 01 Cards, UPI, NB, Wallets by Razorpay | I75: prepaid | J75: Prepaid | K75: RTO / Returned | L75: DELIVERED | M75: Banglore | N75: Karnataka | O75: '560076 | P75: Ameera Purple Royale Anarkali Dress - M | Q75: 2144
A76: 1155 | B76: #1155 | C76: Surekha Aketi | D76: 2026-07-07 | E76: 1112 | F76: paid | G76: fulfilled | H76: 01 Cards, UPI, NB, Wallets by Razorpay | I76: prepaid | J76: Prepaid | K76: Delivered | L76: DELIVERED | M76: Padur | N76: Tamil Nadu | O76: '603103 | P76: Sunset Petal - XXL | Q76: 0
A77: 1156 | B77: #1156 | C77: Nandhini Manikandan | D77: 2026-07-07 | E77: 1211 | F77: paid | G77: fulfilled | H77: Cash on Delivery (COD) | I77: cod | J77: COD | K77: Delivered | L77: DELIVERED | M77: Coimbatore | N77: Tamil Nadu | O77: '641006 | P77: Lime Regalia Top - XXL | Q77: 0
A78: 1157 | B78: #1157 | C78: Benjamin sunil | D78: 2026-07-08 | E78: 1112 | F78: paid | G78: fulfilled | H78: 01 Cards, UPI, NB, Wallets by Razorpay | I78: prepaid | J78: Prepaid | K78: Delivered | L78: DELIVERED | M78: Thrissur | N78: Kerala | O78: '680751 | P78: Sapphire Charm Top - L | Q78: 0
A79: 1158 | B79: #1158 | C79: Edara kavitha Kavitha | D79: 2026-07-08 | E79: 1489 | F79: voided | G79: unfulfilled | H79: Cash on Delivery (COD) | I79: prepaid | J79: COD | K79: Canceled | L79: CANCELED | M79: Ongole | N79: Andhra Pradesh | O79: '523001 | P79: Daisy Dusk Yellow - L | Q79: 0
A80: 1159 | B80: #1159 | C80: SOBANA SHYAM | D80: 2026-07-08 | E80: 2224 | F80: paid | G80: fulfilled | H80: 01 Cards, UPI, NB, Wallets by Razorpay | I80: prepaid | J80: Prepaid | K80: Delivered | L80: DELIVERED | M80: Thoothukudi | N80: Tamil Nadu | O80: '628008 | P80: Geometric Glam - 3XL, Royal Teal Top - 3XL | Q80: 0 | R80: DeliveryAttempted_UnableToContactRecipient
A81: 1160 | B81: #1160 | C81: NANDHINI V | D81: 2026-07-09 | E81: 1112 | F81: paid | G81: fulfilled | H81: 01 Cards, UPI, NB, Wallets by Razorpay | I81: prepaid | J81: Prepaid | K81: Delivered | L81: DELIVERED | M81: Salem | N81: Tamil Nadu | O81: '636005 | P81: Daisy Dusk Yellow - XXL | Q81: 0
A82: 1161 | B82: #1161 | C82: Sumi Aranga | D82: 2026-07-09 | E82: 1112 | F82: paid | G82: fulfilled | H82: 01 Cards, UPI, NB, Wallets by Razorpay | I82: prepaid | J82: Prepaid | K82: Delivered | L82: DELIVERED | M82: Coimbatore | N82: Tamil Nadu | O82: '641018 | P82: Peach Elegance Top - L | Q82: 0 | R82: Consignee unavailable
A83: 1162 | B83: #1162 | C83: Pavithra Sakthivel | D83: 2026-07-09 | E83: 1112 | F83: paid | G83: fulfilled | H83: 01 Cards, UPI, NB, Wallets by Razorpay | I83: prepaid | J83: Prepaid | K83: Delivered | L83: DELIVERED | M83: Tiruchirapalli | N83: Tamil Nadu | O83: '620007 | P83: Sunset Petal - XL | Q83: 0
A84: 1163 | B84: #1163 | C84: Raja M | D84: 2026-07-09 | E84: 1112 | F84: paid | G84: fulfilled | H84: 01 Cards, UPI, NB, Wallets by Razorpay | I84: prepaid | J84: Prepaid | K84: Delivered | L84: DELIVERED | M84: Gummidipoondi | N84: Tamil Nadu | O84: '601201 | P84: Royal Rosa - XXL | Q84: 0 | R84: Consignee unavailable
A85: 1164 | B85: #1164 | C85: Radha K | D85: 2026-07-09 | E85: 2323 | F85: paid | G85: partial | H85: Cash on Delivery (COD) | I85: cod | J85: COD | K85: Delivered | L85: DELIVERED | M85: Chennai | N85: Tamil Nadu | O85: '600077 | P85: Sunset Petal - L, Sunset Petal - XL | Q85: 0
A86: 1165 | B86: #1165 | C86: Raj Dasmati Gagrai | D86: 2026-07-09 | E86: 3256 | F86: paid | G86: fulfilled | H86: 01 Cards, UPI, NB, Wallets by Razorpay | I86: prepaid | J86: Prepaid | K86: Delivered | L86: DELIVERED | M86: Chaibasa | N86: Jharkhand | O86: '833201 | P86: Honey Bloom Top - 3XL, Plum Pinstripe - 2XL, Daisy Dusk Yellow - XXL | Q86: 0
A87: 1166 | B87: #1166 | C87: R.Radha Sakthi | D87: 2026-07-09 | E87: 1032 | F87: paid | G87: fulfilled | H87: 01 Cards, UPI, NB, Wallets by Razorpay | I87: prepaid | J87: Prepaid | K87: Delivered | L87: DELIVERED | M87: Salem | N87: Tamil Nadu | O87: '636115 | P87: Plum Pinstripe - XL | Q87: 0
A88: 1167 | B88: #1167 | C88: Nirosha Koppu | D88: 2026-07-10 | E88: 1131 | F88: paid | G88: fulfilled | H88: Cash on Delivery (COD) | I88: cod | J88: COD | K88: Delivered | L88: DELIVERED | M88: Mancherial | N88: Telangana | O88: '504208 | P88: Plum Pinstripe - 2XL | Q88: 0 | R88: Customer not contactable
A89: 1168 | B89: #1168 | C89: Shyla Niranjan | D89: 2026-07-10 | E89: 2779 | F89: voided | G89: unfulfilled | H89: Cash on Delivery (COD) | I89: cod | J89: COD | K89: Canceled | L89: CANCELED | M89: Arasinakunte | N89: Karnataka | O89: '562123 | P89: Neelara Zari Anarkali Dress - L | Q89: 0
A90: 1169 | B90: #1169 | C90: ashok L | D90: 2026-07-10 | E90: 1752 | F90: paid | G90: fulfilled | H90: 01 Cards, UPI, NB, Wallets by Razorpay | I90: prepaid | J90: Prepaid | K90: Delivered | L90: DELIVERED | M90: Chennau | N90: Tamil Nadu | O90: '600097 | P90: Noorza Crimson Grace Anarkali Dress - XL | Q90: 0
A91: 1170 | B91: #1170 | C91: T.sridevi Sridevi | D91: 2026-07-10 | E91: 3024 | F91: paid | G91: fulfilled | H91: 01 Cards, UPI, NB, Wallets by Razorpay | I91: prepaid | J91: Prepaid | K91: Delivered | L91: DELIVERED | M91: Hyderabad | N91: Telangana | O91: '500038 | P91: Purple Panache - M, Charcoal Zari Grace Chudidhar Set - M | Q91: 0
A92: 1171 | B92: #1171 | C92: Mani Chandran | D92: 2026-07-10 | E92: 10879 | F92: voided | G92: unfulfilled | H92: Cash on Delivery (COD) | I92: prepaid | J92: COD | K92: Canceled | L92: CANCELED | M92: jbjj | N92: Tamil Nadu | O92: '627105 | P92: The Bottle Green Lucknowi Chikankari Lehenga Set | Q92: 0
A93: 1172 | B93: #1172 | C93: Ushasri Babu | D93: 2026-07-10 | E93: 1032 | F93: paid | G93: fulfilled | H93: 01 Cards, UPI, NB, Wallets by Razorpay | I93: prepaid | J93: Prepaid | K93: Delivered | L93: DELIVERED | M93: Chennai | N93: Tamil Nadu | O93: '600042 | P93: Plum Pinstripe - 2XL | Q93: 0
A94: 1173 | B94: #1173 | C94: Rashmi Rashu | D94: 2026-07-10 | E94: 1290 | F94: paid | G94: fulfilled | H94: 01 Cards, UPI, NB, Wallets by Razorpay | I94: prepaid | J94: Prepaid | K94: Delivered | L94: DELIVERED | M94: Sullia | N94: Karnataka | O94: '574248 | P94: Plum Pinstripe - M | Q94: 0
A95: 1174 | B95: #1174 | C95: Sunanda P | D95: 2026-07-10 | E95: 1390 | F95: paid | G95: fulfilled | H95: 01 Cards, UPI, NB, Wallets by Razorpay | I95: prepaid | J95: Prepaid | K95: Delivered | L95: DELIVERED | M95: Bengaluru | N95: Karnataka | O95: '560041 | P95: Scarlet Soul - XXL | Q95: 0
A96: 1175 | B96: #1175 | C96: N Venkata Ramani | D96: 2026-07-10 | E96: 1112 | F96: paid | G96: fulfilled | H96: 01 Cards, UPI, NB, Wallets by Razorpay | I96: prepaid | J96: Prepaid | K96: Delivered | L96: DELIVERED | M96: Vijayawada | N96: Andhra Pradesh | O96: '520008 | P96: Geometric Glam - S | Q96: 0
A97: 1176 | B97: #1176 | C97: Manju | D97: 2026-07-10 | E97: 1112 | F97: paid | G97: fulfilled | H97: 01 Cards, UPI, NB, Wallets by Razorpay | I97: prepaid | J97: Prepaid | K97: Delivered | L97: DELIVERED | M97: Thiruvananthapuram | N97: Kerala | O97: '695009 | P97: Mauve Magnolia - XXL | Q97: 0
A98: 1177 | B98: #1177 | C98: Senthuri kumar | D98: 2026-07-11 | E98: 1112 | F98: paid | G98: fulfilled | H98: 01 Cards, UPI, NB, Wallets by Razorpay | I98: prepaid | J98: Prepaid | K98: Delivered | L98: DELIVERED | M98: Chennai | N98: Tamil Nadu | O98: '600091 | P98: Copper Bloom Top - XL | Q98: 0
A99: 1178 | B99: #1178 | C99: Gowsalya devi Sakthivel | D99: 2026-07-11 | E99: 1112 | F99: paid | G99: fulfilled | H99: 01 Cards, UPI, NB, Wallets by Razorpay | I99: prepaid | J99: Prepaid | K99: Delivered | L99: DELIVERED | M99: Chennai | N99: Tamil Nadu | O99: '600100 | P99: Daisy Dusk Yellow - XXL | Q99: 0
A100: 1179 | B100: #1179 | C100: Annie Sundararaj | D100: 2026-07-11 | E100: 2552 | F100: paid | G100: fulfilled | H100: 01 Cards, UPI, NB, Wallets by Razorpay | I100: prepaid | J100: Prepaid | K100: Delivered | L100: DELIVERED | M100: Chennai | N100: Tamil Nadu | O100: '600010 | P100: Raven Raaga Anarkali Dress - M | Q100: 0
...
